Workbook

Sheet Leia-me
A1: ESTUDO DE VIABILIDADE — KITS DE CAMISETAS BÁSICAS EM MARKETPLACES
A2: Modelo financeiro · Roberto Monte Fusco · Revisão 02 · Edição Blumenau · outubro de 2026
A4: COMO USAR
A5: Passo 1 | B5: Na aba "Ficha de Custo", troque os números AZUIS pelos custos reais da fábrica (malha, facção, aviamentos, embalagem). Todo o resto recalcula.
A6: Passo 2 | B6: Na aba "Premissas", escolha a linha e o tamanho do kit (listas nas células amarelas) e o preço. A "Calculadora" mostra a margem nos quatro canais.
A7: Passo 3 | B7: A aba "Kits 1-3-5-10" mostra, para as 12 combinações de linha e kit, o menor preço com 15% de margem em cada canal e o preço de prateleira sugerido. A conta completa está em "Kits calculo".
A8: Passo 4 | B8: A aba "Tabela de Precos" traz os preços de lançamento propostos; troque um preço e veja a margem de cada canal. "Projecao" projeta 12 meses do kit 3.
A9: Passo 5 | B9: "Benchmark" guarda os 34 preços reais de setembro de 2026 e o Top 10. "Cores" e "Grade de Medidas" calculam o lote de lançamento por cor e tamanho.
A11: LEGENDA DE CORES
A12: Azul | B12: Você edita. É um dado de entrada ou uma premissa.
A13: Preto | B13: Fórmula. Não edite: o modelo se quebra.
A14: Verde | B14: Referência a outra aba desta planilha.
A15: Fundo amarelo | B15: Premissa crítica: um erro aqui distorce todo o resultado.
A16: Fundo verde-claro | B16: Na aba "Frete 2026": valor publicado pelo Mercado Livre. As demais células da tabela são interpolação.
A18: O QUE ESTE MODELO RESPONDE
A19: Margem de contribuição | B19: O que sobra de cada kit depois de CMV (peças + embalagem do kit), comissão, taxa fixa, frete, mídia, imposto e provisão de devolução, antes dos custos fixos.
A20: Piso de 15% | B20: O menor preço, em cada canal, que ainda deixa a margem mínima definida em Premissas!B18, respeitando as faixas de preço de cada plataforma.
A21: Preço sugerido | B21: O próximo preço terminado em 4,90 ou 9,90 acima do piso que mantém a margem mínima.
A22: Custo-alvo | B22: Até quanto a peça pode custar para cada kit empatar com o concorrente de referência e ainda deixar 15%.
A23: Lote de lançamento | B23: 1.200 kits de 3 distribuídos por cor e tamanho, a partir da composição dos kits e da grade de produção.
A24: Equilíbrio e ROAS | B24: Kits por mês para cobrir o custo fixo e o retorno mínimo de mídia para a loja própria não dar prejuízo.
A26: O QUE ELE NÃO RESPONDE
A27: Não é consultoria fiscal | B27: As alíquotas do Simples Nacional são as tabelas públicas de 2026. O enquadramento do CNAE e a decisão sobre IBS e CBS (prazo de cancelamento em 30/11/2026) são do contador.
A28: Não prevê demanda | B28: Os volumes da aba Projecao são premissas de rampa típica, não previsão. Substitua por dados de Nubimetrics e Kalodata.
A29: Custos de fabricação | B29: A Ficha de Custo traz estimativas de mercado calibradas por consumo de malha e preços de atacado de 2026. Não são os custos da fábrica.
A30: Frete do Mercado Livre | B30: Cinco valores da tabela de reputação verde são publicados; os demais foram interpolados. Confira no simulador de custos do painel do vendedor.
A32: O QUE MUDOU DA REV. 01 (AGOSTO) PARA A REV. 02 (OUTUBRO)
B33: • Kits de 1, 3, 5 e 10 peças nas três linhas, com piso de 15% e preço sugerido em cada canal (abas Kits 1-3-5-10 e Kits calculo).
B34: • Embalagem separada: a peça leva só a embalagem individual; cada kit tem sua embalagem de envio e seu peso. Custo da Essencial: R$ 22,06 → R$ 20,52 por peça + embalagem do kit.
B35: • Frete do Mercado Livre pela tabela de reputação verde de 2026, por peso do pacote e faixa de preço (aba Frete 2026), no lugar de R$ 19 fixos.
B36: • Novas abas: Tabela de Precos, Benchmark (34 preços reais e Top 10), Cores (lote por cor e tamanho) e Grade de Medidas.
B37: • Preços terminados em ,90: o kit 3 passa de R$ 169 para R$ 169,90. Projeção e investimento recalculados.

Sheet Premissas
A1: PREMISSAS DO MODELO
A2: Edite apenas as células AZUIS. As amarelas são as que mais mexem no resultado. Ao abrir: Kit 3 da linha Essencial a R$ 169,90.
A4: PRODUTO — KIT EM SIMULAÇÃO NA CALCULADORA
A5: Linha de produto | B5: Essencial | C5: Escolha na lista: Popular, Essencial ou Fibra Longa. Custo, embalagem e peso vêm da Ficha de Custo.
A6: Peças por kit | B6: 3 | C6: Escolha na lista: 1, 3, 5 ou 10.
A7: Índice da linha (1 a 3) | B7: =MATCH(B5,'Ficha de Custo'!$B$4:$D$4,0) -> 2
A8: Custo real por peça (opcional) | C8: Deixe em branco para usar a Ficha de Custo. Preencha com o custo real da fábrica para simular.
A9: Custo por peça aplicado | B9: =IF(ISNUMBER(B8),B8,INDEX('Ficha de Custo'!$B$14:$D$14,B7)) -> 20.52
A10: Embalagem do kit (R$ por pedido) | B10: =IFERROR(INDEX('Ficha de Custo'!$B$18:$D$21,MATCH(B6,'Ficha de Custo'!$A$18:$A$21,0),B7),INDEX('Ficha de Custo'!$B$18:$D$21,MATCH(B6,'Ficha de Custo'!$A$18:$A$21,1),B7)) -> 4.5 | C10: Para kits fora de 1, 3, 5 e 10, usa a embalagem do tamanho padrão imediatamente menor.
A11: Peso da peça (kg) | B11: =INDEX('Ficha de Custo'!$B$15:$D$15,B7) -> 0.2
A12: Peso da embalagem do kit (kg) | B12: =IFERROR(INDEX('Ficha de Custo'!$B$24:$B$27,MATCH(B6,'Ficha de Custo'!$A$24:$A$27,0)),INDEX('Ficha de Custo'!$B$24:$B$27,MATCH(B6,'Ficha de Custo'!$A$24:$A$27,1))) -> 0.08
A13: Peso do pacote (kg) | B13: =ROUND(B6*B11+B12,2) -> 0.68
A14: Faixa de peso (1 = até 0,3 kg … 6 = 2 a 3 kg) | B14: =MATCH(B13-0.0000001,'Frete 2026'!$A$6:$A$11,1) -> 3
A15: Preço de venda do kit | B15: 169.9 | C15: Preço ao consumidor, o mesmo nos quatro canais. Para a tabela por canal, use a aba Tabela de Precos.
A16: CMV do kit | B16: =B9*B6+B10 -> 66.06 | C16: Peças × custo por peça + embalagem do kit.
A17: Preço por peça ao consumidor | B17: =B15/B6 -> 56.633333 | C17: Referências de setembro de 2026: Hering Camiseta Brasil R$ 49,99; Malwee kit 3 R$ 52,33 por peça; Zaroc kit 5 R$ 24,60 por peça.
A18: Margem de contribuição mínima exigida | B18: 0.15 | C18: Abaixo de 15% em moda a operação não sustenta estrutura própria.
A20: COMUM A TODOS OS CANAIS
A21: Simples Nacional — alíquota efetiva | B21: 0.045 | C21: Anexo II (Indústria), 1ª faixa, até R$ 180 mil de receita em 12 meses. Anexo I (Comércio) = 4,0%. Validar com o contador.
A22: Provisão de devolução | B22: 0.05 | C22: Perda líquida com devolução (frete reverso e peça de 2ª). Devolução em moda online: 30% a 40% dos pedidos, mais da metade por tamanho.
A23: Custo fixo mensal da operação | B23: 13000 | C23: Equipe, sistemas, contabilidade, conteúdo. Não inclui pró-labore.
A25: MERCADO LIVRE
A26: Comissão — categoria Moda | B26: 0.14 | C26: Clássico = 14%. Premium = 19% (12x sem juros e mais exposição).
A27: ACOS — Product Ads | B27: 0.06 | C27: Percentual da receita gasto em mídia dentro do ML.
A28: Frete manual (opcional) | C28: Em branco = tabela da aba Frete 2026 pelo peso e pela faixa de preço. Preencha com o valor do seu painel.
A29: Frete aplicado (preço a partir de R$ 79) | B29: =IF(B15<79,0,IF(ISNUMBER(B28),B28,INDEX('Frete 2026'!$C$6:$G$11,B14,MATCH(B15,'Frete 2026'!$C$5:$G$5,1)))) -> 20
A30: Custo logístico manual (opcional) | C30: Em branco = coluna B da aba Frete 2026.
A31: Custo logístico aplicado (preço abaixo de R$ 79) | B31: =IF(B15>=79,0,IF(ISNUMBER(B30),B30,INDEX('Frete 2026'!$B$6:$B$11,B14))) -> 0
A33: SHOPEE
A34: Frete pago pelo vendedor | B34: 0 | C34: Zero no fluxo padrão: desde março de 2026 o Programa de Frete Grátis é obrigatório e está embutido na comissão. Use para a diferença acima do subsídio em pacotes pesados.
A35: ACOS — Shopee Ads | B35: 0.08
A36: Campanha de destaque — adicional | B36: 0 | C36: Use 2,50% se participar de campanha de destaque; 0% caso contrário.
A38: TIKTOK SHOP
A39: Programa de frete grátis | B39: 0.06 | C39: 6% sobre o valor do produto. Inalterado na revisão de 15/07/2026.
A40: Comissão de afiliado | B40: 0.15 | C40: Definida por SKU. Em roupas a prática é de 10% a 20%.
A41: ACOS — anúncios | B41: 0.05
A43: LOJA PRÓPRIA
A44: Gateway de pagamento | B44: 0.0499 | C44: Crédito à vista. Débito costuma ficar perto de 3,99% e parcelado perto de 5,99%.
A45: Gateway — taxa fixa por pedido | B45: 0.39
A46: Frete manual (opcional) | C46: Em branco = coluna H da aba Frete 2026 pelo peso do pacote.
A47: Frete aplicado | B47: =IF(ISNUMBER(B46),B46,INDEX('Frete 2026'!$H$6:$H$11,B14)) -> 19
A48: Plataforma e apps por pedido | B48: 1.57 | C48: Mensalidade da plataforma e dos apps rateada pelo volume. Ex.: R$ 314 por mês ÷ 200 pedidos.
A49: ROAS da mídia | B49: 3 | C49: Receita ÷ verba. A mediana de e-commerce em Meta Ads é 1,93×.

Sheet Ficha de Custo
A1: FICHA TÉCNICA DE CUSTO — TRÊS LINHAS DE PRODUTO
A2: Estimativas de mercado calibradas por consumo de malha e preços de atacado de 2026. SUBSTITUA os números azuis pelos da fábrica.
A4: Componente | B4: Popular | C4: Essencial | D4: Fibra Longa | E4: Observação
A5: Composição | B5: PV 67/33 ou cardado · 140 g/m² | C5: 100% algodão penteado 30.1 · 180 g/m² | D5: Pima ou egípcio com laudo · 165 g/m²
A6: Consumo de malha (kg por peça) | B6: 0.175 | C6: 0.215 | D6: 0.2 | E6: Peso da peça acabada mais cerca de 10% de perda de encaixe, na média dos tamanhos M e G. A grade real consome 2,5% a mais (aba Grade de Medidas).
A7: Preço da malha (R$ por kg) | B7: 27 | C7: 48 | D7: 88 | E7: Atacado 2026 (Itajaí e Brusque/SC, Goiânia/GO, Fortaleza/CE). É a variável de maior impacto no custo: confirme com o fornecedor.
A8: Malha | B8: =B6*B7 -> 4.725 | C8: =C6*C7 -> 10.32 | D8: =D6*D7 -> 17.6 | E8: Consumo × preço por quilo.
A9: Gola, ribana e aviamentos | B9: 0.9 | C9: 1.8 | D9: 2.6 | E9: Na Essencial inclui etiqueta tecida.
A10: Facção · corte, costura e acabamento | B10: 4.2 | C10: 7.2 | D10: 9.5 | E10: Se a fábrica tem capacidade ociosa, o custo marginal real é menor. É a pergunta que decide os kits de 5 e 10.
A11: Embalagem individual | B11: 0.3 | C11: 0.6 | D11: 1.2 | E11: Saco e tag (Popular); saco, tag e selo de gramatura (Essencial); papel de seda e tag (Fibra Longa). A embalagem do kit fica no pedido, abaixo.
A12: Perdas e 2ª qualidade (%) | B12: 0.03 | C12: 0.03 | D12: 0.03 | E12: Aplicado sobre a soma dos componentes.
A13: Perdas e 2ª qualidade (R$) | B13: =SUM(B8:B11)*B12 -> 0.30375 | C13: =SUM(C8:C11)*C12 -> 0.5976 | D13: =SUM(D8:D11)*D12 -> 0.927
A14: CUSTO TOTAL POR PEÇA | B14: =ROUND(SUM(B8:B11)+B13,2) -> 10.43 | C14: =ROUND(SUM(C8:C11)+C13,2) -> 20.52 | D14: =ROUND(SUM(D8:D11)+D13,2) -> 31.83 | E14: Arredondado ao centavo: é o valor usado em todo o modelo e na página.
A15: Peso da peça acabada (kg) | B15: 0.16 | C15: 0.2 | D15: 0.19 | E15: Define a faixa de frete do pacote.
A17: EMBALAGEM DO KIT (R$ POR PEDIDO)
A18: 1 | B18: 0.5 | C18: 1.5 | D18: 2.9 | E18: Envelope plástico (Popular) · envelope na avulsa e caixa de papelão com cinta nos kits (Essencial) · caixa rígida (Fibra Longa).
A19: 3 | B19: 0.9 | C19: 4.5 | D19: 7
A20: 5 | B20: 1.1 | C20: 5.5 | D20: 9
A21: 10 | B21: 1.6 | C21: 7.5 | D21: 12
A23: PESO DA EMBALAGEM DO KIT (KG) — IGUAL PARA AS TRÊS LINHAS
A24: 1 | B24: 0.03
A25: 3 | B25: 0.08
A26: 5 | B26: 0.1
A27: 10 | B27: 0.14
A29: CMV DO KIT (R$) = PEÇAS × CUSTO POR PEÇA + EMBALAGEM DO KIT
A30: =A18 -> 1 | B30: =$A30*B$14+B18 -> 10.93 | C30: =$A30*C$14+C18 -> 22.02 | D30: =$A30*D$14+D18 -> 34.73
A31: =A19 -> 3 | B31: =$A31*B$14+B19 -> 32.19 | C31: =$A31*C$14+C19 -> 66.06 | D31: =$A31*D$14+D19 -> 102.49
A32: =A20 -> 5 | B32: =$A32*B$14+B20 -> 53.25 | C32: =$A32*C$14+C20 -> 108.1 | D32: =$A32*D$14+D20 -> 168.15
A33: =A21 -> 10 | B33: =$A33*B$14+B21 -> 105.9 | C33: =$A33*C$14+C21 -> 212.7 | D33: =$A33*D$14+D21 -> 330.3
A35: PESO DO PACOTE (KG) = PEÇAS × PESO DA PEÇA + EMBALAGEM
A36: =A18 -> 1 | B36: =ROUND($A36*B$15+$B$24,2) -> 0.19 | C36: =ROUND($A36*C$15+$B$24,2) -> 0.23 | D36: =ROUND($A36*D$15+$B$24,2) -> 0.22
A37: =A19 -> 3 | B37: =ROUND($A37*B$15+$B$25,2) -> 0.56 | C37: =ROUND($A37*C$15+$B$25,2) -> 0.68 | D37: =ROUND($A37*D$15+$B$25,2) -> 0.65
A38: =A20 -> 5 | B38: =ROUND($A38*B$15+$B$26,2) -> 0.9 | C38: =ROUND($A38*C$15+$B$26,2) -> 1.1 | D38: =ROUND($A38*D$15+$B$26,2) -> 1.05
A39: =A21 -> 10 | B39: =ROUND($A39*B$15+$B$27,2) -> 1.74 | C39: =ROUND($A39*C$15+$B$27,2) -> 2.14 | D39: =ROUND($A39*D$15+$B$27,2) -> 2.04
A41: Capacidade ociosa: se a fábrica já roda com folga, o custo marginal da peça é próximo de malha + aviamentos + embalagem e a margem real sobe de 6 a 9 pontos. Se a fábrica está cheia, o custo de oportunidade é integral e esta ficha está certa.
A42: Rotulagem: no Brasil não há fiscalização efetiva do termo "algodão egípcio". Declarar composição que a peça não tem é publicidade enganosa (CDC) e motivo de remoção de anúncio. Use "algodão egípcio" só com laudo do fornecedor de malha.

Sheet Frete 2026
A1: TABELAS DE FRETE 2026 — MERCADO LIVRE (REPUTAÇÃO VERDE) E LOJA PRÓPRIA
A2: R$ por pacote. Fundo verde-claro = valor publicado; demais = interpolação. Confira no simulador de custos do painel do vendedor.
A4: Peso a partir de (kg) | B4: ML · abaixo de R$ 79 · custo logístico | C4: ML · R$ 79–99,99 | D4: ML · R$ 100–119,99 | E4: ML · R$ 120–149,99 | F4: ML · R$ 150–199,99 | G4: ML · R$ 200+ | H4: Loja própria · frete médio | I4: Faixa de peso
A5: Preço a partir de (R$) → | C5: 79 | D5: 100 | E5: 120 | F5: 150 | G5: 200
A6: 0 | B6: 6.5 | C6: 12.35 | D6: 14.5 | E6: 16.65 | F6: 18.8 | G6: 20.95 | H6: 16 | I6: até 0,3 kg
A7: 0.3 | B7: 6.75 | C7: 12.95 | D7: 15.1 | E7: 17.25 | F7: 19.4 | G7: 21.55 | H7: 17.5 | I7: 0,3 a 0,5 kg
A8: 0.5 | B8: 7 | C8: 13.55 | D8: 15.7 | E8: 17.85 | F8: 20 | G8: 22.15 | H8: 19 | I8: 0,5 a 1 kg
A9: 1 | B9: 7.25 | C9: 16.05 | D9: 18.2 | E9: 20.35 | F9: 22.5 | G9: 24.65 | H9: 22 | I9: 1 a 1,5 kg
A10: 1.5 | B10: 7.5 | C10: 16.05 | D10: 18.2 | E10: 20.35 | F10: 22.5 | G10: 24.65 | H10: 25 | I10: 1,5 a 2 kg
A11: 2 | B11: 8 | C11: 16.75 | D11: 18.9 | E11: 21.05 | F11: 23.2 | G11: 25.35 | H11: 29 | I11: 2 a 3 kg
A13: Publicado (reputação verde): até 0,3 kg, R$ 12,35 entre R$ 79 e R$ 99,99 e R$ 20,95 a partir de R$ 200; 1 a 1,5 kg e 1,5 a 2 kg, R$ 24,65 a partir de R$ 200; 2 a 3 kg, R$ 21,05 para produto de R$ 120. Fontes: Agência X3, GoSmarter, Duoke (março a setembro de 2026). Reputação amarela paga cerca de 20% a mais e a vermelha, o dobro.
A14: Abaixo de R$ 79 o Mercado Livre banca o frete ao comprador e cobra do vendedor um custo operacional por peso (coluna B, estimado a partir dos mínimos publicados de R$ 5,65 a R$ 6,25). A partir de R$ 79 o frete grátis é obrigatório e o vendedor paga a tabela acima. A faixa de peso de um pacote é a primeira cujo limite superior é igual ou maior que o peso: 0,3 kg cai na primeira faixa.
A15: Loja própria: média nacional estimada para envio por Correios ou transportadora via intermediador de frete, por faixa de peso.

Sheet Calculadora
A1: CALCULADORA DE MARGEM POR PLATAFORMA
A2: Tudo aqui é fórmula e vem das abas Premissas e Frete 2026. Para simular, mude os números lá.
A4: Rubrica | B4: Mercado Livre | C4: Shopee | D4: TikTok Shop | E4: Loja própria | F4: Como é calculado
A5: Receita bruta (preço do kit) | B5: =Premissas!$B$15 -> 169.9 | C5: =Premissas!$B$15 -> 169.9 | D5: =Premissas!$B$15 -> 169.9 | E5: =Premissas!$B$15 -> 169.9 | F5: Premissas!B15: mesmo preço em todos os canais, para a comparação ser honesta.
A6: Comissão da plataforma (%) | B6: =Premissas!$B$26 -> 0.14 | C6: =INDEX('Taxas 2026'!$C$15:$C$19,MATCH(C5,'Taxas 2026'!$B$15:$B$19,1))+Premissas!$B$36 -> 0.14 | D6: =INDEX('Taxas 2026'!$C$24:$C$25,MATCH(D5,'Taxas 2026'!$B$24:$B$25,1)) -> 0.06 | E6: =Premissas!$B$44 -> 0.0499 | F6: Shopee e TikTok Shop: faixa de preço das tabelas da aba Taxas 2026 (a Shopee soma a campanha de destaque).
A7: Comissão da plataforma (R$) | B7: =B5*B6 -> 23.786 | C7: =C5*C6 -> 23.786 | D7: =D5*D6 -> 10.194 | E7: =E5*E6+Premissas!$B$45 -> 8.86801 | F7: Na loja própria inclui a taxa fixa do gateway por pedido.
A8: Taxa fixa por item (R$) | B8: =Premissas!$B$31 -> 0 | C8: =INDEX('Taxas 2026'!$D$15:$D$19,MATCH(C5,'Taxas 2026'!$B$15:$B$19,1)) -> 20 | D8: =INDEX('Taxas 2026'!$D$24:$D$25,MATCH(D5,'Taxas 2026'!$B$24:$B$25,1)) -> 6 | E8: =Premissas!$B$48 -> 1.57 | F8: ML: custo logístico por peso, só abaixo de R$ 79. Shopee e TikTok: taxa fixa da faixa. Loja: plataforma e apps por pedido.
A9: Frete (R$) | B9: =Premissas!$B$29 -> 20 | C9: =Premissas!$B$34 -> 0 | D9: =D5*Premissas!$B$39 -> 10.194 | E9: =Premissas!$B$47 -> 19 | F9: ML: tabela verde de 2026 pelo peso do pacote e pela faixa de preço, a partir de R$ 79. TikTok: 6% do programa de frete grátis.
A10: Mídia e afiliados (R$) | B10: =B5*Premissas!$B$27 -> 10.194 | C10: =C5*Premissas!$B$35 -> 13.592 | D10: =D5*(Premissas!$B$40+Premissas!$B$41) -> 33.98 | E10: =E5/Premissas!$B$49 -> 56.633333 | F10: TikTok soma comissão de afiliado e ACOS. Na loja própria, a mídia é o preço dividido pelo ROAS.
A11: Imposto (R$) | B11: =B5*Premissas!$B$21 -> 7.6455 | C11: =C5*Premissas!$B$21 -> 7.6455 | D11: =D5*Premissas!$B$21 -> 7.6455 | E11: =E5*Premissas!$B$21 -> 7.6455
A12: Provisão de devolução (R$) | B12: =B5*Premissas!$B$22 -> 8.495 | C12: =C5*Premissas!$B$22 -> 8.495 | D12: =D5*Premissas!$B$22 -> 8.495 | E12: =E5*Premissas!$B$22 -> 8.495
A13: CMV — peças + embalagem do kit (R$) | B13: =Premissas!$B$16 -> 66.06 | C13: =Premissas!$B$16 -> 66.06 | D13: =Premissas!$B$16 -> 66.06 | E13: =Premissas!$B$16 -> 66.06
A14: TOTAL DE CUSTOS | B14: =SUM(B7:B13) -> 136.1805 | C14: =SUM(C7:C13) -> 139.5785 | D14: =SUM(D7:D13) -> 142.5685 | E14: =SUM(E7:E13) -> 168.27184 | F14: Soma das linhas 7 a 13. A linha 6 é percentual e não entra na soma.
A15: MARGEM DE CONTRIBUIÇÃO (R$) | B15: =B5-B14 -> 33.7195 | C15: =C5-C14 -> 30.3215 | D15: =D5-D14 -> 27.3315 | E15: =E5-E14 -> 1.6281567
A16: MARGEM DE CONTRIBUIÇÃO (%) | B16: =IF(B5=0,0,B15/B5) -> 0.19846675 | C16: =IF(C5=0,0,C15/C5) -> 0.17846675 | D16: =IF(D5=0,0,D15/D5) -> 0.16086816 | E16: =IF(E5=0,0,E15/E5) -> 0.0095830292
A17: Veredito | B17: =IF(B16<0,"PREJUÍZO",IF(B16<Premissas!$B$18,"ABAIXO DO MÍNIMO",IF(B16<0.25,"SAUDÁVEL","FORTE"))) -> SAUDÁVEL | C17: =IF(C16<0,"PREJUÍZO",IF(C16<Premissas!$B$18,"ABAIXO DO MÍNIMO",IF(C16<0.25,"SAUDÁVEL","FORTE"))) -> SAUDÁVEL | D17: =IF(D16<0,"PREJUÍZO",IF(D16<Premissas!$B$18,"ABAIXO DO MÍNIMO",IF(D16<0.25,"SAUDÁVEL","FORTE"))) -> SAUDÁVEL | E17: =IF(E16<0,"PREJUÍZO",IF(E16<Premissas!$B$18,"ABAIXO DO MÍNIMO",IF(E16<0.25,"SAUDÁVEL","FORTE"))) -> ABAIXO DO MÍNIMO
A19: Ponto de equilíbrio (kits por mês) | B19: =IF(B15<=0,"não atinge",ROUNDUP(Premissas!$B$23/B15,0)) -> 386 | C19: =IF(C15<=0,"não atinge",ROUNDUP(Premissas!$B$23/C15,0)) -> 429 | D19: =IF(D15<=0,"não atinge",ROUNDUP(Premissas!$B$23/D15,0)) -> 476 | E19: =IF(E15<=0,"não atinge",ROUNDUP(Premissas!$B$23/E15,0)) -> 7985 | F19: Custo fixo mensal ÷ margem por kit, se todo o volume viesse de um único canal.
A20: Margem antes de mídia (%) | B20: =IF(B5=0,0,(B15+B10)/B5) -> 0.25846675 | C20: =IF(C5=0,0,(C15+C10)/C5) -> 0.25846675 | D20: =IF(D5=0,0,(D15+D10)/D5) -> 0.36086816 | E20: =IF(E5=0,0,(E15+E10)/E5) -> 0.34291636
A21: ROAS de equilíbrio (loja própria) | E21: =IF(E20<=0,"—",1/E20) -> 2.916163 | F21: Inverso da margem antes de mídia. Abaixo disso, cada venda na loja própria dá prejuízo.

Sheet Kits 1-3-5-10
A1: KITS DE 1, 3, 5 E 10 PEÇAS — PISO DE MARGEM E PREÇO SUGERIDO POR CANAL
A2: Piso = menor preço com a margem mínima de Premissas!B18. Sugerido = preço de prateleira terminado em 4,90 ou 9,90. Referências de mercado em azul: setembro de 2026.
A4: Linha | B4: Kit | C4: CMV | D4: Peso (kg) | E4: ML piso | F4: ML sugerido | G4: ML margem | H4: Shopee piso | I4: Shopee sugerido | J4: Shopee margem | K4: TikTok piso | L4: TikTok sugerido | M4: TikTok margem | N4: Loja piso | O4: Loja sugerido | P4: Loja margem | Q4: Piso ML por peça | R4: Referência de mercado | S4: Preço da referência | T4: Piso ML vs. referência | U4: Referência só em loja própria? | V4: Veredito
A5: ='Kits calculo'!A7 -> Popular | B5: ='Kits calculo'!B7 -> 1 | C5: ='Kits calculo'!F7 -> 10.93 | D5: ='Kits calculo'!G7 -> 0.19 | E5: ='Kits calculo'!O7 -> 31.405405 | F5: ='Kits calculo'!R7 -> 34.9 | G5: ='Kits calculo'!S7 -> 0.20557307 | H5: ='Kits calculo'!X7 -> 31.431579 | I5: ='Kits calculo'!AA7 -> 34.9 | J5: ='Kits calculo'!AB7 -> 0.1972063 | K5: ='Kits calculo'!AE7 -> 27.670886 | L5: ='Kits calculo'!AH7 -> 29.9 | M5: ='Kits calculo'!AI7 -> 0.17944816 | N5: ='Kits calculo'!AJ7 -> 77.710033 | O5: ='Kits calculo'!AM7 -> 79.9 | P5: ='Kits calculo'!AN7 -> 0.1601897 | Q5: =E5/B5 -> 31.405405 | R5: Old Rules avulsa (ML) | S5: 33.55 | T5: =IF(ISNUMBER(S5),E5/S5-1,"") -> -0.063922343 | V5: =IF(NOT(ISNUMBER(S5)),"SEM MERCADO",IF(U5="sim","SÓ COM MARCA PRÓPRIA",IF(T5<=0,"COMPETE",IF(T5<=0.05,"NO LIMITE","NÃO COMPETE")))) -> COMPETE
A6: ='Kits calculo'!A8 -> Popular | B6: ='Kits calculo'!B8 -> 3 | C6: ='Kits calculo'!F8 -> 32.19 | D6: ='Kits calculo'!G8 -> 0.56 | E6: ='Kits calculo'!O8 -> 70.612613 | F6: ='Kits calculo'!R8 -> 74.9 | G6: ='Kits calculo'!S8 -> 0.18176903 | H6: ='Kits calculo'!X8 -> 76.189474 | I6: ='Kits calculo'!AA8 -> 79.9 | J6: ='Kits calculo'!AB8 -> 0.17205882 | K6: ='Kits calculo'!AE8 -> 87.793103 | L6: ='Kits calculo'!AH8 -> 89.9 | M6: ='Kits calculo'!AI8 -> 0.16019466 | N6: ='Kits calculo'!AJ8 -> 142.96602 | O6: ='Kits calculo'!AM8 -> 144.9 | P6: ='Kits calculo'!AN8 -> 0.15496197 | Q6: =E6/B6 -> 23.537538 | R6: Old Rules kit 3 lisa (ML) | S6: 69.9 | T6: =IF(ISNUMBER(S6),E6/S6-1,"") -> 0.010194744 | V6: =IF(NOT(ISNUMBER(S6)),"SEM MERCADO",IF(U6="sim","SÓ COM MARCA PRÓPRIA",IF(T6<=0,"COMPETE",IF(T6<=0.05,"NO LIMITE","NÃO COMPETE")))) -> NO LIMITE
A7: ='Kits calculo'!A9 -> Popular | B7: ='Kits calculo'!B9 -> 5 | C7: ='Kits calculo'!F9 -> 53.25 | D7: ='Kits calculo'!G9 -> 0.9 | E7: ='Kits calculo'!O9 -> 128.10811 | F7: ='Kits calculo'!R9 -> 129.9 | G7: ='Kits calculo'!S9 -> 0.15765589 | H7: ='Kits calculo'!X9 -> 136.91589 | I7: ='Kits calculo'!AA9 -> 139.9 | J7: ='Kits calculo'!AB9 -> 0.16141172 | K7: ='Kits calculo'!AE9 -> 136.2069 | L7: ='Kits calculo'!AH9 -> 139.9 | M7: ='Kits calculo'!AI9 -> 0.1614832 | N7: ='Kits calculo'!AJ9 -> 199.61445 | O7: ='Kits calculo'!AM9 -> 199.9 | P7: ='Kits calculo'!AN9 -> 0.15053105 | Q7: =E7/B7 -> 25.621622 | R7: Zaroc kit 5 slim (ML) | S7: 123.01 | T7: =IF(ISNUMBER(S7),E7/S7-1,"") -> 0.041444664 | V7: =IF(NOT(ISNUMBER(S7)),"SEM MERCADO",IF(U7="sim","SÓ COM MARCA PRÓPRIA",IF(T7<=0,"COMPETE",IF(T7<=0.05,"NO LIMITE","NÃO COMPETE")))) -> NO LIMITE
A8: ='Kits calculo'!A10 -> Popular | B8: ='Kits calculo'!B10 -> 10 | C8: ='Kits calculo'!F10 -> 105.9 | D8: ='Kits calculo'!G10 -> 1.74 | E8: ='Kits calculo'!O10 -> 235.22523 | F8: ='Kits calculo'!R10 -> 239.9 | G8: ='Kits calculo'!S10 -> 0.16081492 | H8: ='Kits calculo'!X10 -> 246.54206 | I8: ='Kits calculo'!AA10 -> 249.9 | J8: ='Kits calculo'!AB10 -> 0.15718888 | K8: ='Kits calculo'!AE10 -> 257.24138 | L8: ='Kits calculo'!AH10 -> 259.9 | M8: ='Kits calculo'!AI10 -> 0.15444979 | N8: ='Kits calculo'!AJ10 -> 357.3747 | O8: ='Kits calculo'!AM10 -> 359.9 | P8: ='Kits calculo'!AN10 -> 0.15260857 | Q8: =E8/B8 -> 23.522523 | R8: Old Rules kit 10 (ML) | S8: 224.99 | T8: =IF(ISNUMBER(S8),E8/S8-1,"") -> 0.045491912 | V8: =IF(NOT(ISNUMBER(S8)),"SEM MERCADO",IF(U8="sim","SÓ COM MARCA PRÓPRIA",IF(T8<=0,"COMPETE",IF(T8<=0.05,"NO LIMITE","NÃO COMPETE")))) -> NO LIMITE
A9: ='Kits calculo'!A11 -> Essencial | B9: ='Kits calculo'!B11 -> 1 | C9: ='Kits calculo'!F11 -> 22.02 | D9: ='Kits calculo'!G11 -> 0.23 | E9: ='Kits calculo'!O11 -> 51.387387 | F9: ='Kits calculo'!R11 -> 54.9 | G9: ='Kits calculo'!S11 -> 0.18551002 | H9: ='Kits calculo'!X11 -> 54.778947 | I9: ='Kits calculo'!AA11 -> 54.9 | J9: ='Kits calculo'!AB11 -> 0.15104736 | K9: ='Kits calculo'!AE11 -> 64.413793 | L9: ='Kits calculo'!AH11 -> 64.9 | M9: ='Kits calculo'!AI11 -> 0.15325886 | N9: ='Kits calculo'!AJ11 -> 107.54057 | O9: ='Kits calculo'!AM11 -> 109.9 | P9: ='Kits calculo'!AN11 -> 0.15798141 | Q9: =E9/B9 -> 51.387387 | R9: Hering Camiseta Brasil | S9: 49.99 | T9: =IF(ISNUMBER(S9),E9/S9-1,"") -> 0.027953338 | V9: =IF(NOT(ISNUMBER(S9)),"SEM MERCADO",IF(U9="sim","SÓ COM MARCA PRÓPRIA",IF(T9<=0,"COMPETE",IF(T9<=0.05,"NO LIMITE","NÃO COMPETE")))) -> NO LIMITE
A10: ='Kits calculo'!A12 -> Essencial | B10: ='Kits calculo'!B12 -> 3 | C10: ='Kits calculo'!F12 -> 66.06 | D10: ='Kits calculo'!G12 -> 0.68 | E10: ='Kits calculo'!O12 -> 155.06306 | F10: ='Kits calculo'!R12 -> 159.9 | G10: ='Kits calculo'!S12 -> 0.16678862 | H10: ='Kits calculo'!X12 -> 160.85981 | I10: ='Kits calculo'!AA12 -> 164.9 | J10: ='Kits calculo'!AB12 -> 0.16310794 | K10: ='Kits calculo'!AE12 -> 165.65517 | L10: ='Kits calculo'!AH12 -> 169.9 | M10: ='Kits calculo'!AI12 -> 0.16086816 | N10: ='Kits calculo'!AJ12 -> 234.07155 | O10: ='Kits calculo'!AM12 -> 234.9 | P10: ='Kits calculo'!AN12 -> 0.15131115 | Q10: =E10/B10 -> 51.687688 | R10: Malwee kit 3 (ML) | S10: 156.99 | T10: =IF(ISNUMBER(S10),E10/S10-1,"") -> -0.012274265 | V10: =IF(NOT(ISNUMBER(S10)),"SEM MERCADO",IF(U10="sim","SÓ COM MARCA PRÓPRIA",IF(T10<=0,"COMPETE",IF(T10<=0.05,"NO LIMITE","NÃO COMPETE")))) -> COMPETE
A11: ='Kits calculo'!A13 -> Essencial | B11: ='Kits calculo'!B13 -> 5 | C11: ='Kits calculo'!F13 -> 108.1 | D11: ='Kits calculo'!G13 -> 1.1 | E11: ='Kits calculo'!O13 -> 239.18919 | F11: ='Kits calculo'!R13 -> 239.9 | G11: ='Kits calculo'!S13 -> 0.15164444 | H11: ='Kits calculo'!X13 -> 250.65421 | I11: ='Kits calculo'!AA13 -> 254.9 | J11: ='Kits calculo'!AB13 -> 0.15891134 | K11: ='Kits calculo'!AE13 -> 262.29885 | L11: ='Kits calculo'!AH13 -> 264.9 | M11: ='Kits calculo'!AI13 -> 0.15427142 | N11: ='Kits calculo'!AJ13 -> 355.22281 | O11: ='Kits calculo'!AM13 -> 359.9 | P11: ='Kits calculo'!AN13 -> 0.15483141 | Q11: =E11/B11 -> 47.837838 | R11: Hering kit 5 (ML) | S11: 174.99 | T11: =IF(ISNUMBER(S11),E11/S11-1,"") -> 0.36687347 | V11: =IF(NOT(ISNUMBER(S11)),"SEM MERCADO",IF(U11="sim","SÓ COM MARCA PRÓPRIA",IF(T11<=0,"COMPETE",IF(T11<=0.05,"NO LIMITE","NÃO COMPETE")))) -> NÃO COMPETE
A12: ='Kits calculo'!A14 -> Essencial | B12: ='Kits calculo'!B14 -> 10 | C12: ='Kits calculo'!F14 -> 212.7 | D12: ='Kits calculo'!G14 -> 2.14 | E12: ='Kits calculo'!O14 -> 428.91892 | F12: ='Kits calculo'!R14 -> 429.9 | G12: ='Kits calculo'!S14 -> 0.15126657 | H12: ='Kits calculo'!X14 -> 446.16822 | I12: ='Kits calculo'!AA14 -> 449.9 | J12: ='Kits calculo'!AB14 -> 0.15443765 | K12: ='Kits calculo'!AE14 -> 502.75862 | L12: ='Kits calculo'!AH14 -> 504.9 | M12: ='Kits calculo'!AI14 -> 0.15184492 | N12: ='Kits calculo'!AJ14 -> 655.4111 | O12: ='Kits calculo'!AM14 -> 659.9 | P12: ='Kits calculo'!AN14 -> 0.1525289 | Q12: =E12/B12 -> 42.891892 | R12: Old Rules kit 10 (ML) | S12: 224.99 | T12: =IF(ISNUMBER(S12),E12/S12-1,"") -> 0.90639103 | V12: =IF(NOT(ISNUMBER(S12)),"SEM MERCADO",IF(U12="sim","SÓ COM MARCA PRÓPRIA",IF(T12<=0,"COMPETE",IF(T12<=0.05,"NO LIMITE","NÃO COMPETE")))) -> NÃO COMPETE
A13: ='Kits calculo'!A15 -> Fibra Longa | B13: ='Kits calculo'!B15 -> 1 | C13: ='Kits calculo'!F15 -> 34.73 | D13: ='Kits calculo'!G15 -> 0.22 | E13: ='Kits calculo'!O15 -> 74.288288 | F13: ='Kits calculo'!R15 -> 74.9 | G13: ='Kits calculo'!S15 -> 0.15453271 | H13: ='Kits calculo'!X15 -> 94.82243 | I13: ='Kits calculo'!AA15 -> 94.9 | J13: ='Kits calculo'!AB15 -> 0.1504373 | K13: ='Kits calculo'!AE15 -> 93.632184 | L13: ='Kits calculo'!AH15 -> 94.9 | M13: ='Kits calculo'!AI15 -> 0.15581138 | N13: ='Kits calculo'!AJ15 -> 141.72868 | O13: ='Kits calculo'!AM15 -> 144.9 | P13: ='Kits calculo'!AN15 -> 0.15813658 | Q13: =E13/B13 -> 74.288288 | R13: Insider Tech T-shirt | S13: 135 | T13: =IF(ISNUMBER(S13),E13/S13-1,"") -> -0.44971638 | V13: =IF(NOT(ISNUMBER(S13)),"SEM MERCADO",IF(U13="sim","SÓ COM MARCA PRÓPRIA",IF(T13<=0,"COMPETE",IF(T13<=0.05,"NO LIMITE","NÃO COMPETE")))) -> COMPETE
A14: ='Kits calculo'!A16 -> Fibra Longa | B14: ='Kits calculo'!B16 -> 3 | C14: ='Kits calculo'!F16 -> 102.49 | D14: ='Kits calculo'!G16 -> 0.65 | E14: ='Kits calculo'!O16 -> 224.57658 | F14: ='Kits calculo'!R16 -> 224.9 | G14: ='Kits calculo'!S16 -> 0.15079813 | H14: ='Kits calculo'!X16 -> 240.16822 | I14: ='Kits calculo'!AA16 -> 244.9 | J14: ='Kits calculo'!AB16 -> 0.16033687 | K14: ='Kits calculo'!AE16 -> 249.4023 | L14: ='Kits calculo'!AH16 -> 249.9 | M14: ='Kits calculo'!AI16 -> 0.15086635 | N14: ='Kits calculo'!AJ16 -> 332.06312 | O14: ='Kits calculo'!AM16 -> 334.9 | P14: ='Kits calculo'!AN16 -> 0.15314917 | Q14: =E14/B14 -> 74.858859 | R14: Minimal Club kit 4 → 3 peças | S14: 344.36 | T14: =IF(ISNUMBER(S14),E14/S14-1,"") -> -0.3478436 | V14: =IF(NOT(ISNUMBER(S14)),"SEM MERCADO",IF(U14="sim","SÓ COM MARCA PRÓPRIA",IF(T14<=0,"COMPETE",IF(T14<=0.05,"NO LIMITE","NÃO COMPETE")))) -> COMPETE
A15: ='Kits calculo'!A17 -> Fibra Longa | B15: ='Kits calculo'!B17 -> 5 | C15: ='Kits calculo'!F17 -> 168.15 | D15: ='Kits calculo'!G17 -> 1.05 | E15: ='Kits calculo'!O17 -> 347.38739 | F15: ='Kits calculo'!R17 -> 349.9 | G15: ='Kits calculo'!S17 -> 0.15398542 | H15: ='Kits calculo'!X17 -> 362.8972 | I15: ='Kits calculo'!AA17 -> 364.9 | J15: ='Kits calculo'!AB17 -> 0.15293642 | K15: ='Kits calculo'!AE17 -> 400.34483 | L15: ='Kits calculo'!AH17 -> 404.9 | M15: ='Kits calculo'!AI17 -> 0.1548938 | N15: ='Kits calculo'!AJ17 -> 516.74886 | O15: ='Kits calculo'!AM17 -> 519.9 | P15: ='Kits calculo'!AN17 -> 0.1522533 | Q15: =E15/B15 -> 69.477477 | R15: Minimal Club kit 6 → 5 peças | S15: 638.5 | T15: =IF(ISNUMBER(S15),E15/S15-1,"") -> -0.45593205 | U15: sim | V15: =IF(NOT(ISNUMBER(S15)),"SEM MERCADO",IF(U15="sim","SÓ COM MARCA PRÓPRIA",IF(T15<=0,"COMPETE",IF(T15<=0.05,"NO LIMITE","NÃO COMPETE")))) -> SÓ COM MARCA PRÓPRIA
A16: ='Kits calculo'!A18 -> Fibra Longa | B16: ='Kits calculo'!B18 -> 10 | C16: ='Kits calculo'!F18 -> 330.3 | D16: ='Kits calculo'!G18 -> 2.04 | E16: ='Kits calculo'!O18 -> 640.81081 | F16: ='Kits calculo'!R18 -> 644.9 | G16: ='Kits calculo'!S18 -> 0.15351915 | H16: ='Kits calculo'!X18 -> 665.98131 | I16: ='Kits calculo'!AA18 -> 669.9 | J16: ='Kits calculo'!AB18 -> 0.15312957 | K16: ='Kits calculo'!AE18 -> 773.10345 | L16: ='Kits calculo'!AH18 -> 774.9 | M16: ='Kits calculo'!AI18 -> 0.15100852 | N16: ='Kits calculo'!AJ18 -> 971.73855 | O16: ='Kits calculo'!AM18 -> 974.9 | P16: ='Kits calculo'!AN18 -> 0.15120558 | Q16: =E16/B16 -> 64.081081 | R16: sem referência | T16: =IF(ISNUMBER(S16),E16/S16-1,"") | V16: =IF(NOT(ISNUMBER(S16)),"SEM MERCADO",IF(U16="sim","SÓ COM MARCA PRÓPRIA",IF(T16<=0,"COMPETE",IF(T16<=0.05,"NO LIMITE","NÃO COMPETE")))) -> SEM MERCADO
A18: Veredito: COMPETE = piso abaixo do preço da referência; NO LIMITE = até 5% acima (vender ali significa aceitar menos de 15%); NÃO COMPETE = mais de 5% acima. Nos kits premium de 4 e 6 peças da Minimal Club o preço por peça foi aplicado ao tamanho do kit. Loja própria com mídia paga ao ROAS de Premissas!B49.
A20: CUSTO-ALVO — ATÉ QUANTO A PEÇA PODE CUSTAR PARA EMPATAR COM O CONCORRENTE E DEIXAR A MARGEM MÍNIMA NO ML
A21: Kit | B21: Peças | C21: Referência | D21: Preço | E21: Linha usada | F21: Índice | G21: Embalagem | H21: Peso (kg) | I21: Faixa | J21: Frete ou custo log. | K21: Custo-alvo por peça | L21: Custo da linha | M21: Folga (+) ou falta (−)
A22: Avulsa | B22: 1 | C22: Hering Camiseta Brasil | D22: 49.99 | E22: Essencial | F22: =MATCH(E22,'Ficha de Custo'!$B$4:$D$4,0) -> 2 | G22: =INDEX('Ficha de Custo'!$B$18:$D$21,MATCH(B22,'Ficha de Custo'!$A$18:$A$21,0),F22) -> 1.5 | H22: =INDEX('Ficha de Custo'!$B$36:$D$39,MATCH(B22,'Ficha de Custo'!$A$36:$A$39,0),F22) -> 0.23 | I22: =MATCH(H22-0.0000001,'Frete 2026'!$A$6:$A$11,1) -> 1 | J22: =IF(D22<79,INDEX('Frete 2026'!$B$6:$B$11,I22),INDEX('Frete 2026'!$C$6:$G$11,I22,MATCH(D22,'Frete 2026'!$C$5:$G$5,1))) -> 6.5 | K22: =(D22*(1-Premissas!$B$18)-D22*'Kits calculo'!$D$4-J22-G22)/B22 -> 19.74445 | L22: =INDEX('Ficha de Custo'!$B$14:$D$14,F22) -> 20.52 | M22: =K22-L22 -> -0.77555
A23: Kit 3 | B23: 3 | C23: Malwee kit 3 (ML) | D23: 156.99 | E23: Essencial | F23: =MATCH(E23,'Ficha de Custo'!$B$4:$D$4,0) -> 2 | G23: =INDEX('Ficha de Custo'!$B$18:$D$21,MATCH(B23,'Ficha de Custo'!$A$18:$A$21,0),F23) -> 4.5 | H23: =INDEX('Ficha de Custo'!$B$36:$D$39,MATCH(B23,'Ficha de Custo'!$A$36:$A$39,0),F23) -> 0.68 | I23: =MATCH(H23-0.0000001,'Frete 2026'!$A$6:$A$11,1) -> 3 | J23: =IF(D23<79,INDEX('Frete 2026'!$B$6:$B$11,I23),INDEX('Frete 2026'!$C$6:$G$11,I23,MATCH(D23,'Frete 2026'!$C$5:$G$5,1))) -> 20 | K23: =(D23*(1-Premissas!$B$18)-D23*'Kits calculo'!$D$4-J23-G23)/B23 -> 20.876483 | L23: =INDEX('Ficha de Custo'!$B$14:$D$14,F23) -> 20.52 | M23: =K23-L23 -> 0.35648333
A24: Kit 5 | B24: 5 | C24: Zaroc kit 5 slim (ML) | D24: 123.01 | E24: Popular | F24: =MATCH(E24,'Ficha de Custo'!$B$4:$D$4,0) -> 1 | G24: =INDEX('Ficha de Custo'!$B$18:$D$21,MATCH(B24,'Ficha de Custo'!$A$18:$A$21,0),F24) -> 1.1 | H24: =INDEX('Ficha de Custo'!$B$36:$D$39,MATCH(B24,'Ficha de Custo'!$A$36:$A$39,0),F24) -> 0.9 | I24: =MATCH(H24-0.0000001,'Frete 2026'!$A$6:$A$11,1) -> 3 | J24: =IF(D24<79,INDEX('Frete 2026'!$B$6:$B$11,I24),INDEX('Frete 2026'!$C$6:$G$11,I24,MATCH(D24,'Frete 2026'!$C$5:$G$5,1))) -> 17.85 | K24: =(D24*(1-Premissas!$B$18)-D24*'Kits calculo'!$D$4-J24-G24)/B24 -> 9.86411 | L24: =INDEX('Ficha de Custo'!$B$14:$D$14,F24) -> 10.43 | M24: =K24-L24 -> -0.56589
A25: Kit 10 | B25: 10 | C25: Old Rules kit 10 (ML) | D25: 224.99 | E25: Popular | F25: =MATCH(E25,'Ficha de Custo'!$B$4:$D$4,0) -> 1 | G25: =INDEX('Ficha de Custo'!$B$18:$D$21,MATCH(B25,'Ficha de Custo'!$A$18:$A$21,0),F25) -> 1.6 | H25: =INDEX('Ficha de Custo'!$B$36:$D$39,MATCH(B25,'Ficha de Custo'!$A$36:$A$39,0),F25) -> 1.74 | I25: =MATCH(H25-0.0000001,'Frete 2026'!$A$6:$A$11,1) -> 5 | J25: =IF(D25<79,INDEX('Frete 2026'!$B$6:$B$11,I25),INDEX('Frete 2026'!$C$6:$G$11,I25,MATCH(D25,'Frete 2026'!$C$5:$G$5,1))) -> 24.65 | K25: =(D25*(1-Premissas!$B$18)-D25*'Kits calculo'!$D$4-J25-G25)/B25 -> 9.861945 | L25: =INDEX('Ficha de Custo'!$B$14:$D$14,F25) -> 10.43 | M25: =K25-L25 -> -0.568055

Sheet Kits calculo
A1: MEMÓRIA DE CÁLCULO — PISO DE MARGEM E PREÇO SUGERIDO POR LINHA, KIT E CANAL
A2: Para cada canal, o piso é o menor preço que entrega a margem mínima em alguma faixa de preço da plataforma (colunas "cand."). Não edite: tudo vem de Premissas, Ficha de Custo, Frete 2026 e Taxas 2026.
A4: Margem mínima | B4: =Premissas!$B$18 -> 0.15 | C4: k ML | D4: =Premissas!$B$26+Premissas!$B$27+Premissas!$B$21+Premissas!$B$22 -> 0.295 | E4: k Shopee s/ comissão | F4: =Premissas!$B$36+Premissas!$B$35+Premissas!$B$21+Premissas!$B$22 -> 0.175 | G4: k TikTok s/ comissão | H4: =Premissas!$B$39+Premissas!$B$40+Premissas!$B$41+Premissas!$B$21+Premissas!$B$22 -> 0.355 | I4: k Loja com mídia | J4: =Premissas!$B$44+1/Premissas!$B$49+Premissas!$B$21+Premissas!$B$22 -> 0.47823333 | K4: k Loja sem mídia | L4: =Premissas!$B$44+Premissas!$B$21+Premissas!$B$22 -> 0.1449
A6: Linha | B6: Kit | C6: Índice | D6: Custo/peça | E6: Emb. kit | F6: CMV | G6: Peso (kg) | H6: Faixa peso | I6: ML cand. <79 | J6: ML cand. 79–99 | K6: ML cand. 100–119 | L6: ML cand. 120–149 | M6: ML cand. 150–199 | N6: ML cand. 200+ | O6: ML piso | P6: ML s0 | Q6: ML margem s0 | R6: ML sugerido | S6: ML margem | T6: Shopee cand. 8–79 | U6: Shopee cand. 80–99 | V6: Shopee cand. 100–199 | W6: Shopee cand. 200+ | X6: Shopee piso | Y6: Shopee s0 | Z6: Shopee margem s0 | AA6: Shopee sugerido | AB6: Shopee margem | AC6: TikTok cand. <50 | AD6: TikTok cand. 50+ | AE6: TikTok piso | AF6: TikTok s0 | AG6: TikTok margem s0 | AH6: TikTok sugerido | AI6: TikTok margem | AJ6: Loja piso | AK6: Loja s0 | AL6: Loja margem s0 | AM6: Loja sugerido | AN6: Loja margem
A7: Popular | B7: 1 | C7: =MATCH(A7,'Ficha de Custo'!$B$4:$D$4,0) -> 1 | D7: =INDEX('Ficha de Custo'!$B$14:$D$14,C7) -> 10.43 | E7: =INDEX('Ficha de Custo'!$B$18:$D$21,MATCH(B7,'Ficha de Custo'!$A$18:$A$21,0),C7) -> 0.5 | F7: =D7*B7+E7 -> 10.93 | G7: =INDEX('Ficha de Custo'!$B$36:$D$39,MATCH(B7,'Ficha de Custo'!$A$36:$A$39,0),C7) -> 0.19 | H7: =MATCH(G7-0.0000001,'Frete 2026'!$A$6:$A$11,1) -> 1 | I7: =IF((1-$D$4-$B$4)<=0,"",IF(MAX(1,(F7+INDEX('Frete 2026'!$B$6:$B$11,H7))/(1-$D$4-$B$4))<79,MAX(1,(F7+INDEX('Frete 2026'!$B$6:$B$11,H7))/(1-$D$4-$B$4)),"")) -> 31.405405 | J7: =IF((1-$D$4-$B$4)<=0,"",IF(MAX('Frete 2026'!$C$5,(F7+INDEX('Frete 2026'!$C$6:$C$11,H7))/(1-$D$4-$B$4))<'Frete 2026'!$D$5,MAX('Frete 2026'!$C$5,(F7+INDEX('Frete 2026'!$C$6:$C$11,H7))/(1-$D$4-$B$4)),"")) -> 79 | K7: =IF((1-$D$4-$B$4)<=0,"",IF(MAX('Frete 2026'!$D$5,(F7+INDEX('Frete 2026'!$D$6:$D$11,H7))/(1-$D$4-$B$4))<'Frete 2026'!$E$5,MAX('Frete 2026'!$D$5,(F7+INDEX('Frete 2026'!$D$6:$D$11,H7))/(1-$D$4-$B$4)),"")) -> 100 | L7: =IF((1-$D$4-$B$4)<=0,"",IF(MAX('Frete 2026'!$E$5,(F7+INDEX('Frete 2026'!$E$6:$E$11,H7))/(1-$D$4-$B$4))<'Frete 2026'!$F$5,MAX('Frete 2026'!$E$5,(F7+INDEX('Frete 2026'!$E$6:$E$11,H7))/(1-$D$4-$B$4)),"")) -> 120 | M7: =IF((1-$D$4-$B$4)<=0,"",IF(MAX('Frete 2026'!$F$5,(F7+INDEX('Frete 2026'!$F$6:$F$11,H7))/(1-$D$4-$B$4))<'Frete 2026'!$G$5,MAX('Frete 2026'!$F$5,(F7+INDEX('Frete 2026'!$F$6:$F$11,H7))/(1-$D$4-$B$4)),"")) -> 150 | N7: =IF((1-$D$4-$B$4)<=0,"",IF(MAX('Frete 2026'!$G$5,(F7+INDEX('Frete 2026'!$G$6:$G$11,H7))/(1-$D$4-$B$4))<1000000000,MAX('Frete 2026'!$G$5,(F7+INDEX('Frete 2026'!$G$6:$G$11,H7))/(1-$D$4-$B$4)),"")) -> 200 | O7: =MIN(I7:N7) -> 31.405405 | P7: =CEILING(O7-4.9,5)+4.9 -> 34.9 | Q7: =((P7)-(F7+IF((P7)<79,INDEX('Frete 2026'!$B$6:$B$11,H7),INDEX('Frete 2026'!$C$6:$G$11,H7,MATCH((P7),'Frete 2026'!$C$5:$G$5,1)))+(P7)*$D$4))/(P7) -> 0.20557307 | R7: =IF(((P7)-(F7+IF((P7)<79,INDEX('Frete 2026'!$B$6:$B$11,H7),INDEX('Frete 2026'!$C$6:$G$11,H7,MATCH((P7),'Frete 2026'!$C$5:$G$5,1)))+(P7)*$D$4))/(P7)>=$B$4,P7,IF(((P7+5)-(F7+IF((P7+5)<79,INDEX('Frete 2026'!$B$6:$B$11,H7),INDEX('Frete 2026'!$C$6:$G$11,H7,MATCH((P7+5),'Frete 2026'!$C$5:$G$5,1)))+(P7+5)*$D$4))/(P7+5)>=$B$4,P7+5,P7+10)) -> 34.9 | S7: =((R7)-(F7+IF((R7)<79,INDEX('Frete 2026'!$B$6:$B$11,H7),INDEX('Frete 2026'!$C$6:$G$11,H7,MATCH((R7),'Frete 2026'!$C$5:$G$5,1)))+(R7)*$D$4))/(R7) -> 0.20557307 | T7: =IF((1-'Taxas 2026'!$C$16-$F$4-$B$4)<=0,"",IF(MAX('Taxas 2026'!$B$16,(F7+'Taxas 2026'!$D$16+Premissas!$B$34)/(1-'Taxas 2026'!$C$16-$F$4-$B$4))<'Taxas 2026'!$B$17,MAX('Taxas 2026'!$B$16,(F7+'Taxas 2026'!$D$16+Premissas!$B$34)/(1-'Taxas 2026'!$C$16-$F$4-$B$4)),"")) -> 31.431579 | U7: =IF((1-'Taxas 2026'!$C$17-$F$4-$B$4)<=0,"",IF(MAX('Taxas 2026'!$B$17,(F7+'Taxas 2026'!$D$17+Premissas!$B$34)/(1-'Taxas 2026'!$C$17-$F$4-$B$4))<'Taxas 2026'!$B$18,MAX('Taxas 2026'!$B$17,(F7+'Taxas 2026'!$D$17+Premissas!$B$34)/(1-'Taxas 2026'!$C$17-$F$4-$B$4)),"")) -> 80 | V7: =IF((1-'Taxas 2026'!$C$18-$F$4-$B$4)<=0,"",IF(MAX('Taxas 2026'!$B$18,(F7+'Taxas 2026'!$D$18+Premissas!$B$34)/(1-'Taxas 2026'!$C$18-$F$4-$B$4))<'Taxas 2026'!$B$19,MAX('Taxas 2026'!$B$18,(F7+'Taxas 2026'!$D$18+Premissas!$B$34)/(1-'Taxas 2026'!$C$18-$F$4-$B$4)),"")) -> 100 | W7: =IF((1-'Taxas 2026'!$C$19-$F$4-$B$4)<=0,"",IF(MAX('Taxas 2026'!$B$19,(F7+'Taxas 2026'!$D$19+Premissas!$B$34)/(1-'Taxas 2026'!$C$19-$F$4-$B$4))<1000000000,MAX('Taxas 2026'!$B$19,(F7+'Taxas 2026'!$D$19+Premissas!$B$34)/(1-'Taxas 2026'!$C$19-$F$4-$B$4)),"")) -> 200 | X7: =MIN(T7:W7) -> 31.431579 | Y7: =CEILING(X7-4.9,5)+4.9 -> 34.9 | Z7: =((Y7)-(F7+(Y7)*(INDEX('Taxas 2026'!$C$15:$C$19,MATCH((Y7),'Taxas 2026'!$B$15:$B$19,1))+$F$4)+INDEX('Taxas 2026'!$D$15:$D$19,MATCH((Y7),'Taxas 2026'!$B$15:$B$19,1))+Premissas!$B$34))/(Y7) -> 0.1972063 | AA7: =IF(((Y7)-(F7+(Y7)*(INDEX('Taxas 2026'!$C$15:$C$19,MATCH((Y7),'Taxas 2026'!$B$15:$B$19,1))+$F$4)+INDEX('Taxas 2026'!$D$15:$D$19,MATCH((Y7),'Taxas 2026'!$B$15:$B$19,1))+Premissas!$B$34))/(Y7)>=$B$4,Y7,IF(((Y7+5)-(F7+(Y7+5)*(INDEX('Taxas 2026'!$C$15:$C$19,MATCH((Y7+5),'Taxas 2026'!$B$15:$B$19,1))+$F$4)+INDEX('Taxas 2026'!$D$15:$D$19,MATCH((Y7+5),'Taxas 2026'!$B$15:$B$19,1))+Premissas!$B$34))/(Y7+5)>=$B$4,Y7+5,Y7+10)) -> 34.9 | AB7: =((AA7)-(F7+(AA7)*(INDEX('Taxas 2026'!$C$15:$C$19,MATCH((AA7),'Taxas 2026'!$B$15:$B$19,1))+$F$4)+INDEX('Taxas 2026'!$D$15:$D$19,MATCH((AA7),'Taxas 2026'!$B$15:$B$19,1))+Premissas!$B$34))/(AA7) -> 0.1972063 | AC7: =IF((1-'Taxas 2026'!$C$24-$H$4-$B$4)<=0,"",IF(MAX(1,(F7+'Taxas 2026'!$D$24)/(1-'Taxas 2026'!$C$24-$H$4-$B$4))<'Taxas 2026'!$B$25,MAX(1,(F7+'Taxas 2026'!$D$24)/(1-'Taxas 2026'!$C$24-$H$4-$B$4)),"")) -> 27.670886 | AD7: =IF((1-'Taxas 2026'!$C$25-$H$4-$B$4)<=0,"",IF(MAX('Taxas 2026'!$B$25,(F7+'Taxas 2026'!$D$25)/(1-'Taxas 2026'!$C$25-$H$4-$B$4))<1000000000,MAX('Taxas 2026'!$B$25,(F7+'Taxas 2026'!$D$25)/(1-'Taxas 2026'!$C$25-$H$4-$B$4)),"")) -> 50 | AE7: =MIN(AC7:AD7) -> 27.670886 | AF7: =CEILING(AE7-4.9,5)+4.9 -> 29.9 | AG7: =((AF7)-(F7+(AF7)*(INDEX('Taxas 2026'!$C$24:$C$25,MATCH((AF7),'Taxas 2026'!$B$24:$B$25,1))+$H$4)+INDEX('Taxas 2026'!$D$24:$D$25,MATCH((AF7),'Taxas 2026'!$B$24:$B$25,1))))/(AF7) -> 0.17944816 | AH7: =IF(((AF7)-(F7+(AF7)*(INDEX('Taxas 2026'!$C$24:$C$25,MATCH((AF7),'Taxas 2026'!$B$24:$B$25,1))+$H$4)+INDEX('Taxas 2026'!$D$24:$D$25,MATCH((AF7),'Taxas 2026'!$B$24:$B$25,1))))/(AF7)>=$B$4,AF7,IF(((AF7+5)-(F7+(AF7+5)*(INDEX('Taxas 2026'!$C$24:$C$25,MATCH((AF7+5),'Taxas 2026'!$B$24:$B$25,1))+$H$4)+INDEX('Taxas 2026'!$D$24:$D$25,MATCH((AF7+5),'Taxas 2026'!$B$24:$B$25,1))))/(AF7+5)>=$B$4,AF7+5,AF7+10)) -> 29.9 | AI7: =((AH7)-(F7+(AH7)*(INDEX('Taxas 2026'!$C$24:$C$25,MATCH((AH7),'Taxas 2026'!$B$24:$B$25,1))+$H$4)+INDEX('Taxas 2026'!$D$24:$D$25,MATCH((AH7),'Taxas 2026'!$B$24:$B$25,1))))/(AH7) -> 0.17944816 | AJ7: =MAX(1,(F7+Premissas!$B$45+Premissas!$B$48+INDEX('Frete 2026'!$H$6:$H$11,H7))/(1-$J$4-$B$4)) -> 77.710033 | AK7: =CEILING(AJ7-4.9,5)+4.9 -> 79.9 | AL7: =((AK7)-(F7+Premissas!$B$45+Premissas!$B$48+INDEX('Frete 2026'!$H$6:$H$11,H7)+(AK7)*$J$4))/(AK7) -> 0.1601897 | AM7: =IF(((AK7)-(F7+Premissas!$B$45+Premissas!$B$48+INDEX('Frete 2026'!$H$6:$H$11,H7)+(AK7)*$J$4))/(AK7)>=$B$4,AK7,IF(((AK7+5)-(F7+Premissas!$B$45+Premissas!$B$48+INDEX('Frete 2026'!$H$6:$H$11,H7)+(AK7+5)*$J$4))/(AK7+5)>=$B$4,AK7+5,AK7+10)) -> 79.9 | AN7: =((AM7)-(F7+Premissas!$B$45+Premissas!$B$48+INDEX('Frete 2026'!$H$6:$H$11,H7)+(AM7)*$J$4))/(AM7) -> 0.1601897
A8: Popular | B8: 3 | C8: =MATCH(A8,'Ficha de Custo'!$B$4:$D$4,0) -> 1 | D8: =INDEX('Ficha de Custo'!$B$14:$D$14,C8) -> 10.43 | E8: =INDEX('Ficha de Custo'!$B$18:$D$21,MATCH(B8,'Ficha de Custo'!$A$18:$A$21,0),C8) -> 0.9 | F8: =D8*B8+E8 -> 32.19 | G8: =INDEX('Ficha de Custo'!$B$36:$D$39,MATCH(B8,'Ficha de Custo'!$A$36:$A$39,0),C8) -> 0.56 | H8: =MATCH(G8-0.0000001,'Frete 2026'!$A$6:$A$11,1) -> 3 | I8: =IF((1-$D$4-$B$4)<=0,"",IF(MAX(1,(F8+INDEX('Frete 2026'!$B$6:$B$11,H8))/(1-$D$4-$B$4))<79,MAX(1,(F8+INDEX('Frete 2026'!$B$6:$B$11,H8))/(1-$D$4-$B$4)),"")) -> 70.612613 | J8: =IF((1-$D$4-$B$4)<=0,"",IF(MAX('Frete 2026'!$C$5,(F8+INDEX('Frete 2026'!$C$6:$C$11,H8))/(1-$D$4-$B$4))<'Frete 2026'!$D$5,MAX('Frete 2026'!$C$5,(F8+INDEX('Frete 2026'!$C$6:$C$11,H8))/(1-$D$4-$B$4)),"")) -> 82.414414 | K8: =IF((1-$D$4-$B$4)<=0,"",IF(MAX('Frete 2026'!$D$5,(F8+INDEX('Frete 2026'!$D$6:$D$11,H8))/(1-$D$4-$B$4))<'Frete 2026'!$E$5,MAX('Frete 2026'!$D$5,(F8+INDEX('Frete 2026'!$D$6:$D$11,H8))/(1-$D$4-$B$4)),"")) -> 100 | L8: =IF((1-$D$4-$B$4)<=0,"",IF(MAX('Frete 2026'!$E$5,(F8+INDEX('Frete 2026'!$E$6:$E$11,H8))/(1-$D$4-$B$4))<'Frete 2026'!$F$5,MAX('Frete 2026'!$E$5,(F8+INDEX('Frete 2026'!$E$6:$E$11,H8))/(1-$D$4-$B$4)),"")) -> 120 | M8: =IF((1-$D$4-$B$4)<=0,"",IF(MAX('Frete 2026'!$F$5,(F8+INDEX('Frete 2026'!$F$6:$F$11,H8))/(1-$D$4-$B$4))<'Frete 2026'!$G$5,MAX('Frete 2026'!$F$5,(F8+INDEX('Frete 2026'!$F$6:$F$11,H8))/(1-$D$4-$B$4)),"")) -> 150 | N8: =IF((1-$D$4-$B$4)<=0,"",IF(MAX('Frete 2026'!$G$5,(F8+INDEX('Frete 2026'!$G$6:$G$11,H8))/(1-$D$4-$B$4))<1000000000,MAX('Frete 2026'!$G$5,(F8+INDEX('Frete 2026'!$G$6:$G$11,H8))/(1-$D$4-$B$4)),"")) -> 200 | O8: =MIN(I8:N8) -> 70.612613 | P8: =CEILING(O8-4.9,5)+4.9 -> 74.9 | Q8: =((P8)-(F8+IF((P8)<79,INDEX('Frete 2026'!$B$6:$B$11,H8),INDEX('Frete 2026'!$C$6:$G$11,H8,MATCH((P8),'Frete 2026'!$C$5:$G$5,1)))+(P8)*$D$4))/(P8) -> 0.18176903 | R8: =IF(((P8)-(F8+IF((P8)<79,INDEX('Frete 2026'!$B$6:$B$11,H8),INDEX('Frete 2026'!$C$6:$G$11,H8,MATCH((P8),'Frete 2026'!$C$5:$G$5,1)))+(P8)*$D$4))/(P8)>=$B$4,P8,IF(((P8+5)-(F8+IF((P8+5)<79,INDEX('Frete 2026'!$B$6:$B$11,H8),INDEX('Frete 2026'!$C$6:$G$11,H8,MATCH((P8+5),'Frete 2026'!$C$5:$G$5,1)))+(P8+5)*$D$4))/(P8+5)>=$B$4,P8+5,P8+10)) -> 74.9 | S8: =((R8)-(F8+IF((R8)<79,INDEX('Frete 2026'!$B$6:$B$11,H8),INDEX('Frete 2026'!$C$6:$G$11,H8,MATCH((R8),'Frete 2026'!$C$5:$G$5,1)))+(R8)*$D$4))/(R8) -> 0.18176903 | T8: =IF((1-'Taxas 2026'!$C$16-$F$4-$B$4)<=0,"",IF(MAX('Taxas 2026'!$B$16,(F8+'Taxas 2026'!$D$16+Premissas!$B$34)/(1-'Taxas 2026'!$C$16-$F$4-$B$4))<'Taxas 2026'!$B$17,MAX('Taxas 2026'!$B$16,(F8+'Taxas 2026'!$D$16+Premissas!$B$34)/(1-'Taxas 2026'!$C$16-$F$4-$B$4)),"")) -> 76.189474 | U8: =IF((1-'Taxas 2026'!$C$17-$F$4-$B$4)<=0,"",IF(MAX('Taxas 2026'!$B$17,(F8+'Taxas 2026'!$D$17+Premissas!$B$34)/(1-'Taxas 2026'!$C$17-$F$4-$B$4))<'Taxas 2026'!$B$18,MAX('Taxas 2026'!$B$17,(F8+'Taxas 2026'!$D$17+Premissas!$B$34)/(1-'Taxas 2026'!$C$17-$F$4-$B$4)),"")) -> 90.074766 | V8: =IF((1-'Taxas 2026'!$C$18-$F$4-$B$4)<=0,"",IF(MAX('Taxas 2026'!$B$18,(F8+'Taxas 2026'!$D$18+Premissas!$B$34)/(1-'Taxas 2026'!$C$18-$F$4-$B$4))<'Taxas 2026'!$B$19,MAX('Taxas 2026'!$B$18,(F8+'Taxas 2026'!$D$18+Premissas!$B$34)/(1-'Taxas 2026'!$C$18-$F$4-$B$4)),"")) -> 100 | W8: =IF((1-'Taxas 2026'!$C$19-$F$4-$B$4)<=0,"",IF(MAX('Taxas 2026'!$B$19,(F8+'Taxas 2026'!$D$19+Premissas!$B$34)/(1-'Taxas 2026'!$C$19-$F$4-$B$4))<1000000000,MAX('Taxas 2026'!$B$19,(F8+'Taxas 2026'!$D$19+Premissas!$B$34)/(1-'Taxas 2026'!$C$19-$F$4-$B$4)),"")) -> 200 | X8: =MIN(T8:W8) -> 76.189474 | Y8: =CEILING(X8-4.9,5)+4.9 -> 79.9 | Z8: =((Y8)-(F8+(Y8)*(INDEX('Taxas 2026'!$C$15:$C$19,MATCH((Y8),'Taxas 2026'!$B$15:$B$19,1))+$F$4)+INDEX('Taxas 2026'!$D$15:$D$19,MATCH((Y8),'Taxas 2026'!$B$15:$B$19,1))+Premissas!$B$34))/(Y8) -> 0.17205882 | AA8: =IF(((Y8)-(F8+(Y8)*(INDEX('Taxas 2026'!$C$15:$C$19,MATCH((Y8),'Taxas 2026'!$B$15:$B$19,1))+$F$4)+INDEX('Taxas 2026'!$D$15:$D$19,MATCH((Y8),'Taxas 2026'!$B$15:$B$19,1))+Premissas!$B$34))/(Y8)>=$B$4,Y8,IF(((Y8+5)-(F8+(Y8+5)*(INDEX('Taxas 2026'!$C$15:$C$19,MATCH((Y8+5),'Taxas 2026'!$B$15:$B$19,1))+$F$4)+INDEX('Taxas 2026'!$D$15:$D$19,MATCH((Y8+5),'Taxas 2026'!$B$15:$B$19,1))+Premissas!$B$34))/(Y8+5)>=$B$4,Y8+5,Y8+10)) -> 79.9 | AB8: =((AA8)-(F8+(AA8)*(INDEX('Taxas 2026'!$C$15:$C$19,MATCH((AA8),'Taxas 2026'!$B$15:$B$19,1))+$F$4)+INDEX('Taxas 2026'!$D$15:$D$19,MATCH((AA8),'Taxas 2026'!$B$15:$B$19,1))+Premissas!$B$34))/(AA8) -> 0.17205882 | AC8: =IF((1-'Taxas 2026'!$C$24-$H$4-$B$4)<=0,"",IF(MAX(1,(F8+'Taxas 2026'!$D$24)/(1-'Taxas 2026'!$C$24-$H$4-$B$4))<'Taxas 2026'!$B$25,MAX(1,(F8+'Taxas 2026'!$D$24)/(1-'Taxas 2026'!$C$24-$H$4-$B$4)),"")) | AD8: =IF((1-'Taxas 2026'!$C$25-$H$4-$B$4)<=0,"",IF(MAX('Taxas 2026'!$B$25,(F8+'Taxas 2026'!$D$25)/(1-'Taxas 2026'!$C$25-$H$4-$B$4))<1000000000,MAX('Taxas 2026'!$B$25,(F8+'Taxas 2026'!$D$25)/(1-'Taxas 2026'!$C$25-$H$4-$B$4)),"")) -> 87.793103 | AE8: =MIN(AC8:AD8) -> 87.793103 | AF8: =CEILING(AE8-4.9,5)+4.9 -> 89.9 | AG8: =((AF8)-(F8+(AF8)*(INDEX('Taxas 2026'!$C$24:$C$25,MATCH((AF8),'Taxas 2026'!$B$24:$B$25,1))+$H$4)+INDEX('Taxas 2026'!$D$24:$D$25,MATCH((AF8),'Taxas 2026'!$B$24:$B$25,1))))/(AF8) -> 0.16019466 | AH8: =IF(((AF8)-(F8+(AF8)*(INDEX('Taxas 2026'!$C$24:$C$25,MATCH((AF8),'Taxas 2026'!$B$24:$B$25,1))+$H$4)+INDEX('Taxas 2026'!$D$24:$D$25,MATCH((AF8),'Taxas 2026'!$B$24:$B$25,1))))/(AF8)>=$B$4,AF8,IF(((AF8+5)-(F8+(AF8+5)*(INDEX('Taxas 2026'!$C$24:$C$25,MATCH((AF8+5),'Taxas 2026'!$B$24:$B$25,1))+$H$4)+INDEX('Taxas 2026'!$D$24:$D$25,MATCH((AF8+5),'Taxas 2026'!$B$24:$B$25,1))))/(AF8+5)>=$B$4,AF8+5,AF8+10)) -> 89.9 | AI8: =((AH8)-(F8+(AH8)*(INDEX('Taxas 2026'!$C$24:$C$25,MATCH((AH8),'Taxas 2026'!$B$24:$B$25,1))+$H$4)+INDEX('Taxas 2026'!$D$24:$D$25,MATCH((AH8),'Taxas 2026'!$B$24:$B$25,1))))/(AH8) -> 0.16019466 | AJ8: =MAX(1,(F8+Premissas!$B$45+Premissas!$B$48+INDEX('Frete 2026'!$H$6:$H$11,H8))/(1-$J$4-$B$4)) -> 142.96602 | AK8: =CEILING(AJ8-4.9,5)+4.9 -> 144.9 | AL8: =((AK8)-(F8+Premissas!$B$45+Premissas!$B$48+INDEX('Frete 2026'!$H$6:$H$11,H8)+(AK8)*$J$4))/(AK8) -> 0.15496197 | AM8: =IF(((AK8)-(F8+Premissas!$B$45+Premissas!$B$48+INDEX('Frete 2026'!$H$6:$H$11,H8)+(AK8)*$J$4))/(AK8)>=$B$4,AK8,IF(((AK8+5)-(F8+Premissas!$B$45+Premissas!$B$48+INDEX('Frete 2026'!$H$6:$H$11,H8)+(AK8+5)*$J$4))/(AK8+5)>=$B$4,AK8+5,AK8+10)) -> 144.9 | AN8: =((AM8)-(F8+Premissas!$B$45+Premissas!$B$48+INDEX('Frete 2026'!$H$6:$H$11,H8)+(AM8)*$J$4))/(AM8) -> 0.15496197
A9: Popular | B9: 5 | C9: =MATCH(A9,'Ficha de Custo'!$B$4:$D$4,0) -> 1 | D9: =INDEX('Ficha de Custo'!$B$14:$D$14,C9) -> 10.43 | E9: =INDEX('Ficha de Custo'!$B$18:$D$21,MATCH(B9,'Ficha de Custo'!$A$18:$A$21,0),C9) -> 1.1 | F9: =D9*B9+E9 -> 53.25 | G9: =INDEX('Ficha de Custo'!$B$36:$D$39,MATCH(B9,'Ficha de Custo'!$A$36:$A$39,0),C9) -> 0.9 | H9: =MATCH(G9-0.0000001,'Frete 2026'!$A$6:$A$11,1) -> 3 | I9: =IF((1-$D$4-$B$4)<=0,"",IF(MAX(1,(F9+INDEX('Frete 2026'!$B$6:$B$11,H9))/(1-$D$4-$B$4))<79,MAX(1,(F9+INDEX('Frete 2026'!$B$6:$B$11,H9))/(1-$D$4-$B$4)),"")) | J9: =IF((1-$D$4-$B$4)<=0,"",IF(MAX('Frete 2026'!$C$5,(F9+INDEX('Frete 2026'!$C$6:$C$11,H9))/(1-$D$4-$B$4))<'Frete 2026'!$D$5,MAX('Frete 2026'!$C$5,(F9+INDEX('Frete 2026'!$C$6:$C$11,H9))/(1-$D$4-$B$4)),"")) | K9: =IF((1-$D$4-$B$4)<=0,"",IF(MAX('Frete 2026'!$D$5,(F9+INDEX('Frete 2026'!$D$6:$D$11,H9))/(1-$D$4-$B$4))<'Frete 2026'!$E$5,MAX('Frete 2026'!$D$5,(F9+INDEX('Frete 2026'!$D$6:$D$11,H9))/(1-$D$4-$B$4)),"")) | L9: =IF((1-$D$4-$B$4)<=0,"",IF(MAX('Frete 2026'!$E$5,(F9+INDEX('Frete 2026'!$E$6:$E$11,H9))/(1-$D$4-$B$4))<'Frete 2026'!$F$5,MAX('Frete 2026'!$E$5,(F9+INDEX('Frete 2026'!$E$6:$E$11,H9))/(1-$D$4-$B$4)),"")) -> 128.10811 | M9: =IF((1-$D$4-$B$4)<=0,"",IF(MAX('Frete 2026'!$F$5,(F9+INDEX('Frete 2026'!$F$6:$F$11,H9))/(1-$D$4-$B$4))<'Frete 2026'!$G$5,MAX('Frete 2026'!$F$5,(F9+INDEX('Frete 2026'!$F$6:$F$11,H9))/(1-$D$4-$B$4)),"")) -> 150 | N9: =IF((1-$D$4-$B$4)<=0,"",IF(MAX('Frete 2026'!$G$5,(F9+INDEX('Frete 2026'!$G$6:$G$11,H9))/(1-$D$4-$B$4))<1000000000,MAX('Frete 2026'!$G$5,(F9+INDEX('Frete 2026'!$G$6:$G$11,H9))/(1-$D$4-$B$4)),"")) -> 200 | O9: =MIN(I9:N9) -> 128.10811 | P9: =CEILING(O9-4.9,5)+4.9 -> 129.9 | Q9: =((P9)-(F9+IF((P9)<79,INDEX('Frete 2026'!$B$6:$B$11,H9),INDEX('Frete 2026'!$C$6:$G$11,H9,MATCH((P9),'Frete 2026'!$C$5:$G$5,1)))+(P9)*$D$4))/(P9) -> 0.15765589 | R9: =IF(((P9)-(F9+IF((P9)<79,INDEX('Frete 2026'!$B$6:$B$11,H9),INDEX('Frete 2026'!$C$6:$G$11,H9,MATCH((P9),'Frete 2026'!$C$5:$G$5,1)))+(P9)*$D$4))/(P9)>=$B$4,P9,IF(((P9+5)-(F9+IF((P9+5)<79,INDEX('Frete 2026'!$B$6:$B$11,H9),INDEX('Frete 2026'!$C$6:$G$11,H9,MATCH((P9+5),'Frete 2026'!$C$5:$G$5,1)))+(P9+5)*$D$4))/(P9+5)>=$B$4,P9+5,P9+10)) -> 129.9 | S9: =((R9)-(F9+IF((R9)<79,INDEX('Frete 2026'!$B$6:$B$11,H9),INDEX('Frete 2026'!$C$6:$G$11,H9,MATCH((R9),'Frete 2026'!$C$5:$G$5,1)))+(R9)*$D$4))/(R9) -> 0.15765589 | T9: =IF((1-'Taxas 2026'!$C$16-$F$4-$B$4)<=0,"",IF(MAX('Taxas 2026'!$B$16,(F9+'Taxas 2026'!$D$16+Premissas!$B$34)/(1-'Taxas 2026'!$C$16-$F$4-$B$4))<'Taxas 2026'!$B$17,MAX('Taxas 2026'!$B$16,(F9+'Taxas 2026'!$D$16+Premissas!$B$34)/(1-'Taxas 2026'!$C$16-$F$4-$B$4)),"")) | U9: =IF((1-'Taxas 2026'!$C$17-$F$4-$B$4)<=0,"",IF(MAX('Taxas 2026'!$B$17,(F9+'Taxas 2026'!$D$17+Premissas!$B$34)/(1-'Taxas 2026'!$C$17-$F$4-$B$4))<'Taxas 2026'!$B$18,MAX('Taxas 2026'!$B$17,(F9+'Taxas 2026'!$D$17+Premissas!$B$34)/(1-'Taxas 2026'!$C$17-$F$4-$B$4)),"")) | V9: =IF((1-'Taxas 2026'!$C$18-$F$4-$B$4)<=0,"",IF(MAX('Taxas 2026'!$B$18,(F9+'Taxas 2026'!$D$18+Premissas!$B$34)/(1-'Taxas 2026'!$C$18-$F$4-$B$4))<'Taxas 2026'!$B$19,MAX('Taxas 2026'!$B$18,(F9+'Taxas 2026'!$D$18+Premissas!$B$34)/(1-'Taxas 2026'!$C$18-$F$4-$B$4)),"")) -> 136.91589 | W9: =IF((1-'Taxas 2026'!$C$19-$F$4-$B$4)<=0,"",IF(MAX('Taxas 2026'!$B$19,(F9+'Taxas 2026'!$D$19+Premissas!$B$34)/(1-'Taxas 2026'!$C$19-$F$4-$B$4))<1000000000,MAX('Taxas 2026'!$B$19,(F9+'Taxas 2026'!$D$19+Premissas!$B$34)/(1-'Taxas 2026'!$C$19-$F$4-$B$4)),"")) -> 200 | X9: =MIN(T9:W9) -> 136.91589 | Y9: =CEILING(X9-4.9,5)+4.9 -> 139.9 | Z9: =((Y9)-(F9+(Y9)*(INDEX('Taxas 2026'!$C$15:$C$19,MATCH((Y9),'Taxas 2026'!$B$15:$B$19,1))+$F$4)+INDEX('Taxas 2026'!$D$15:$D$19,MATCH((Y9),'Taxas 2026'!$B$15:$B$19,1))+Premissas!$B$34))/(Y9) -> 0.16141172 | AA9: =IF(((Y9)-(F9+(Y9)*(INDEX('Taxas 2026'!$C$15:$C$19,MATCH((Y9),'Taxas 2026'!$B$15:$B$19,1))+$F$4)+INDEX('Taxas 2026'!$D$15:$D$19,MATCH((Y9),'Taxas 2026'!$B$15:$B$19,1))+Premissas!$B$34))/(Y9)>=$B$4,Y9,IF(((Y9+5)-(F9+(Y9+5)*(INDEX('Taxas 2026'!$C$15:$C$19,MATCH((Y9+5),'Taxas 2026'!$B$15:$B$19,1))+$F$4)+INDEX('Taxas 2026'!$D$15:$D$19,MATCH((Y9+5),'Taxas 2026'!$B$15:$B$19,1))+Premissas!$B$34))/(Y9+5)>=$B$4,Y9+5,Y9+10)) -> 139.9 | AB9: =((AA9)-(F9+(AA9)*(INDEX('Taxas 2026'!$C$15:$C$19,MATCH((AA9),'Taxas 2026'!$B$15:$B$19,1))+$F$4)+INDEX('Taxas 2026'!$D$15:$D$19,MATCH((AA9),'Taxas 2026'!$B$15:$B$19,1))+Premissas!$B$34))/(AA9) -> 0.16141172 | AC9: =IF((1-'Taxas 2026'!$C$24-$H$4-$B$4)<=0,"",IF(MAX(1,(F9+'Taxas 2026'!$D$24)/(1-'Taxas 2026'!$C$24-$H$4-$B$4))<'Taxas 2026'!$B$25,MAX(1,(F9+'Taxas 2026'!$D$24)/(1-'Taxas 2026'!$C$24-$H$4-$B$4)),"")) | AD9: =IF((1-'Taxas 2026'!$C$25-$H$4-$B$4)<=0,"",IF(MAX('Taxas 2026'!$B$25,(F9+'Taxas 2026'!$D$25)/(1-'Taxas 2026'!$C$25-$H$4-$B$4))<1000000000,MAX('Taxas 2026'!$B$25,(F9+'Taxas 2026'!$D$25)/(1-'Taxas 2026'!$C$25-$H$4-$B$4)),"")) -> 136.2069 | AE9: =MIN(AC9:AD9) -> 136.2069 | AF9: =CEILING(AE9-4.9,5)+4.9 -> 139.9 | AG9: =((AF9)-(F9+(AF9)*(INDEX('Taxas 2026'!$C$24:$C$25,MATCH((AF9),'Taxas 2026'!$B$24:$B$25,1))+$H$4)+INDEX('Taxas 2026'!$D$24:$D$25,MATCH((AF9),'Taxas 2026'!$B$24:$B$25,1))))/(AF9) -> 0.1614832 | AH9: =IF(((AF9)-(F9+(AF9)*(INDEX('Taxas 2026'!$C$24:$C$25,MATCH((AF9),'Taxas 2026'!$B$24:$B$25,1))+$H$4)+INDEX('Taxas 2026'!$D$24:$D$25,MATCH((AF9),'Taxas 2026'!$B$24:$B$25,1))))/(AF9)>=$B$4,AF9,IF(((AF9+5)-(F9+(AF9+5)*(INDEX('Taxas 2026'!$C$24:$C$25,MATCH((AF9+5),'Taxas 2026'!$B$24:$B$25,1))+$H$4)+INDEX('Taxas 2026'!$D$24:$D$25,MATCH((AF9+5),'Taxas 2026'!$B$24:$B$25,1))))/(AF9+5)>=$B$4,AF9+5,AF9+10)) -> 139.9 | AI9: =((AH9)-(F9+(AH9)*(INDEX('Taxas 2026'!$C$24:$C$25,MATCH((AH9),'Taxas 2026'!$B$24:$B$25,1))+$H$4)+INDEX('Taxas 2026'!$D$24:$D$25,MATCH((AH9),'Taxas 2026'!$B$24:$B$25,1))))/(AH9) -> 0.1614832 | AJ9: =MAX(1,(F9+Premissas!$B$45+Premissas!$B$48+INDEX('Frete 2026'!$H$6:$H$11,H9))/(1-$J$4-$B$4)) -> 199.61445 | AK9: =CEILING(AJ9-4.9,5)+4.9 -> 199.9 | AL9: =((AK9)-(F9+Premissas!$B$45+Premissas!$B$48+INDEX('Frete 2026'!$H$6:$H$11,H9)+(AK9)*$J$4))/(AK9) -> 0.15053105 | AM9: =IF(((AK9)-(F9+Premissas!$B$45+Premissas!$B$48+INDEX('Frete 2026'!$H$6:$H$11,H9)+(AK9)*$J$4))/(AK9)>=$B$4,AK9,IF(((AK9+5)-(F9+Premissas!$B$45+Premissas!$B$48+INDEX('Frete 2026'!$H$6:$H$11,H9)+(AK9+5)*$J$4))/(AK9+5)>=$B$4,AK9+5,AK9+10)) -> 199.9 | AN9: =((AM9)-(F9+Premissas!$B$45+Premissas!$B$48+INDEX('Frete 2026'!$H$6:$H$11,H9)+(AM9)*$J$4))/(AM9) -> 0.15053105
A10: Popular | B10: 10 | C10: =MATCH(A10,'Ficha de Custo'!$B$4:$D$4,0) -> 1 | D10: =INDEX('Ficha de Custo'!$B$14:$D$14,C10) -> 10.43 | E10: =INDEX('Ficha de Custo'!$B$18:$D$21,MATCH(B10,'Ficha de Custo'!$A$18:$A$21,0),C10) -> 1.6 | F10: =D10*B10+E10 -> 105.9 | G10: =INDEX('Ficha de Custo'!$B$36:$D$39,MATCH(B10,'Ficha de Custo'!$A$36:$A$39,0),C10) -> 1.74 | H10: =MATCH(G10-0.0000001,'Frete 2026'!$A$6:$A$11,1) -> 5 | I10: =IF((1-$D$4-$B$4)<=0,"",IF(MAX(1,(F10+INDEX('Frete 2026'!$B$6:$B$11,H10))/(1-$D$4-$B$4))<79,MAX(1,(F10+INDEX('Frete 2026'!$B$6:$B$11,H10))/(1-$D$4-$B$4)),"")) | J10: =IF((1-$D$4-$B$4)<=0,"",IF(MAX('Frete 2026'!$C$5,(F10+INDEX('Frete 2026'!$C$6:$C$11,H10))/(1-$D$4-$B$4))<'Frete 2026'!$D$5,MAX('Frete 2026'!$C$5,(F10+INDEX('Frete 2026'!$C$6:$C$11,H10))/(1-$D$4-$B$4)),"")) | K10: =IF((1-$D$4-$B$4)<=0,"",IF(MAX('Frete 2026'!$D$5,(F10+INDEX('Frete 2026'!$D$6:$D$11,H10))/(1-$D$4-$B$4))<'Frete 2026'!$E$5,MAX('Frete 2026'!$D$5,(F10+INDEX('Frete 2026'!$D$6:$D$11,H10))/(1-$D$4-$B$4)),"")) | L10: =IF((1-$D$4-$B$4)<=0,"",IF(MAX('Frete 2026'!$E$5,(F10+INDEX('Frete 2026'!$E$6:$E$11,H10))/(1-$D$4-$B$4))<'Frete 2026'!$F$5,MAX('Frete 2026'!$E$5,(F10+INDEX('Frete 2026'!$E$6:$E$11,H10))/(1-$D$4-$B$4)),"")) | M10: =IF((1-$D$4-$B$4)<=0,"",IF(MAX('Frete 2026'!$F$5,(F10+INDEX('Frete 2026'!$F$6:$F$11,H10))/(1-$D$4-$B$4))<'Frete 2026'!$G$5,MAX('Frete 2026'!$F$5,(F10+INDEX('Frete 2026'!$F$6:$F$11,H10))/(1-$D$4-$B$4)),"")) | N10: =IF((1-$D$4-$B$4)<=0,"",IF(MAX('Frete 2026'!$G$5,(F10+INDEX('Frete 2026'!$G$6:$G$11,H10))/(1-$D$4-$B$4))<1000000000,MAX('Frete 2026'!$G$5,(F10+INDEX('Frete 2026'!$G$6:$G$11,H10))/(1-$D$4-$B$4)),"")) -> 235.22523 | O10: =MIN(I10:N10) -> 235.22523 | P10: =CEILING(O10-4.9,5)+4.9 -> 239.9 | Q10: =((P10)-(F10+IF((P10)<79,INDEX('Frete 2026'!$B$6:$B$11,H10),INDEX('Frete 2026'!$C$6:$G$11,H10,MATCH((P10),'Frete 2026'!$C$5:$G$5,1)))+(P10)*$D$4))/(P10) -> 0.16081492 | R10: =IF(((P10)-(F10+IF((P10)<79,INDEX('Frete 2026'!$B$6:$B$11,H10),INDEX('Frete 2026'!$C$6:$G$11,H10,MATCH((P10),'Frete 2026'!$C$5:$G$5,1)))+(P10)*$D$4))/(P10)>=$B$4,P10,IF(((P10+5)-(F10+IF((P10+5)<79,INDEX('Frete 2026'!$B$6:$B$11,H10),INDEX('Frete 2026'!$C$6:$G$11,H10,MATCH((P10+5),'Frete 2026'!$C$5:$G$5,1)))+(P10+5)*$D$4))/(P10+5)>=$B$4,P10+5,P10+10)) -> 239.9 | S10: =((R10)-(F10+IF((R10)<79,INDEX('Frete 2026'!$B$6:$B$11,H10),INDEX('Frete 2026'!$C$6:$G$11,H10,MATCH((R10),'Frete 2026'!$C$5:$G$5,1)))+(R10)*$D$4))/(R10) -> 0.16081492 | T10: =IF((1-'Taxas 2026'!$C$16-$F$4-$B$4)<=0,"",IF(MAX('Taxas 2026'!$B$16,(F10+'Taxas 2026'!$D$16+Premissas!$B$34)/(1-'Taxas 2026'!$C$16-$F$4-$B$4))<'Taxas 2026'!$B$17,MAX('Taxas 2026'!$B$16,(F10+'Taxas 2026'!$D$16+Premissas!$B$34)/(1-'Taxas 2026'!$C$16-$F$4-$B$4)),"")) | U10: =IF((1-'Taxas 2026'!$C$17-$F$4-$B$4)<=0,"",IF(MAX('Taxas 2026'!$B$17,(F10+'Taxas 2026'!$D$17+Premissas!$B$34)/(1-'Taxas 2026'!$C$17-$F$4-$B$4))<'Taxas 2026'!$B$18,MAX('Taxas 2026'!$B$17,(F10+'Taxas 2026'!$D$17+Premissas!$B$34)/(1-'Taxas 2026'!$C$17-$F$4-$B$4)),"")) | V10: =IF((1-'Taxas 2026'!$C$18-$F$4-$B$4)<=0,"",IF(MAX('Taxas 2026'!$B$18,(F10+'Taxas 2026'!$D$18+Premissas!$B$34)/(1-'Taxas 2026'!$C$18-$F$4-$B$4))<'Taxas 2026'!$B$19,MAX('Taxas 2026'!$B$18,(F10+'Taxas 2026'!$D$18+Premissas!$B$34)/(1-'Taxas 2026'!$C$18-$F$4-$B$4)),"")) | W10: =IF((1-'Taxas 2026'!$C$19-$F$4-$B$4)<=0,"",IF(MAX('Taxas 2026'!$B$19,(F10+'Taxas 2026'!$D$19+Premissas!$B$34)/(1-'Taxas 2026'!$C$19-$F$4-$B$4))<1000000000,MAX('Taxas 2026'!$B$19,(F10+'Taxas 2026'!$D$19+Premissas!$B$34)/(1-'Taxas 2026'!$C$19-$F$4-$B$4)),"")) -> 246.54206 | X10: =MIN(T10:W10) -> 246.54206 | Y10: =CEILING(X10-4.9,5)+4.9 -> 249.9 | Z10: =((Y10)-(F10+(Y10)*(INDEX('Taxas 2026'!$C$15:$C$19,MATCH((Y10),'Taxas 2026'!$B$15:$B$19,1))+$F$4)+INDEX('Taxas 2026'!$D$15:$D$19,MATCH((Y10),'Taxas 2026'!$B$15:$B$19,1))+Premissas!$B$34))/(Y10) -> 0.15718888 | AA10: =IF(((Y10)-(F10+(Y10)*(INDEX('Taxas 2026'!$C$15:$C$19,MATCH((Y10),'Taxas 2026'!$B$15:$B$19,1))+$F$4)+INDEX('Taxas 2026'!$D$15:$D$19,MATCH((Y10),'Taxas 2026'!$B$15:$B$19,1))+Premissas!$B$34))/(Y10)>=$B$4,Y10,IF(((Y10+5)-(F10+(Y10+5)*(INDEX('Taxas 2026'!$C$15:$C$19,MATCH((Y10+5),'Taxas 2026'!$B$15:$B$19,1))+$F$4)+INDEX('Taxas 2026'!$D$15:$D$19,MATCH((Y10+5),'Taxas 2026'!$B$15:$B$19,1))+Premissas!$B$34))/(Y10+5)>=$B$4,Y10+5,Y10+10)) -> 249.9 | AB10: =((AA10)-(F10+(AA10)*(INDEX('Taxas 2026'!$C$15:$C$19,MATCH((AA10),'Taxas 2026'!$B$15:$B$19,1))+$F$4)+INDEX('Taxas 2026'!$D$15:$D$19,MATCH((AA10),'Taxas 2026'!$B$15:$B$19,1))+Premissas!$B$34))/(AA10) -> 0.15718888 | AC10: =IF((1-'Taxas 2026'!$C$24-$H$4-$B$4)<=0,"",IF(MAX(1,(F10+'Taxas 2026'!$D$24)/(1-'Taxas 2026'!$C$24-$H$4-$B$4))<'Taxas 2026'!$B$25,MAX(1,(F10+'Taxas 2026'!$D$24)/(1-'Taxas 2026'!$C$24-$H$4-$B$4)),"")) | AD10: =IF((1-'Taxas 2026'!$C$25-$H$4-$B$4)<=0,"",IF(MAX('Taxas 2026'!$B$25,(F10+'Taxas 2026'!$D$25)/(1-'Taxas 2026'!$C$25-$H$4-$B$4))<1000000000,MAX('Taxas 2026'!$B$25,(F10+'Taxas 2026'!$D$25)/(1-'Taxas 2026'!$C$25-$H$4-$B$4)),"")) -> 257.24138 | AE10: =MIN(AC10:AD10) -> 257.24138 | AF10: =CEILING(AE10-4.9,5)+4.9 -> 259.9 | AG10: =((AF10)-(F10+(AF10)*(INDEX('Taxas 2026'!$C$24:$C$25,MATCH((AF10),'Taxas 2026'!$B$24:$B$25,1))+$H$4)+INDEX('Taxas 2026'!$D$24:$D$25,MATCH((AF10),'Taxas 2026'!$B$24:$B$25,1))))/(AF10) -> 0.15444979 | AH10: =IF(((AF10)-(F10+(AF10)*(INDEX('Taxas 2026'!$C$24:$C$25,MATCH((AF10),'Taxas 2026'!$B$24:$B$25,1))+$H$4)+INDEX('Taxas 2026'!$D$24:$D$25,MATCH((AF10),'Taxas 2026'!$B$24:$B$25,1))))/(AF10)>=$B$4,AF10,IF(((AF10+5)-(F10+(AF10+5)*(INDEX('Taxas 2026'!$C$24:$C$25,MATCH((AF10+5),'Taxas 2026'!$B$24:$B$25,1))+$H$4)+INDEX('Taxas 2026'!$D$24:$D$25,MATCH((AF10+5),'Taxas 2026'!$B$24:$B$25,1))))/(AF10+5)>=$B$4,AF10+5,AF10+10)) -> 259.9 | AI10: =((AH10)-(F10+(AH10)*(INDEX('Taxas 2026'!$C$24:$C$25,MATCH((AH10),'Taxas 2026'!$B$24:$B$25,1))+$H$4)+INDEX('Taxas 2026'!$D$24:$D$25,MATCH((AH10),'Taxas 2026'!$B$24:$B$25,1))))/(AH10) -> 0.15444979 | AJ10: =MAX(1,(F10+Premissas!$B$45+Premissas!$B$48+INDEX('Frete 2026'!$H$6:$H$11,H10))/(1-$J$4-$B$4)) -> 357.3747 | AK10: =CEILING(AJ10-4.9,5)+4.9 -> 359.9 | AL10: =((AK10)-(F10+Premissas!$B$45+Premissas!$B$48+INDEX('Frete 2026'!$H$6:$H$11,H10)+(AK10)*$J$4))/(AK10) -> 0.15260857 | AM10: =IF(((AK10)-(F10+Premissas!$B$45+Premissas!$B$48+INDEX('Frete 2026'!$H$6:$H$11,H10)+(AK10)*$J$4))/(AK10)>=$B$4,AK10,IF(((AK10+5)-(F10+Premissas!$B$45+Premissas!$B$48+INDEX('Frete 2026'!$H$6:$H$11,H10)+(AK10+5)*$J$4))/(AK10+5)>=$B$4,AK10+5,AK10+10)) -> 359.9 | AN10: =((AM10)-(F10+Premissas!$B$45+Premissas!$B$48+INDEX('Frete 2026'!$H$6:$H$11,H10)+(AM10)*$J$4))/(AM10) -> 0.15260857
A11: Essencial | B11: 1 | C11: =MATCH(A11,'Ficha de Custo'!$B$4:$D$4,0) -> 2 | D11: =INDEX('Ficha de Custo'!$B$14:$D$14,C11) -> 20.52 | E11: =INDEX('Ficha de Custo'!$B$18:$D$21,MATCH(B11,'Ficha de Custo'!$A$18:$A$21,0),C11) -> 1.5 | F11: =D11*B11+E11 -> 22.02 | G11: =INDEX('Ficha de Custo'!$B$36:$D$39,MATCH(B11,'Ficha de Custo'!$A$36:$A$39,0),C11) -> 0.23 | H11: =MATCH(G11-0.0000001,'Frete 2026'!$A$6:$A$11,1) -> 1 | I11: =IF((1-$D$4-$B$4)<=0,"",IF(MAX(1,(F11+INDEX('Frete 2026'!$B$6:$B$11,H11))/(1-$D$4-$B$4))<79,MAX(1,(F11+INDEX('Frete 2026'!$B$6:$B$11,H11))/(1-$D$4-$B$4)),"")) -> 51.387387 | J11: =IF((1-$D$4-$B$4)<=0,"",IF(MAX('Frete 2026'!$C$5,(F11+INDEX('Frete 2026'!$C$6:$C$11,H11))/(1-$D$4-$B$4))<'Frete 2026'!$D$5,MAX('Frete 2026'!$C$5,(F11+INDEX('Frete 2026'!$C$6:$C$11,H11))/(1-$D$4-$B$4)),"")) -> 79 | K11: =IF((1-$D$4-$B$4)<=0,"",IF(MAX('Frete 2026'!$D$5,(F11+INDEX('Frete 2026'!$D$6:$D$11,H11))/(1-$D$4-$B$4))<'Frete 2026'!$E$5,MAX('Frete 2026'!$D$5,(F11+INDEX('Frete 2026'!$D$6:$D$11,H11))/(1-$D$4-$B$4)),"")) -> 100 | L11: =IF((1-$D$4-$B$4)<=0,"",IF(MAX('Frete 2026'!$E$5,(F11+INDEX('Frete 2026'!$E$6:$E$11,H11))/(1-$D$4-$B$4))<'Frete 2026'!$F$5,MAX('Frete 2026'!$E$5,(F11+INDEX('Frete 2026'!$E$6:$E$11,H11))/(1-$D$4-$B$4)),"")) -> 120 | M11: =IF((1-$D$4-$B$4)<=0,"",IF(MAX('Frete 2026'!$F$5,(F11+INDEX('Frete 2026'!$F$6:$F$11,H11))/(1-$D$4-$B$4))<'Frete 2026'!$G$5,MAX('Frete 2026'!$F$5,(F11+INDEX('Frete 2026'!$F$6:$F$11,H11))/(1-$D$4-$B$4)),"")) -> 150 | N11: =IF((1-$D$4-$B$4)<=0,"",IF(MAX('Frete 2026'!$G$5,(F11+INDEX('Frete 2026'!$G$6:$G$11,H11))/(1-$D$4-$B$4))<1000000000,MAX('Frete 2026'!$G$5,(F11+INDEX('Frete 2026'!$G$6:$G$11,H11))/(1-$D$4-$B$4)),"")) -> 200 | O11: =MIN(I11:N11) -> 51.387387 | P11: =CEILING(O11-4.9,5)+4.9 -> 54.9 | Q11: =((P11)-(F11+IF((P11)<79,INDEX('Frete 2026'!$B$6:$B$11,H11),INDEX('Frete 2026'!$C$6:$G$11,H11,MATCH((P11),'Frete 2026'!$C$5:$G$5,1)))+(P11)*$D$4))/(P11) -> 0.18551002 | R11: =IF(((P11)-(F11+IF((P11)<79,INDEX('Frete 2026'!$B$6:$B$11,H11),INDEX('Frete 2026'!$C$6:$G$11,H11,MATCH((P11),'Frete 2026'!$C$5:$G$5,1)))+(P11)*$D$4))/(P11)>=$B$4,P11,IF(((P11+5)-(F11+IF((P11+5)<79,INDEX('Frete 2026'!$B$6:$B$11,H11),INDEX('Frete 2026'!$C$6:$G$11,H11,MATCH((P11+5),'Frete 2026'!$C$5:$G$5,1)))+(P11+5)*$D$4))/(P11+5)>=$B$4,P11+5,P11+10)) -> 54.9 | S11: =((R11)-(F11+IF((R11)<79,INDEX('Frete 2026'!$B$6:$B$11,H11),INDEX('Frete 2026'!$C$6:$G$11,H11,MATCH((R11),'Frete 2026'!$C$5:$G$5,1)))+(R11)*$D$4))/(R11) -> 0.18551002 | T11: =IF((1-'Taxas 2026'!$C$16-$F$4-$B$4)<=0,"",IF(MAX('Taxas 2026'!$B$16,(F11+'Taxas 2026'!$D$16+Premissas!$B$34)/(1-'Taxas 2026'!$C$16-$F$4-$B$4))<'Taxas 2026'!$B$17,MAX('Taxas 2026'!$B$16,(F11+'Taxas 2026'!$D$16+Premissas!$B$34)/(1-'Taxas 2026'!$C$16-$F$4-$B$4)),"")) -> 54.778947 | U11: =IF((1-'Taxas 2026'!$C$17-$F$4-$B$4)<=0,"",IF(MAX('Taxas 2026'!$B$17,(F11+'Taxas 2026'!$D$17+Premissas!$B$34)/(1-'Taxas 2026'!$C$17-$F$4-$B$4))<'Taxas 2026'!$B$18,MAX('Taxas 2026'!$B$17,(F11+'Taxas 2026'!$D$17+Premissas!$B$34)/(1-'Taxas 2026'!$C$17-$F$4-$B$4)),"")) -> 80 | V11: =IF((1-'Taxas 2026'!$C$18-$F$4-$B$4)<=0,"",IF(MAX('Taxas 2026'!$B$18,(F11+'Taxas 2026'!$D$18+Premissas!$B$34)/(1-'Taxas 2026'!$C$18-$F$4-$B$4))<'Taxas 2026'!$B$19,MAX('Taxas 2026'!$B$18,(F11+'Taxas 2026'!$D$18+Premissas!$B$34)/(1-'Taxas 2026'!$C$18-$F$4-$B$4)),"")) -> 100 | W11: =IF((1-'Taxas 2026'!$C$19-$F$4-$B$4)<=0,"",IF(MAX('Taxas 2026'!$B$19,(F11+'Taxas 2026'!$D$19+Premissas!$B$34)/(1-'Taxas 2026'!$C$19-$F$4-$B$4))<1000000000,MAX('Taxas 2026'!$B$19,(F11+'Taxas 2026'!$D$19+Premissas!$B$34)/(1-'Taxas 2026'!$C$19-$F$4-$B$4)),"")) -> 200 | X11: =MIN(T11:W11) -> 54.778947 | Y11: =CEILING(X11-4.9,5)+4.9 -> 54.9 | Z11: =((Y11)-(F11+(Y11)*(INDEX('Taxas 2026'!$C$15:$C$19,MATCH((Y11),'Taxas 2026'!$B$15:$B$19,1))+$F$4)+INDEX('Taxas 2026'!$D$15:$D$19,MATCH((Y11),'Taxas 2026'!$B$15:$B$19,1))+Premissas!$B$34))/(Y11) -> 0.15104736 | AA11: =IF(((Y11)-(F11+(Y11)*(INDEX('Taxas 2026'!$C$15:$C$19,MATCH((Y11),'Taxas 2026'!$B$15:$B$19,1))+$F$4)+INDEX('Taxas 2026'!$D$15:$D$19,MATCH((Y11),'Taxas 2026'!$B$15:$B$19,1))+Premissas!$B$34))/(Y11)>=$B$4,Y11,IF(((Y11+5)-(F11+(Y11+5)*(INDEX('Taxas 2026'!$C$15:$C$19,MATCH((Y11+5),'Taxas 2026'!$B$15:$B$19,1))+$F$4)+INDEX('Taxas 2026'!$D$15:$D$19,MATCH((Y11+5),'Taxas 2026'!$B$15:$B$19,1))+Premissas!$B$34))/(Y11+5)>=$B$4,Y11+5,Y11+10)) -> 54.9 | AB11: =((AA11)-(F11+(AA11)*(INDEX('Taxas 2026'!$C$15:$C$19,MATCH((AA11),'Taxas 2026'!$B$15:$B$19,1))+$F$4)+INDEX('Taxas 2026'!$D$15:$D$19,MATCH((AA11),'Taxas 2026'!$B$15:$B$19,1))+Premissas!$B$34))/(AA11) -> 0.15104736 | AC11: =IF((1-'Taxas 2026'!$C$24-$H$4-$B$4)<=0,"",IF(MAX(1,(F11+'Taxas 2026'!$D$24)/(1-'Taxas 2026'!$C$24-$H$4-$B$4))<'Taxas 2026'!$B$25,MAX(1,(F11+'Taxas 2026'!$D$24)/(1-'Taxas 2026'!$C$24-$H$4-$B$4)),"")) | AD11: =IF((1-'Taxas 2026'!$C$25-$H$4-$B$4)<=0,"",IF(MAX('Taxas 2026'!$B$25,(F11+'Taxas 2026'!$D$25)/(1-'Taxas 2026'!$C$25-$H$4-$B$4))<1000000000,MAX('Taxas 2026'!$B$25,(F11+'Taxas 2026'!$D$25)/(1-'Taxas 2026'!$C$25-$H$4-$B$4)),"")) -> 64.413793 | AE11: =MIN(AC11:AD11) -> 64.413793 | AF11: =CEILING(AE11-4.9,5)+4.9 -> 64.9 | AG11: =((AF11)-(F11+(AF11)*(INDEX('Taxas 2026'!$C$24:$C$25,MATCH((AF11),'Taxas 2026'!$B$24:$B$25,1))+$H$4)+INDEX('Taxas 2026'!$D$24:$D$25,MATCH((AF11),'Taxas 2026'!$B$24:$B$25,1))))/(AF11) -> 0.15325886 | AH11: =IF(((AF11)-(F11+(AF11)*(INDEX('Taxas 2026'!$C$24:$C$25,MATCH((AF11),'Taxas 2026'!$B$24:$B$25,1))+$H$4)+INDEX('Taxas 2026'!$D$24:$D$25,MATCH((AF11),'Taxas 2026'!$B$24:$B$25,1))))/(AF11)>=$B$4,AF11,IF(((AF11+5)-(F11+(AF11+5)*(INDEX('Taxas 2026'!$C$24:$C$25,MATCH((AF11+5),'Taxas 2026'!$B$24:$B$25,1))+$H$4)+INDEX('Taxas 2026'!$D$24:$D$25,MATCH((AF11+5),'Taxas 2026'!$B$24:$B$25,1))))/(AF11+5)>=$B$4,AF11+5,AF11+10)) -> 64.9 | AI11: =((AH11)-(F11+(AH11)*(INDEX('Taxas 2026'!$C$24:$C$25,MATCH((AH11),'Taxas 2026'!$B$24:$B$25,1))+$H$4)+INDEX('Taxas 2026'!$D$24:$D$25,MATCH((AH11),'Taxas 2026'!$B$24:$B$25,1))))/(AH11) -> 0.15325886 | AJ11: =MAX(1,(F11+Premissas!$B$45+Premissas!$B$48+INDEX('Frete 2026'!$H$6:$H$11,H11))/(1-$J$4-$B$4)) -> 107.54057 | AK11: =CEILING(AJ11-4.9,5)+4.9 -> 109.9 | AL11: =((AK11)-(F11+Premissas!$B$45+Premissas!$B$48+INDEX('Frete 2026'!$H$6:$H$11,H11)+(AK11)*$J$4))/(AK11) -> 0.15798141 | AM11: =IF(((AK11)-(F11+Premissas!$B$45+Premissas!$B$48+INDEX('Frete 2026'!$H$6:$H$11,H11)+(AK11)*$J$4))/(AK11)>=$B$4,AK11,IF(((AK11+5)-(F11+Premissas!$B$45+Premissas!$B$48+INDEX('Frete 2026'!$H$6:$H$11,H11)+(AK11+5)*$J$4))/(AK11+5)>=$B$4,AK11+5,AK11+10)) -> 109.9 | AN11: =((AM11)-(F11+Premissas!$B$45+Premissas!$B$48+INDEX('Frete 2026'!$H$6:$H$11,H11)+(AM11)*$J$4))/(AM11) -> 0.15798141
A12: Essencial | B12: 3 | C12: =MATCH(A12,'Ficha de Custo'!$B$4:$D$4,0) -> 2 | D12: =INDEX('Ficha de Custo'!$B$14:$D$14,C12) -> 20.52 | E12: =INDEX('Ficha de Custo'!$B$18:$D$21,MATCH(B12,'Ficha de Custo'!$A$18:$A$21,0),C12) -> 4.5 | F12: =D12*B12+E12 -> 66.06 | G12: =INDEX('Ficha de Custo'!$B$36:$D$39,MATCH(B12,'Ficha de Custo'!$A$36:$A$39,0),C12) -> 0.68 | H12: =MATCH(G12-0.0000001,'Frete 2026'!$A$6:$A$11,1) -> 3 | I12: =IF((1-$D$4-$B$4)<=0,"",IF(MAX(1,(F12+INDEX('Frete 2026'!$B$6:$B$11,H12))/(1-$D$4-$B$4))<79,MAX(1,(F12+INDEX('Frete 2026'!$B$6:$B$11,H12))/(1-$D$4-$B$4)),"")) | J12: =IF((1-$D$4-$B$4)<=0,"",IF(MAX('Frete 2026'!$C$5,(F12+INDEX('Frete 2026'!$C$6:$C$11,H12))/(1-$D$4-$B$4))<'Frete 2026'!$D$5,MAX('Frete 2026'!$C$5,(F12+INDEX('Frete 2026'!$C$6:$C$11,H12))/(1-$D$4-$B$4)),"")) | K12: =IF((1-$D$4-$B$4)<=0,"",IF(MAX('Frete 2026'!$D$5,(F12+INDEX('Frete 2026'!$D$6:$D$11,H12))/(1-$D$4-$B$4))<'Frete 2026'!$E$5,MAX('Frete 2026'!$D$5,(F12+INDEX('Frete 2026'!$D$6:$D$11,H12))/(1-$D$4-$B$4)),"")) | L12: =IF((1-$D$4-$B$4)<=0,"",IF(MAX('Frete 2026'!$E$5,(F12+INDEX('Frete 2026'!$E$6:$E$11,H12))/(1-$D$4-$B$4))<'Frete 2026'!$F$5,MAX('Frete 2026'!$E$5,(F12+INDEX('Frete 2026'!$E$6:$E$11,H12))/(1-$D$4-$B$4)),"")) | M12: =IF((1-$D$4-$B$4)<=0,"",IF(MAX('Frete 2026'!$F$5,(F12+INDEX('Frete 2026'!$F$6:$F$11,H12))/(1-$D$4-$B$4))<'Frete 2026'!$G$5,MAX('Frete 2026'!$F$5,(F12+INDEX('Frete 2026'!$F$6:$F$11,H12))/(1-$D$4-$B$4)),"")) -> 155.06306 | N12: =IF((1-$D$4-$B$4)<=0,"",IF(MAX('Frete 2026'!$G$5,(F12+INDEX('Frete 2026'!$G$6:$G$11,H12))/(1-$D$4-$B$4))<1000000000,MAX('Frete 2026'!$G$5,(F12+INDEX('Frete 2026'!$G$6:$G$11,H12))/(1-$D$4-$B$4)),"")) -> 200 | O12: =MIN(I12:N12) -> 155.06306 | P12: =CEILING(O12-4.9,5)+4.9 -> 159.9 | Q12: =((P12)-(F12+IF((P12)<79,INDEX('Frete 2026'!$B$6:$B$11,H12),INDEX('Frete 2026'!$C$6:$G$11,H12,MATCH((P12),'Frete 2026'!$C$5:$G$5,1)))+(P12)*$D$4))/(P12) -> 0.16678862 | R12: =IF(((P12)-(F12+IF((P12)<79,INDEX('Frete 2026'!$B$6:$B$11,H12),INDEX('Frete 2026'!$C$6:$G$11,H12,MATCH((P12),'Frete 2026'!$C$5:$G$5,1)))+(P12)*$D$4))/(P12)>=$B$4,P12,IF(((P12+5)-(F12+IF((P12+5)<79,INDEX('Frete 2026'!$B$6:$B$11,H12),INDEX('Frete 2026'!$C$6:$G$11,H12,MATCH((P12+5),'Frete 2026'!$C$5:$G$5,1)))+(P12+5)*$D$4))/(P12+5)>=$B$4,P12+5,P12+10)) -> 159.9 | S12: =((R12)-(F12+IF((R12)<79,INDEX('Frete 2026'!$B$6:$B$11,H12),INDEX('Frete 2026'!$C$6:$G$11,H12,MATCH((R12),'Frete 2026'!$C$5:$G$5,1)))+(R12)*$D$4))/(R12) -> 0.16678862 | T12: =IF((1-'Taxas 2026'!$C$16-$F$4-$B$4)<=0,"",IF(MAX('Taxas 2026'!$B$16,(F12+'Taxas 2026'!$D$16+Premissas!$B$34)/(1-'Taxas 2026'!$C$16-$F$4-$B$4))<'Taxas 2026'!$B$17,MAX('Taxas 2026'!$B$16,(F12+'Taxas 2026'!$D$16+Premissas!$B$34)/(1-'Taxas 2026'!$C$16-$F$4-$B$4)),"")) | U12: =IF((1-'Taxas 2026'!$C$17-$F$4-$B$4)<=0,"",IF(MAX('Taxas 2026'!$B$17,(F12+'Taxas 2026'!$D$17+Premissas!$B$34)/(1-'Taxas 2026'!$C$17-$F$4-$B$4))<'Taxas 2026'!$B$18,MAX('Taxas 2026'!$B$17,(F12+'Taxas 2026'!$D$17+Premissas!$B$34)/(1-'Taxas 2026'!$C$17-$F$4-$B$4)),"")) | V12: =IF((1-'Taxas 2026'!$C$18-$F$4-$B$4)<=0,"",IF(MAX('Taxas 2026'!$B$18,(F12+'Taxas 2026'!$D$18+Premissas!$B$34)/(1-'Taxas 2026'!$C$18-$F$4-$B$4))<'Taxas 2026'!$B$19,MAX('Taxas 2026'!$B$18,(F12+'Taxas 2026'!$D$18+Premissas!$B$34)/(1-'Taxas 2026'!$C$18-$F$4-$B$4)),"")) -> 160.85981 | W12: =IF((1-'Taxas 2026'!$C$19-$F$4-$B$4)<=0,"",IF(MAX('Taxas 2026'!$B$19,(F12+'Taxas 2026'!$D$19+Premissas!$B$34)/(1-'Taxas 2026'!$C$19-$F$4-$B$4))<1000000000,MAX('Taxas 2026'!$B$19,(F12+'Taxas 2026'!$D$19+Premissas!$B$34)/(1-'Taxas 2026'!$C$19-$F$4-$B$4)),"")) -> 200 | X12: =MIN(T12:W12) -> 160.85981 | Y12: =CEILING(X12-4.9,5)+4.9 -> 164.9 | Z12: =((Y12)-(F12+(Y12)*(INDEX('Taxas 2026'!$C$15:$C$19,MATCH((Y12),'Taxas 2026'!$B$15:$B$19,1))+$F$4)+INDEX('Taxas 2026'!$D$15:$D$19,MATCH((Y12),'Taxas 2026'!$B$15:$B$19,1))+Premissas!$B$34))/(Y12) -> 0.16310794 | AA12: =IF(((Y12)-(F12+(Y12)*(INDEX('Taxas 2026'!$C$15:$C$19,MATCH((Y12),'Taxas 2026'!$B$15:$B$19,1))+$F$4)+INDEX('Taxas 2026'!$D$15:$D$19,MATCH((Y12),'Taxas 2026'!$B$15:$B$19,1))+Premissas!$B$34))/(Y12)>=$B$4,Y12,IF(((Y12+5)-(F12+(Y12+5)*(INDEX('Taxas 2026'!$C$15:$C$19,MATCH((Y12+5),'Taxas 2026'!$B$15:$B$19,1))+$F$4)+INDEX('Taxas 2026'!$D$15:$D$19,MATCH((Y12+5),'Taxas 2026'!$B$15:$B$19,1))+Premissas!$B$34))/(Y12+5)>=$B$4,Y12+5,Y12+10)) -> 164.9 | AB12: =((AA12)-(F12+(AA12)*(INDEX('Taxas 2026'!$C$15:$C$19,MATCH((AA12),'Taxas 2026'!$B$15:$B$19,1))+$F$4)+INDEX('Taxas 2026'!$D$15:$D$19,MATCH((AA12),'Taxas 2026'!$B$15:$B$19,1))+Premissas!$B$34))/(AA12) -> 0.16310794 | AC12: =IF((1-'Taxas 2026'!$C$24-$H$4-$B$4)<=0,"",IF(MAX(1,(F12+'Taxas 2026'!$D$24)/(1-'Taxas 2026'!$C$24-$H$4-$B$4))<'Taxas 2026'!$B$25,MAX(1,(F12+'Taxas 2026'!$D$24)/(1-'Taxas 2026'!$C$24-$H$4-$B$4)),"")) | AD12: =IF((1-'Taxas 2026'!$C$25-$H$4-$B$4)<=0,"",IF(MAX('Taxas 2026'!$B$25,(F12+'Taxas 2026'!$D$25)/(1-'Taxas 2026'!$C$25-$H$4-$B$4))<1000000000,MAX('Taxas 2026'!$B$25,(F12+'Taxas 2026'!$D$25)/(1-'Taxas 2026'!$C$25-$H$4-$B$4)),"")) -> 165.65517 | AE12: =MIN(AC12:AD12) -> 165.65517 | AF12: =CEILING(AE12-4.9,5)+4.9 -> 169.9 | AG12: =((AF12)-(F12+(AF12)*(INDEX('Taxas 2026'!$C$24:$C$25,MATCH((AF12),'Taxas 2026'!$B$24:$B$25,1))+$H$4)+INDEX('Taxas 2026'!$D$24:$D$25,MATCH((AF12),'Taxas 2026'!$B$24:$B$25,1))))/(AF12) -> 0.16086816 | AH12: =IF(((AF12)-(F12+(AF12)*(INDEX('Taxas 2026'!$C$24:$C$25,MATCH((AF12),'Taxas 2026'!$B$24:$B$25,1))+$H$4)+INDEX('Taxas 2026'!$D$24:$D$25,MATCH((AF12),'Taxas 2026'!$B$24:$B$25,1))))/(AF12)>=$B$4,AF12,IF(((AF12+5)-(F12+(AF12+5)*(INDEX('Taxas 2026'!$C$24:$C$25,MATCH((AF12+5),'Taxas 2026'!$B$24:$B$25,1))+$H$4)+INDEX('Taxas 2026'!$D$24:$D$25,MATCH((AF12+5),'Taxas 2026'!$B$24:$B$25,1))))/(AF12+5)>=$B$4,AF12+5,AF12+10)) -> 169.9 | AI12: =((AH12)-(F12+(AH12)*(INDEX('Taxas 2026'!$C$24:$C$25,MATCH((AH12),'Taxas 2026'!$B$24:$B$25,1))+$H$4)+INDEX('Taxas 2026'!$D$24:$D$25,MATCH((AH12),'Taxas 2026'!$B$24:$B$25,1))))/(AH12) -> 0.16086816 | AJ12: =MAX(1,(F12+Premissas!$B$45+Premissas!$B$48+INDEX('Frete 2026'!$H$6:$H$11,H12))/(1-$J$4-$B$4)) -> 234.07155 | AK12: =CEILING(AJ12-4.9,5)+4.9 -> 234.9 | AL12: =((AK12)-(F12+Premissas!$B$45+Premissas!$B$48+INDEX('Frete 2026'!$H$6:$H$11,H12)+(AK12)*$J$4))/(AK12) -> 0.15131115 | AM12: =IF(((AK12)-(F12+Premissas!$B$45+Premissas!$B$48+INDEX('Frete 2026'!$H$6:$H$11,H12)+(AK12)*$J$4))/(AK12)>=$B$4,AK12,IF(((AK12+5)-(F12+Premissas!$B$45+Premissas!$B$48+INDEX('Frete 2026'!$H$6:$H$11,H12)+(AK12+5)*$J$4))/(AK12+5)>=$B$4,AK12+5,AK12+10)) -> 234.9 | AN12: =((AM12)-(F12+Premissas!$B$45+Premissas!$B$48+INDEX('Frete 2026'!$H$6:$H$11,H12)+(AM12)*$J$4))/(AM12) -> 0.15131115
A13: Essencial | B13: 5 | C13: =MATCH(A13,'Ficha de Custo'!$B$4:$D$4,0) -> 2 | D13: =INDEX('Ficha de Custo'!$B$14:$D$14,C13) -> 20.52 | E13: =INDEX('Ficha de Custo'!$B$18:$D$21,MATCH(B13,'Ficha de Custo'!$A$18:$A$21,0),C13) -> 5.5 | F13: =D13*B13+E13 -> 108.1 | G13: =INDEX('Ficha de Custo'!$B$36:$D$39,MATCH(B13,'Ficha de Custo'!$A$36:$A$39,0),C13) -> 1.1 | H13: =MATCH(G13-0.0000001,'Frete 2026'!$A$6:$A$11,1) -> 4 | I13: =IF((1-$D$4-$B$4)<=0,"",IF(MAX(1,(F13+INDEX('Frete 2026'!$B$6:$B$11,H13))/(1-$D$4-$B$4))<79,MAX(1,(F13+INDEX('Frete 2026'!$B$6:$B$11,H13))/(1-$D$4-$B$4)),"")) | J13: =IF((1-$D$4-$B$4)<=0,"",IF(MAX('Frete 2026'!$C$5,(F13+INDEX('Frete 2026'!$C$6:$C$11,H13))/(1-$D$4-$B$4))<'Frete 2026'!$D$5,MAX('Frete 2026'!$C$5,(F13+INDEX('Frete 2026'!$C$6:$C$11,H13))/(1-$D$4-$B$4)),"")) | K13: =IF((1-$D$4-$B$4)<=0,"",IF(MAX('Frete 2026'!$D$5,(F13+INDEX('Frete 2026'!$D$6:$D$11,H13))/(1-$D$4-$B$4))<'Frete 2026'!$E$5,MAX('Frete 2026'!$D$5,(F13+INDEX('Frete 2026'!$D$6:$D$11,H13))/(1-$D$4-$B$4)),"")) | L13: =IF((1-$D$4-$B$4)<=0,"",IF(MAX('Frete 2026'!$E$5,(F13+INDEX('Frete 2026'!$E$6:$E$11,H13))/(1-$D$4-$B$4))<'Frete 2026'!$F$5,MAX('Frete 2026'!$E$5,(F13+INDEX('Frete 2026'!$E$6:$E$11,H13))/(1-$D$4-$B$4)),"")) | M13: =IF((1-$D$4-$B$4)<=0,"",IF(MAX('Frete 2026'!$F$5,(F13+INDEX('Frete 2026'!$F$6:$F$11,H13))/(1-$D$4-$B$4))<'Frete 2026'!$G$5,MAX('Frete 2026'!$F$5,(F13+INDEX('Frete 2026'!$F$6:$F$11,H13))/(1-$D$4-$B$4)),"")) | N13: =IF((1-$D$4-$B$4)<=0,"",IF(MAX('Frete 2026'!$G$5,(F13+INDEX('Frete 2026'!$G$6:$G$11,H13))/(1-$D$4-$B$4))<1000000000,MAX('Frete 2026'!$G$5,(F13+INDEX('Frete 2026'!$G$6:$G$11,H13))/(1-$D$4-$B$4)),"")) -> 239.18919 | O13: =MIN(I13:N13) -> 239.18919 | P13: =CEILING(O13-4.9,5)+4.9 -> 239.9 | Q13: =((P13)-(F13+IF((P13)<79,INDEX('Frete 2026'!$B$6:$B$11,H13),INDEX('Frete 2026'!$C$6:$G$11,H13,MATCH((P13),'Frete 2026'!$C$5:$G$5,1)))+(P13)*$D$4))/(P13) -> 0.15164444 | R13: =IF(((P13)-(F13+IF((P13)<79,INDEX('Frete 2026'!$B$6:$B$11,H13),INDEX('Frete 2026'!$C$6:$G$11,H13,MATCH((P13),'Frete 2026'!$C$5:$G$5,1)))+(P13)*$D$4))/(P13)>=$B$4,P13,IF(((P13+5)-(F13+IF((P13+5)<79,INDEX('Frete 2026'!$B$6:$B$11,H13),INDEX('Frete 2026'!$C$6:$G$11,H13,MATCH((P13+5),'Frete 2026'!$C$5:$G$5,1)))+(P13+5)*$D$4))/(P13+5)>=$B$4,P13+5,P13+10)) -> 239.9 | S13: =((R13)-(F13+IF((R13)<79,INDEX('Frete 2026'!$B$6:$B$11,H13),INDEX('Frete 2026'!$C$6:$G$11,H13,MATCH((R13),'Frete 2026'!$C$5:$G$5,1)))+(R13)*$D$4))/(R13) -> 0.15164444 | T13: =IF((1-'Taxas 2026'!$C$16-$F$4-$B$4)<=0,"",IF(MAX('Taxas 2026'!$B$16,(F13+'Taxas 2026'!$D$16+Premissas!$B$34)/(1-'Taxas 2026'!$C$16-$F$4-$B$4))<'Taxas 2026'!$B$17,MAX('Taxas 2026'!$B$16,(F13+'Taxas 2026'!$D$16+Premissas!$B$34)/(1-'Taxas 2026'!$C$16-$F$4-$B$4)),"")) | U13: =IF((1-'Taxas 2026'!$C$17-$F$4-$B$4)<=0,"",IF(MAX('Taxas 2026'!$B$17,(F13+'Taxas 2026'!$D$17+Premissas!$B$34)/(1-'Taxas 2026'!$C$17-$F$4-$B$4))<'Taxas 2026'!$B$18,MAX('Taxas 2026'!$B$17,(F13+'Taxas 2026'!$D$17+Premissas!$B$34)/(1-'Taxas 2026'!$C$17-$F$4-$B$4)),"")) | V13: =IF((1-'Taxas 2026'!$C$18-$F$4-$B$4)<=0,"",IF(MAX('Taxas 2026'!$B$18,(F13+'Taxas 2026'!$D$18+Premissas!$B$34)/(1-'Taxas 2026'!$C$18-$F$4-$B$4))<'Taxas 2026'!$B$19,MAX('Taxas 2026'!$B$18,(F13+'Taxas 2026'!$D$18+Premissas!$B$34)/(1-'Taxas 2026'!$C$18-$F$4-$B$4)),"")) | W13: =IF((1-'Taxas 2026'!$C$19-$F$4-$B$4)<=0,"",IF(MAX('Taxas 2026'!$B$19,(F13+'Taxas 2026'!$D$19+Premissas!$B$34)/(1-'Taxas 2026'!$C$19-$F$4-$B$4))<1000000000,MAX('Taxas 2026'!$B$19,(F13+'Taxas 2026'!$D$19+Premissas!$B$34)/(1-'Taxas 2026'!$C$19-$F$4-$B$4)),"")) -> 250.65421 | X13: =MIN(T13:W13) -> 250.65421 | Y13: =CEILING(X13-4.9,5)+4.9 -> 254.9 | Z13: =((Y13)-(F13+(Y13)*(INDEX('Taxas 2026'!$C$15:$C$19,MATCH((Y13),'Taxas 2026'!$B$15:$B$19,1))+$F$4)+INDEX('Taxas 2026'!$D$15:$D$19,MATCH((Y13),'Taxas 2026'!$B$15:$B$19,1))+Premissas!$B$34))/(Y13) -> 0.15891134 | AA13: =IF(((Y13)-(F13+(Y13)*(INDEX('Taxas 2026'!$C$15:$C$19,MATCH((Y13),'Taxas 2026'!$B$15:$B$19,1))+$F$4)+INDEX('Taxas 2026'!$D$15:$D$19,MATCH((Y13),'Taxas 2026'!$B$15:$B$19,1))+Premissas!$B$34))/(Y13)>=$B$4,Y13,IF(((Y13+5)-(F13+(Y13+5)*(INDEX('Taxas 2026'!$C$15:$C$19,MATCH((Y13+5),'Taxas 2026'!$B$15:$B$19,1))+$F$4)+INDEX('Taxas 2026'!$D$15:$D$19,MATCH((Y13+5),'Taxas 2026'!$B$15:$B$19,1))+Premissas!$B$34))/(Y13+5)>=$B$4,Y13+5,Y13+10)) -> 254.9 | AB13: =((AA13)-(F13+(AA13)*(INDEX('Taxas 2026'!$C$15:$C$19,MATCH((AA13),'Taxas 2026'!$B$15:$B$19,1))+$F$4)+INDEX('Taxas 2026'!$D$15:$D$19,MATCH((AA13),'Taxas 2026'!$B$15:$B$19,1))+Premissas!$B$34))/(AA13) -> 0.15891134 | AC13: =IF((1-'Taxas 2026'!$C$24-$H$4-$B$4)<=0,"",IF(MAX(1,(F13+'Taxas 2026'!$D$24)/(1-'Taxas 2026'!$C$24-$H$4-$B$4))<'Taxas 2026'!$B$25,MAX(1,(F13+'Taxas 2026'!$D$24)/(1-'Taxas 2026'!$C$24-$H$4-$B$4)),"")) | AD13: =IF((1-'Taxas 2026'!$C$25-$H$4-$B$4)<=0,"",IF(MAX('Taxas 2026'!$B$25,(F13+'Taxas 2026'!$D$25)/(1-'Taxas 2026'!$C$25-$H$4-$B$4))<1000000000,MAX('Taxas 2026'!$B$25,(F13+'Taxas 2026'!$D$25)/(1-'Taxas 2026'!$C$25-$H$4-$B$4)),"")) -> 262.29885 | AE13: =MIN(AC13:AD13) -> 262.29885 | AF13: =CEILING(AE13-4.9,5)+4.9 -> 264.9 | AG13: =((AF13)-(F13+(AF13)*(INDEX('Taxas 2026'!$C$24:$C$25,MATCH((AF13),'Taxas 2026'!$B$24:$B$25,1))+$H$4)+INDEX('Taxas 2026'!$D$24:$D$25,MATCH((AF13),'Taxas 2026'!$B$24:$B$25,1))))/(AF13) -> 0.15427142 | AH13: =IF(((AF13)-(F13+(AF13)*(INDEX('Taxas 2026'!$C$24:$C$25,MATCH((AF13),'Taxas 2026'!$B$24:$B$25,1))+$H$4)+INDEX('Taxas 2026'!$D$24:$D$25,MATCH((AF13),'Taxas 2026'!$B$24:$B$25,1))))/(AF13)>=$B$4,AF13,IF(((AF13+5)-(F13+(AF13+5)*(INDEX('Taxas 2026'!$C$24:$C$25,MATCH((AF13+5),'Taxas 2026'!$B$24:$B$25,1))+$H$4)+INDEX('Taxas 2026'!$D$24:$D$25,MATCH((AF13+5),'Taxas 2026'!$B$24:$B$25,1))))/(AF13+5)>=$B$4,AF13+5,AF13+10)) -> 264.9 | AI13: =((AH13)-(F13+(AH13)*(INDEX('Taxas 2026'!$C$24:$C$25,MATCH((AH13),'Taxas 2026'!$B$24:$B$25,1))+$H$4)+INDEX('Taxas 2026'!$D$24:$D$25,MATCH((AH13),'Taxas 2026'!$B$24:$B$25,1))))/(AH13) -> 0.15427142 | AJ13: =MAX(1,(F13+Premissas!$B$45+Premissas!$B$48+INDEX('Frete 2026'!$H$6:$H$11,H13))/(1-$J$4-$B$4)) -> 355.22281 | AK13: =CEILING(AJ13-4.9,5)+4.9 -> 359.9 | AL13: =((AK13)-(F13+Premissas!$B$45+Premissas!$B$48+INDEX('Frete 2026'!$H$6:$H$11,H13)+(AK13)*$J$4))/(AK13) -> 0.15483141 | AM13: =IF(((AK13)-(F13+Premissas!$B$45+Premissas!$B$48+INDEX('Frete 2026'!$H$6:$H$11,H13)+(AK13)*$J$4))/(AK13)>=$B$4,AK13,IF(((AK13+5)-(F13+Premissas!$B$45+Premissas!$B$48+INDEX('Frete 2026'!$H$6:$H$11,H13)+(AK13+5)*$J$4))/(AK13+5)>=$B$4,AK13+5,AK13+10)) -> 359.9 | AN13: =((AM13)-(F13+Premissas!$B$45+Premissas!$B$48+INDEX('Frete 2026'!$H$6:$H$11,H13)+(AM13)*$J$4))/(AM13) -> 0.15483141
A14: Essencial | B14: 10 | C14: =MATCH(A14,'Ficha de Custo'!$B$4:$D$4,0) -> 2 | D14: =INDEX('Ficha de Custo'!$B$14:$D$14,C14) -> 20.52 | E14: =INDEX('Ficha de Custo'!$B$18:$D$21,MATCH(B14,'Ficha de Custo'!$A$18:$A$21,0),C14) -> 7.5 | F14: =D14*B14+E14 -> 212.7 | G14: =INDEX('Ficha de Custo'!$B$36:$D$39,MATCH(B14,'Ficha de Custo'!$A$36:$A$39,0),C14) -> 2.14 | H14: =MATCH(G14-0.0000001,'Frete 2026'!$A$6:$A$11,1) -> 6 | I14: =IF((1-$D$4-$B$4)<=0,"",IF(MAX(1,(F14+INDEX('Frete 2026'!$B$6:$B$11,H14))/(1-$D$4-$B$4))<79,MAX(1,(F14+INDEX('Frete 2026'!$B$6:$B$11,H14))/(1-$D$4-$B$4)),"")) | J14: =IF((1-$D$4-$B$4)<=0,"",IF(MAX('Frete 2026'!$C$5,(F14+INDEX('Frete 2026'!$C$6:$C$11,H14))/(1-$D$4-$B$4))<'Frete 2026'!$D$5,MAX('Frete 2026'!$C$5,(F14+INDEX('Frete 2026'!$C$6:$C$11,H14))/(1-$D$4-$B$4)),"")) | K14: =IF((1-$D$4-$B$4)<=0,"",IF(MAX('Frete 2026'!$D$5,(F14+INDEX('Frete 2026'!$D$6:$D$11,H14))/(1-$D$4-$B$4))<'Frete 2026'!$E$5,MAX('Frete 2026'!$D$5,(F14+INDEX('Frete 2026'!$D$6:$D$11,H14))/(1-$D$4-$B$4)),"")) | L14: =IF((1-$D$4-$B$4)<=0,"",IF(MAX('Frete 2026'!$E$5,(F14+INDEX('Frete 2026'!$E$6:$E$11,H14))/(1-$D$4-$B$4))<'Frete 2026'!$F$5,MAX('Frete 2026'!$E$5,(F14+INDEX('Frete 2026'!$E$6:$E$11,H14))/(1-$D$4-$B$4)),"")) | M14: =IF((1-$D$4-$B$4)<=0,"",IF(MAX('Frete 2026'!$F$5,(F14+INDEX('Frete 2026'!$F$6:$F$11,H14))/(1-$D$4-$B$4))<'Frete 2026'!$G$5,MAX('Frete 2026'!$F$5,(F14+INDEX('Frete 2026'!$F$6:$F$11,H14))/(1-$D$4-$B$4)),"")) | N14: =IF((1-$D$4-$B$4)<=0,"",IF(MAX('Frete 2026'!$G$5,(F14+INDEX('Frete 2026'!$G$6:$G$11,H14))/(1-$D$4-$B$4))<1000000000,MAX('Frete 2026'!$G$5,(F14+INDEX('Frete 2026'!$G$6:$G$11,H14))/(1-$D$4-$B$4)),"")) -> 428.91892 | O14: =MIN(I14:N14) -> 428.91892 | P14: =CEILING(O14-4.9,5)+4.9 -> 429.9 | Q14: =((P14)-(F14+IF((P14)<79,INDEX('Frete 2026'!$B$6:$B$11,H14),INDEX('Frete 2026'!$C$6:$G$11,H14,MATCH((P14),'Frete 2026'!$C$5:$G$5,1)))+(P14)*$D$4))/(P14) -> 0.15126657 | R14: =IF(((P14)-(F14+IF((P14)<79,INDEX('Frete 2026'!$B$6:$B$11,H14),INDEX('Frete 2026'!$C$6:$G$11,H14,MATCH((P14),'Frete 2026'!$C$5:$G$5,1)))+(P14)*$D$4))/(P14)>=$B$4,P14,IF(((P14+5)-(F14+IF((P14+5)<79,INDEX('Frete 2026'!$B$6:$B$11,H14),INDEX('Frete 2026'!$C$6:$G$11,H14,MATCH((P14+5),'Frete 2026'!$C$5:$G$5,1)))+(P14+5)*$D$4))/(P14+5)>=$B$4,P14+5,P14+10)) -> 429.9 | S14: =((R14)-(F14+IF((R14)<79,INDEX('Frete 2026'!$B$6:$B$11,H14),INDEX('Frete 2026'!$C$6:$G$11,H14,MATCH((R14),'Frete 2026'!$C$5:$G$5,1)))+(R14)*$D$4))/(R14) -> 0.15126657 | T14: =IF((1-'Taxas 2026'!$C$16-$F$4-$B$4)<=0,"",IF(MAX('Taxas 2026'!$B$16,(F14+'Taxas 2026'!$D$16+Premissas!$B$34)/(1-'Taxas 2026'!$C$16-$F$4-$B$4))<'Taxas 2026'!$B$17,MAX('Taxas 2026'!$B$16,(F14+'Taxas 2026'!$D$16+Premissas!$B$34)/(1-'Taxas 2026'!$C$16-$F$4-$B$4)),"")) | U14: =IF((1-'Taxas 2026'!$C$17-$F$4-$B$4)<=0,"",IF(MAX('Taxas 2026'!$B$17,(F14+'Taxas 2026'!$D$17+Premissas!$B$34)/(1-'Taxas 2026'!$C$17-$F$4-$B$4))<'Taxas 2026'!$B$18,MAX('Taxas 2026'!$B$17,(F14+'Taxas 2026'!$D$17+Premissas!$B$34)/(1-'Taxas 2026'!$C$17-$F$4-$B$4)),"")) | V14: =IF((1-'Taxas 2026'!$C$18-$F$4-$B$4)<=0,"",IF(MAX('Taxas 2026'!$B$18,(F14+'Taxas 2026'!$D$18+Premissas!$B$34)/(1-'Taxas 2026'!$C$18-$F$4-$B$4))<'Taxas 2026'!$B$19,MAX('Taxas 2026'!$B$18,(F14+'Taxas 2026'!$D$18+Premissas!$B$34)/(1-'Taxas 2026'!$C$18-$F$4-$B$4)),"")) | W14: =IF((1-'Taxas 2026'!$C$19-$F$4-$B$4)<=0,"",IF(MAX('Taxas 2026'!$B$19,(F14+'Taxas 2026'!$D$19+Premissas!$B$34)/(1-'Taxas 2026'!$C$19-$F$4-$B$4))<1000000000,MAX('Taxas 2026'!$B$19,(F14+'Taxas 2026'!$D$19+Premissas!$B$34)/(1-'Taxas 2026'!$C$19-$F$4-$B$4)),"")) -> 446.16822 | X14: =MIN(T14:W14) -> 446.16822 | Y14: =CEILING(X14-4.9,5)+4.9 -> 449.9 | Z14: =((Y14)-(F14+(Y14)*(INDEX('Taxas 2026'!$C$15:$C$19,MATCH((Y14),'Taxas 2026'!$B$15:$B$19,1))+$F$4)+INDEX('Taxas 2026'!$D$15:$D$19,MATCH((Y14),'Taxas 2026'!$B$15:$B$19,1))+Premissas!$B$34))/(Y14) -> 0.15443765 | AA14: =IF(((Y14)-(F14+(Y14)*(INDEX('Taxas 2026'!$C$15:$C$19,MATCH((Y14),'Taxas 2026'!$B$15:$B$19,1))+$F$4)+INDEX('Taxas 2026'!$D$15:$D$19,MATCH((Y14),'Taxas 2026'!$B$15:$B$19,1))+Premissas!$B$34))/(Y14)>=$B$4,Y14,IF(((Y14+5)-(F14+(Y14+5)*(INDEX('Taxas 2026'!$C$15:$C$19,MATCH((Y14+5),'Taxas 2026'!$B$15:$B$19,1))+$F$4)+INDEX('Taxas 2026'!$D$15:$D$19,MATCH((Y14+5),'Taxas 2026'!$B$15:$B$19,1))+Premissas!$B$34))/(Y14+5)>=$B$4,Y14+5,Y14+10)) -> 449.9 | AB14: =((AA14)-(F14+(AA14)*(INDEX('Taxas 2026'!$C$15:$C$19,MATCH((AA14),'Taxas 2026'!$B$15:$B$19,1))+$F$4)+INDEX('Taxas 2026'!$D$15:$D$19,MATCH((AA14),'Taxas 2026'!$B$15:$B$19,1))+Premissas!$B$34))/(AA14) -> 0.15443765 | AC14: =IF((1-'Taxas 2026'!$C$24-$H$4-$B$4)<=0,"",IF(MAX(1,(F14+'Taxas 2026'!$D$24)/(1-'Taxas 2026'!$C$24-$H$4-$B$4))<'Taxas 2026'!$B$25,MAX(1,(F14+'Taxas 2026'!$D$24)/(1-'Taxas 2026'!$C$24-$H$4-$B$4)),"")) | AD14: =IF((1-'Taxas 2026'!$C$25-$H$4-$B$4)<=0,"",IF(MAX('Taxas 2026'!$B$25,(F14+'Taxas 2026'!$D$25)/(1-'Taxas 2026'!$C$25-$H$4-$B$4))<1000000000,MAX('Taxas 2026'!$B$25,(F14+'Taxas 2026'!$D$25)/(1-'Taxas 2026'!$C$25-$H$4-$B$4)),"")) -> 502.75862 | AE14: =MIN(AC14:AD14) -> 502.75862 | AF14: =CEILING(AE14-4.9,5)+4.9 -> 504.9 | AG14: =((AF14)-(F14+(AF14)*(INDEX('Taxas 2026'!$C$24:$C$25,MATCH((AF14),'Taxas 2026'!$B$24:$B$25,1))+$H$4)+INDEX('Taxas 2026'!$D$24:$D$25,MATCH((AF14),'Taxas 2026'!$B$24:$B$25,1))))/(AF14) -> 0.15184492 | AH14: =IF(((AF14)-(F14+(AF14)*(INDEX('Taxas 2026'!$C$24:$C$25,MATCH((AF14),'Taxas 2026'!$B$24:$B$25,1))+$H$4)+INDEX('Taxas 2026'!$D$24:$D$25,MATCH((AF14),'Taxas 2026'!$B$24:$B$25,1))))/(AF14)>=$B$4,AF14,IF(((AF14+5)-(F14+(AF14+5)*(INDEX('Taxas 2026'!$C$24:$C$25,MATCH((AF14+5),'Taxas 2026'!$B$24:$B$25,1))+$H$4)+INDEX('Taxas 2026'!$D$24:$D$25,MATCH((AF14+5),'Taxas 2026'!$B$24:$B$25,1))))/(AF14+5)>=$B$4,AF14+5,AF14+10)) -> 504.9 | AI14: =((AH14)-(F14+(AH14)*(INDEX('Taxas 2026'!$C$24:$C$25,MATCH((AH14),'Taxas 2026'!$B$24:$B$25,1))+$H$4)+INDEX('Taxas 2026'!$D$24:$D$25,MATCH((AH14),'Taxas 2026'!$B$24:$B$25,1))))/(AH14) -> 0.15184492 | AJ14: =MAX(1,(F14+Premissas!$B$45+Premissas!$B$48+INDEX('Frete 2026'!$H$6:$H$11,H14))/(1-$J$4-$B$4)) -> 655.4111 | AK14: =CEILING(AJ14-4.9,5)+4.9 -> 659.9 | AL14: =((AK14)-(F14+Premissas!$B$45+Premissas!$B$48+INDEX('Frete 2026'!$H$6:$H$11,H14)+(AK14)*$J$4))/(AK14) -> 0.1525289 | AM14: =IF(((AK14)-(F14+Premissas!$B$45+Premissas!$B$48+INDEX('Frete 2026'!$H$6:$H$11,H14)+(AK14)*$J$4))/(AK14)>=$B$4,AK14,IF(((AK14+5)-(F14+Premissas!$B$45+Premissas!$B$48+INDEX('Frete 2026'!$H$6:$H$11,H14)+(AK14+5)*$J$4))/(AK14+5)>=$B$4,AK14+5,AK14+10)) -> 659.9 | AN14: =((AM14)-(F14+Premissas!$B$45+Premissas!$B$48+INDEX('Frete 2026'!$H$6:$H$11,H14)+(AM14)*$J$4))/(AM14) -> 0.1525289
A15: Fibra Longa | B15: 1 | C15: =MATCH(A15,'Ficha de Custo'!$B$4:$D$4,0) -> 3 | D15: =INDEX('Ficha de Custo'!$B$14:$D$14,C15) -> 31.83 | E15: =INDEX('Ficha de Custo'!$B$18:$D$21,MATCH(B15,'Ficha de Custo'!$A$18:$A$21,0),C15) -> 2.9 | F15: =D15*B15+E15 -> 34.73 | G15: =INDEX('Ficha de Custo'!$B$36:$D$39,MATCH(B15,'Ficha de Custo'!$A$36:$A$39,0),C15) -> 0.22 | H15: =MATCH(G15-0.0000001,'Frete 2026'!$A$6:$A$11,1) -> 1 | I15: =IF((1-$D$4-$B$4)<=0,"",IF(MAX(1,(F15+INDEX('Frete 2026'!$B$6:$B$11,H15))/(1-$D$4-$B$4))<79,MAX(1,(F15+INDEX('Frete 2026'!$B$6:$B$11,H15))/(1-$D$4-$B$4)),"")) -> 74.288288 | J15: =IF((1-$D$4-$B$4)<=0,"",IF(MAX('Frete 2026'!$C$5,(F15+INDEX('Frete 2026'!$C$6:$C$11,H15))/(1-$D$4-$B$4))<'Frete 2026'!$D$5,MAX('Frete 2026'!$C$5,(F15+INDEX('Frete 2026'!$C$6:$C$11,H15))/(1-$D$4-$B$4)),"")) -> 84.828829 | K15: =IF((1-$D$4-$B$4)<=0,"",IF(MAX('Frete 2026'!$D$5,(F15+INDEX('Frete 2026'!$D$6:$D$11,H15))/(1-$D$4-$B$4))<'Frete 2026'!$E$5,MAX('Frete 2026'!$D$5,(F15+INDEX('Frete 2026'!$D$6:$D$11,H15))/(1-$D$4-$B$4)),"")) -> 100 | L15: =IF((1-$D$4-$B$4)<=0,"",IF(MAX('Frete 2026'!$E$5,(F15+INDEX('Frete 2026'!$E$6:$E$11,H15))/(1-$D$4-$B$4))<'Frete 2026'!$F$5,MAX('Frete 2026'!$E$5,(F15+INDEX('Frete 2026'!$E$6:$E$11,H15))/(1-$D$4-$B$4)),"")) -> 120 | M15: =IF((1-$D$4-$B$4)<=0,"",IF(MAX('Frete 2026'!$F$5,(F15+INDEX('Frete 2026'!$F$6:$F$11,H15))/(1-$D$4-$B$4))<'Frete 2026'!$G$5,MAX('Frete 2026'!$F$5,(F15+INDEX('Frete 2026'!$F$6:$F$11,H15))/(1-$D$4-$B$4)),"")) -> 150 | N15: =IF((1-$D$4-$B$4)<=0,"",IF(MAX('Frete 2026'!$G$5,(F15+INDEX('Frete 2026'!$G$6:$G$11,H15))/(1-$D$4-$B$4))<1000000000,MAX('Frete 2026'!$G$5,(F15+INDEX('Frete 2026'!$G$6:$G$11,H15))/(1-$D$4-$B$4)),"")) -> 200 | O15: =MIN(I15:N15) -> 74.288288 | P15: =CEILING(O15-4.9,5)+4.9 -> 74.9 | Q15: =((P15)-(F15+IF((P15)<79,INDEX('Frete 2026'!$B$6:$B$11,H15),INDEX('Frete 2026'!$C$6:$G$11,H15,MATCH((P15),'Frete 2026'!$C$5:$G$5,1)))+(P15)*$D$4))/(P15) -> 0.15453271 | R15: =IF(((P15)-(F15+IF((P15)<79,INDEX('Frete 2026'!$B$6:$B$11,H15),INDEX('Frete 2026'!$C$6:$G$11,H15,MATCH((P15),'Frete 2026'!$C$5:$G$5,1)))+(P15)*$D$4))/(P15)>=$B$4,P15,IF(((P15+5)-(F15+IF((P15+5)<79,INDEX('Frete 2026'!$B$6:$B$11,H15),INDEX('Frete 2026'!$C$6:$G$11,H15,MATCH((P15+5),'Frete 2026'!$C$5:$G$5,1)))+(P15+5)*$D$4))/(P15+5)>=$B$4,P15+5,P15+10)) -> 74.9 | S15: =((R15)-(F15+IF((R15)<79,INDEX('Frete 2026'!$B$6:$B$11,H15),INDEX('Frete 2026'!$C$6:$G$11,H15,MATCH((R15),'Frete 2026'!$C$5:$G$5,1)))+(R15)*$D$4))/(R15) -> 0.15453271 | T15: =IF((1-'Taxas 2026'!$C$16-$F$4-$B$4)<=0,"",IF(MAX('Taxas 2026'!$B$16,(F15+'Taxas 2026'!$D$16+Premissas!$B$34)/(1-'Taxas 2026'!$C$16-$F$4-$B$4))<'Taxas 2026'!$B$17,MAX('Taxas 2026'!$B$16,(F15+'Taxas 2026'!$D$16+Premissas!$B$34)/(1-'Taxas 2026'!$C$16-$F$4-$B$4)),"")) | U15: =IF((1-'Taxas 2026'!$C$17-$F$4-$B$4)<=0,"",IF(MAX('Taxas 2026'!$B$17,(F15+'Taxas 2026'!$D$17+Premissas!$B$34)/(1-'Taxas 2026'!$C$17-$F$4-$B$4))<'Taxas 2026'!$B$18,MAX('Taxas 2026'!$B$17,(F15+'Taxas 2026'!$D$17+Premissas!$B$34)/(1-'Taxas 2026'!$C$17-$F$4-$B$4)),"")) -> 94.82243 | V15: =IF((1-'Taxas 2026'!$C$18-$F$4-$B$4)<=0,"",IF(MAX('Taxas 2026'!$B$18,(F15+'Taxas 2026'!$D$18+Premissas!$B$34)/(1-'Taxas 2026'!$C$18-$F$4-$B$4))<'Taxas 2026'!$B$19,MAX('Taxas 2026'!$B$18,(F15+'Taxas 2026'!$D$18+Premissas!$B$34)/(1-'Taxas 2026'!$C$18-$F$4-$B$4)),"")) -> 102.29907 | W15: =IF((1-'Taxas 2026'!$C$19-$F$4-$B$4)<=0,"",IF(MAX('Taxas 2026'!$B$19,(F15+'Taxas 2026'!$D$19+Premissas!$B$34)/(1-'Taxas 2026'!$C$19-$F$4-$B$4))<1000000000,MAX('Taxas 2026'!$B$19,(F15+'Taxas 2026'!$D$19+Premissas!$B$34)/(1-'Taxas 2026'!$C$19-$F$4-$B$4)),"")) -> 200 | X15: =MIN(T15:W15) -> 94.82243 | Y15: =CEILING(X15-4.9,5)+4.9 -> 94.9 | Z15: =((Y15)-(F15+(Y15)*(INDEX('Taxas 2026'!$C$15:$C$19,MATCH((Y15),'Taxas 2026'!$B$15:$B$19,1))+$F$4)+INDEX('Taxas 2026'!$D$15:$D$19,MATCH((Y15),'Taxas 2026'!$B$15:$B$19,1))+Premissas!$B$34))/(Y15) -> 0.1504373 | AA15: =IF(((Y15)-(F15+(Y15)*(INDEX('Taxas 2026'!$C$15:$C$19,MATCH((Y15),'Taxas 2026'!$B$15:$B$19,1))+$F$4)+INDEX('Taxas 2026'!$D$15:$D$19,MATCH((Y15),'Taxas 2026'!$B$15:$B$19,1))+Premissas!$B$34))/(Y15)>=$B$4,Y15,IF(((Y15+5)-(F15+(Y15+5)*(INDEX('Taxas 2026'!$C$15:$C$19,MATCH((Y15+5),'Taxas 2026'!$B$15:$B$19,1))+$F$4)+INDEX('Taxas 2026'!$D$15:$D$19,MATCH((Y15+5),'Taxas 2026'!$B$15:$B$19,1))+Premissas!$B$34))/(Y15+5)>=$B$4,Y15+5,Y15+10)) -> 94.9 | AB15: =((AA15)-(F15+(AA15)*(INDEX('Taxas 2026'!$C$15:$C$19,MATCH((AA15),'Taxas 2026'!$B$15:$B$19,1))+$F$4)+INDEX('Taxas 2026'!$D$15:$D$19,MATCH((AA15),'Taxas 2026'!$B$15:$B$19,1))+Premissas!$B$34))/(AA15) -> 0.1504373 | AC15: =IF((1-'Taxas 2026'!$C$24-$H$4-$B$4)<=0,"",IF(MAX(1,(F15+'Taxas 2026'!$D$24)/(1-'Taxas 2026'!$C$24-$H$4-$B$4))<'Taxas 2026'!$B$25,MAX(1,(F15+'Taxas 2026'!$D$24)/(1-'Taxas 2026'!$C$24-$H$4-$B$4)),"")) | AD15: =IF((1-'Taxas 2026'!$C$25-$H$4-$B$4)<=0,"",IF(MAX('Taxas 2026'!$B$25,(F15+'Taxas 2026'!$D$25)/(1-'Taxas 2026'!$C$25-$H$4-$B$4))<1000000000,MAX('Taxas 2026'!$B$25,(F15+'Taxas 2026'!$D$25)/(1-'Taxas 2026'!$C$25-$H$4-$B$4)),"")) -> 93.632184 | AE15: =MIN(AC15:AD15) -> 93.632184 | AF15: =CEILING(AE15-4.9,5)+4.9 -> 94.9 | AG15: =((AF15)-(F15+(AF15)*(INDEX('Taxas 2026'!$C$24:$C$25,MATCH((AF15),'Taxas 2026'!$B$24:$B$25,1))+$H$4)+INDEX('Taxas 2026'!$D$24:$D$25,MATCH((AF15),'Taxas 2026'!$B$24:$B$25,1))))/(AF15) -> 0.15581138 | AH15: =IF(((AF15)-(F15+(AF15)*(INDEX('Taxas 2026'!$C$24:$C$25,MATCH((AF15),'Taxas 2026'!$B$24:$B$25,1))+$H$4)+INDEX('Taxas 2026'!$D$24:$D$25,MATCH((AF15),'Taxas 2026'!$B$24:$B$25,1))))/(AF15)>=$B$4,AF15,IF(((AF15+5)-(F15+(AF15+5)*(INDEX('Taxas 2026'!$C$24:$C$25,MATCH((AF15+5),'Taxas 2026'!$B$24:$B$25,1))+$H$4)+INDEX('Taxas 2026'!$D$24:$D$25,MATCH((AF15+5),'Taxas 2026'!$B$24:$B$25,1))))/(AF15+5)>=$B$4,AF15+5,AF15+10)) -> 94.9 | AI15: =((AH15)-(F15+(AH15)*(INDEX('Taxas 2026'!$C$24:$C$25,MATCH((AH15),'Taxas 2026'!$B$24:$B$25,1))+$H$4)+INDEX('Taxas 2026'!$D$24:$D$25,MATCH((AH15),'Taxas 2026'!$B$24:$B$25,1))))/(AH15) -> 0.15581138 | AJ15: =MAX(1,(F15+Premissas!$B$45+Premissas!$B$48+INDEX('Frete 2026'!$H$6:$H$11,H15))/(1-$J$4-$B$4)) -> 141.72868 | AK15: =CEILING(AJ15-4.9,5)+4.9 -> 144.9 | AL15: =((AK15)-(F15+Premissas!$B$45+Premissas!$B$48+INDEX('Frete 2026'!$H$6:$H$11,H15)+(AK15)*$J$4))/(AK15) -> 0.15813658 | AM15: =IF(((AK15)-(F15+Premissas!$B$45+Premissas!$B$48+INDEX('Frete 2026'!$H$6:$H$11,H15)+(AK15)*$J$4))/(AK15)>=$B$4,AK15,IF(((AK15+5)-(F15+Premissas!$B$45+Premissas!$B$48+INDEX('Frete 2026'!$H$6:$H$11,H15)+(AK15+5)*$J$4))/(AK15+5)>=$B$4,AK15+5,AK15+10)) -> 144.9 | AN15: =((AM15)-(F15+Premissas!$B$45+Premissas!$B$48+INDEX('Frete 2026'!$H$6:$H$11,H15)+(AM15)*$J$4))/(AM15) -> 0.15813658
A16: Fibra Longa | B16: 3 | C16: =MATCH(A16,'Ficha de Custo'!$B$4:$D$4,0) -> 3 | D16: =INDEX('Ficha de Custo'!$B$14:$D$14,C16) -> 31.83 | E16: =INDEX('Ficha de Custo'!$B$18:$D$21,MATCH(B16,'Ficha de Custo'!$A$18:$A$21,0),C16) -> 7 | F16: =D16*B16+E16 -> 102.49 | G16: =INDEX('Ficha de Custo'!$B$36:$D$39,MATCH(B16,'Ficha de Custo'!$A$36:$A$39,0),C16) -> 0.65 | H16: =MATCH(G16-0.0000001,'Frete 2026'!$A$6:$A$11,1) -> 3 | I16: =IF((1-$D$4-$B$4)<=0,"",IF(MAX(1,(F16+INDEX('Frete 2026'!$B$6:$B$11,H16))/(1-$D$4-$B$4))<79,MAX(1,(F16+INDEX('Frete 2026'!$B$6:$B$11,H16))/(1-$D$4-$B$4)),"")) | J16: =IF((1-$D$4-$B$4)<=0,"",IF(MAX('Frete 2026'!$C$5,(F16+INDEX('Frete 2026'!$C$6:$C$11,H16))/(1-$D$4-$B$4))<'Frete 2026'!$D$5,MAX('Frete 2026'!$C$5,(F16+INDEX('Frete 2026'!$C$6:$C$11,H16))/(1-$D$4-$B$4)),"")) | K16: =IF((1-$D$4-$B$4)<=0,"",IF(MAX('Frete 2026'!$D$5,(F16+INDEX('Frete 2026'!$D$6:$D$11,H16))/(1-$D$4-$B$4))<'Frete 2026'!$E$5,MAX('Frete 2026'!$D$5,(F16+INDEX('Frete 2026'!$D$6:$D$11,H16))/(1-$D$4-$B$4)),"")) | L16: =IF((1-$D$4-$B$4)<=0,"",IF(MAX('Frete 2026'!$E$5,(F16+INDEX('Frete 2026'!$E$6:$E$11,H16))/(1-$D$4-$B$4))<'Frete 2026'!$F$5,MAX('Frete 2026'!$E$5,(F16+INDEX('Frete 2026'!$E$6:$E$11,H16))/(1-$D$4-$B$4)),"")) | M16: =IF((1-$D$4-$B$4)<=0,"",IF(MAX('Frete 2026'!$F$5,(F16+INDEX('Frete 2026'!$F$6:$F$11,H16))/(1-$D$4-$B$4))<'Frete 2026'!$G$5,MAX('Frete 2026'!$F$5,(F16+INDEX('Frete 2026'!$F$6:$F$11,H16))/(1-$D$4-$B$4)),"")) | N16: =IF((1-$D$4-$B$4)<=0,"",IF(MAX('Frete 2026'!$G$5,(F16+INDEX('Frete 2026'!$G$6:$G$11,H16))/(1-$D$4-$B$4))<1000000000,MAX('Frete 2026'!$G$5,(F16+INDEX('Frete 2026'!$G$6:$G$11,H16))/(1-$D$4-$B$4)),"")) -> 224.57658 | O16: =MIN(I16:N16) -> 224.57658 | P16: =CEILING(O16-4.9,5)+4.9 -> 224.9 | Q16: =((P16)-(F16+IF((P16)<79,INDEX('Frete 2026'!$B$6:$B$11,H16),INDEX('Frete 2026'!$C$6:$G$11,H16,MATCH((P16),'Frete 2026'!$C$5:$G$5,1)))+(P16)*$D$4))/(P16) -> 0.15079813 | R16: =IF(((P16)-(F16+IF((P16)<79,INDEX('Frete 2026'!$B$6:$B$11,H16),INDEX('Frete 2026'!$C$6:$G$11,H16,MATCH((P16),'Frete 2026'!$C$5:$G$5,1)))+(P16)*$D$4))/(P16)>=$B$4,P16,IF(((P16+5)-(F16+IF((P16+5)<79,INDEX('Frete 2026'!$B$6:$B$11,H16),INDEX('Frete 2026'!$C$6:$G$11,H16,MATCH((P16+5),'Frete 2026'!$C$5:$G$5,1)))+(P16+5)*$D$4))/(P16+5)>=$B$4,P16+5,P16+10)) -> 224.9 | S16: =((R16)-(F16+IF((R16)<79,INDEX('Frete 2026'!$B$6:$B$11,H16),INDEX('Frete 2026'!$C$6:$G$11,H16,MATCH((R16),'Frete 2026'!$C$5:$G$5,1)))+(R16)*$D$4))/(R16) -> 0.15079813 | T16: =IF((1-'Taxas 2026'!$C$16-$F$4-$B$4)<=0,"",IF(MAX('Taxas 2026'!$B$16,(F16+'Taxas 2026'!$D$16+Premissas!$B$34)/(1-'Taxas 2026'!$C$16-$F$4-$B$4))<'Taxas 2026'!$B$17,MAX('Taxas 2026'!$B$16,(F16+'Taxas 2026'!$D$16+Premissas!$B$34)/(1-'Taxas 2026'!$C$16-$F$4-$B$4)),"")) | U16: =IF((1-'Taxas 2026'!$C$17-$F$4-$B$4)<=0,"",IF(MAX('Taxas 2026'!$B$17,(F16+'Taxas 2026'!$D$17+Premissas!$B$34)/(1-'Taxas 2026'!$C$17-$F$4-$B$4))<'Taxas 2026'!$B$18,MAX('Taxas 2026'!$B$17,(F16+'Taxas 2026'!$D$17+Premissas!$B$34)/(1-'Taxas 2026'!$C$17-$F$4-$B$4)),"")) | V16: =IF((1-'Taxas 2026'!$C$18-$F$4-$B$4)<=0,"",IF(MAX('Taxas 2026'!$B$18,(F16+'Taxas 2026'!$D$18+Premissas!$B$34)/(1-'Taxas 2026'!$C$18-$F$4-$B$4))<'Taxas 2026'!$B$19,MAX('Taxas 2026'!$B$18,(F16+'Taxas 2026'!$D$18+Premissas!$B$34)/(1-'Taxas 2026'!$C$18-$F$4-$B$4)),"")) | W16: =IF((1-'Taxas 2026'!$C$19-$F$4-$B$4)<=0,"",IF(MAX('Taxas 2026'!$B$19,(F16+'Taxas 2026'!$D$19+Premissas!$B$34)/(1-'Taxas 2026'!$C$19-$F$4-$B$4))<1000000000,MAX('Taxas 2026'!$B$19,(F16+'Taxas 2026'!$D$19+Premissas!$B$34)/(1-'Taxas 2026'!$C$19-$F$4-$B$4)),"")) -> 240.16822 | X16: =MIN(T16:W16) -> 240.16822 | Y16: =CEILING(X16-4.9,5)+4.9 -> 244.9 | Z16: =((Y16)-(F16+(Y16)*(INDEX('Taxas 2026'!$C$15:$C$19,MATCH((Y16),'Taxas 2026'!$B$15:$B$19,1))+$F$4)+INDEX('Taxas 2026'!$D$15:$D$19,MATCH((Y16),'Taxas 2026'!$B$15:$B$19,1))+Premissas!$B$34))/(Y16) -> 0.16033687 | AA16: =IF(((Y16)-(F16+(Y16)*(INDEX('Taxas 2026'!$C$15:$C$19,MATCH((Y16),'Taxas 2026'!$B$15:$B$19,1))+$F$4)+INDEX('Taxas 2026'!$D$15:$D$19,MATCH((Y16),'Taxas 2026'!$B$15:$B$19,1))+Premissas!$B$34))/(Y16)>=$B$4,Y16,IF(((Y16+5)-(F16+(Y16+5)*(INDEX('Taxas 2026'!$C$15:$C$19,MATCH((Y16+5),'Taxas 2026'!$B$15:$B$19,1))+$F$4)+INDEX('Taxas 2026'!$D$15:$D$19,MATCH((Y16+5),'Taxas 2026'!$B$15:$B$19,1))+Premissas!$B$34))/(Y16+5)>=$B$4,Y16+5,Y16+10)) -> 244.9 | AB16: =((AA16)-(F16+(AA16)*(INDEX('Taxas 2026'!$C$15:$C$19,MATCH((AA16),'Taxas 2026'!$B$15:$B$19,1))+$F$4)+INDEX('Taxas 2026'!$D$15:$D$19,MATCH((AA16),'Taxas 2026'!$B$15:$B$19,1))+Premissas!$B$34))/(AA16) -> 0.16033687 | AC16: =IF((1-'Taxas 2026'!$C$24-$H$4-$B$4)<=0,"",IF(MAX(1,(F16+'Taxas 2026'!$D$24)/(1-'Taxas 2026'!$C$24-$H$4-$B$4))<'Taxas 2026'!$B$25,MAX(1,(F16+'Taxas 2026'!$D$24)/(1-'Taxas 2026'!$C$24-$H$4-$B$4)),"")) | AD16: =IF((1-'Taxas 2026'!$C$25-$H$4-$B$4)<=0,"",IF(MAX('Taxas 2026'!$B$25,(F16+'Taxas 2026'!$D$25)/(1-'Taxas 2026'!$C$25-$H$4-$B$4))<1000000000,MAX('Taxas 2026'!$B$25,(F16+'Taxas 2026'!$D$25)/(1-'Taxas 2026'!$C$25-$H$4-$B$4)),"")) -> 249.4023 | AE16: =MIN(AC16:AD16) -> 249.4023 | AF16: =CEILING(AE16-4.9,5)+4.9 -> 249.9 | AG16: =((AF16)-(F16+(AF16)*(INDEX('Taxas 2026'!$C$24:$C$25,MATCH((AF16),'Taxas 2026'!$B$24:$B$25,1))+$H$4)+INDEX('Taxas 2026'!$D$24:$D$25,MATCH((AF16),'Taxas 2026'!$B$24:$B$25,1))))/(AF16) -> 0.15086635 | AH16: =IF(((AF16)-(F16+(AF16)*(INDEX('Taxas 2026'!$C$24:$C$25,MATCH((AF16),'Taxas 2026'!$B$24:$B$25,1))+$H$4)+INDEX('Taxas 2026'!$D$24:$D$25,MATCH((AF16),'Taxas 2026'!$B$24:$B$25,1))))/(AF16)>=$B$4,AF16,IF(((AF16+5)-(F16+(AF16+5)*(INDEX('Taxas 2026'!$C$24:$C$25,MATCH((AF16+5),'Taxas 2026'!$B$24:$B$25,1))+$H$4)+INDEX('Taxas 2026'!$D$24:$D$25,MATCH((AF16+5),'Taxas 2026'!$B$24:$B$25,1))))/(AF16+5)>=$B$4,AF16+5,AF16+10)) -> 249.9 | AI16: =((AH16)-(F16+(AH16)*(INDEX('Taxas 2026'!$C$24:$C$25,MATCH((AH16),'Taxas 2026'!$B$24:$B$25,1))+$H$4)+INDEX('Taxas 2026'!$D$24:$D$25,MATCH((AH16),'Taxas 2026'!$B$24:$B$25,1))))/(AH16) -> 0.15086635 | AJ16: =MAX(1,(F16+Premissas!$B$45+Premissas!$B$48+INDEX('Frete 2026'!$H$6:$H$11,H16))/(1-$J$4-$B$4)) -> 332.06312 | AK16: =CEILING(AJ16-4.9,5)+4.9 -> 334.9 | AL16: =((AK16)-(F16+Premissas!$B$45+Premissas!$B$48+INDEX('Frete 2026'!$H$6:$H$11,H16)+(AK16)*$J$4))/(AK16) -> 0.15314917 | AM16: =IF(((AK16)-(F16+Premissas!$B$45+Premissas!$B$48+INDEX('Frete 2026'!$H$6:$H$11,H16)+(AK16)*$J$4))/(AK16)>=$B$4,AK16,IF(((AK16+5)-(F16+Premissas!$B$45+Premissas!$B$48+INDEX('Frete 2026'!$H$6:$H$11,H16)+(AK16+5)*$J$4))/(AK16+5)>=$B$4,AK16+5,AK16+10)) -> 334.9 | AN16: =((AM16)-(F16+Premissas!$B$45+Premissas!$B$48+INDEX('Frete 2026'!$H$6:$H$11,H16)+(AM16)*$J$4))/(AM16) -> 0.15314917
A17: Fibra Longa | B17: 5 | C17: =MATCH(A17,'Ficha de Custo'!$B$4:$D$4,0) -> 3 | D17: =INDEX('Ficha de Custo'!$B$14:$D$14,C17) -> 31.83 | E17: =INDEX('Ficha de Custo'!$B$18:$D$21,MATCH(B17,'Ficha de Custo'!$A$18:$A$21,0),C17) -> 9 | F17: =D17*B17+E17 -> 168.15 | G17: =INDEX('Ficha de Custo'!$B$36:$D$39,MATCH(B17,'Ficha de Custo'!$A$36:$A$39,0),C17) -> 1.05 | H17: =MATCH(G17-0.0000001,'Frete 2026'!$A$6:$A$11,1) -> 4 | I17: =IF((1-$D$4-$B$4)<=0,"",IF(MAX(1,(F17+INDEX('Frete 2026'!$B$6:$B$11,H17))/(1-$D$4-$B$4))<79,MAX(1,(F17+INDEX('Frete 2026'!$B$6:$B$11,H17))/(1-$D$4-$B$4)),"")) | J17: =IF((1-$D$4-$B$4)<=0,"",IF(MAX('Frete 2026'!$C$5,(F17+INDEX('Frete 2026'!$C$6:$C$11,H17))/(1-$D$4-$B$4))<'Frete 2026'!$D$5,MAX('Frete 2026'!$C$5,(F17+INDEX('Frete 2026'!$C$6:$C$11,H17))/(1-$D$4-$B$4)),"")) | K17: =IF((1-$D$4-$B$4)<=0,"",IF(MAX('Frete 2026'!$D$5,(F17+INDEX('Frete 2026'!$D$6:$D$11,H17))/(1-$D$4-$B$4))<'Frete 2026'!$E$5,MAX('Frete 2026'!$D$5,(F17+INDEX('Frete 2026'!$D$6:$D$11,H17))/(1-$D$4-$B$4)),"")) | L17: =IF((1-$D$4-$B$4)<=0,"",IF(MAX('Frete 2026'!$E$5,(F17+INDEX('Frete 2026'!$E$6:$E$11,H17))/(1-$D$4-$B$4))<'Frete 2026'!$F$5,MAX('Frete 2026'!$E$5,(F17+INDEX('Frete 2026'!$E$6:$E$11,H17))/(1-$D$4-$B$4)),"")) | M17: =IF((1-$D$4-$B$4)<=0,"",IF(MAX('Frete 2026'!$F$5,(F17+INDEX('Frete 2026'!$F$6:$F$11,H17))/(1-$D$4-$B$4))<'Frete 2026'!$G$5,MAX('Frete 2026'!$F$5,(F17+INDEX('Frete 2026'!$F$6:$F$11,H17))/(1-$D$4-$B$4)),"")) | N17: =IF((1-$D$4-$B$4)<=0,"",IF(MAX('Frete 2026'!$G$5,(F17+INDEX('Frete 2026'!$G$6:$G$11,H17))/(1-$D$4-$B$4))<1000000000,MAX('Frete 2026'!$G$5,(F17+INDEX('Frete 2026'!$G$6:$G$11,H17))/(1-$D$4-$B$4)),"")) -> 347.38739 | O17: =MIN(I17:N17) -> 347.38739 | P17: =CEILING(O17-4.9,5)+4.9 -> 349.9 | Q17: =((P17)-(F17+IF((P17)<79,INDEX('Frete 2026'!$B$6:$B$11,H17),INDEX('Frete 2026'!$C$6:$G$11,H17,MATCH((P17),'Frete 2026'!$C$5:$G$5,1)))+(P17)*$D$4))/(P17) -> 0.15398542 | R17: =IF(((P17)-(F17+IF((P17)<79,INDEX('Frete 2026'!$B$6:$B$11,H17),INDEX('Frete 2026'!$C$6:$G$11,H17,MATCH((P17),'Frete 2026'!$C$5:$G$5,1)))+(P17)*$D$4))/(P17)>=$B$4,P17,IF(((P17+5)-(F17+IF((P17+5)<79,INDEX('Frete 2026'!$B$6:$B$11,H17),INDEX('Frete 2026'!$C$6:$G$11,H17,MATCH((P17+5),'Frete 2026'!$C$5:$G$5,1)))+(P17+5)*$D$4))/(P17+5)>=$B$4,P17+5,P17+10)) -> 349.9 | S17: =((R17)-(F17+IF((R17)<79,INDEX('Frete 2026'!$B$6:$B$11,H17),INDEX('Frete 2026'!$C$6:$G$11,H17,MATCH((R17),'Frete 2026'!$C$5:$G$5,1)))+(R17)*$D$4))/(R17) -> 0.15398542 | T17: =IF((1-'Taxas 2026'!$C$16-$F$4-$B$4)<=0,"",IF(MAX('Taxas 2026'!$B$16,(F17+'Taxas 2026'!$D$16+Premissas!$B$34)/(1-'Taxas 2026'!$C$16-$F$4-$B$4))<'Taxas 2026'!$B$17,MAX('Taxas 2026'!$B$16,(F17+'Taxas 2026'!$D$16+Premissas!$B$34)/(1-'Taxas 2026'!$C$16-$F$4-$B$4)),"")) | U17: =IF((1-'Taxas 2026'!$C$17-$F$4-$B$4)<=0,"",IF(MAX('Taxas 2026'!$B$17,(F17+'Taxas 2026'!$D$17+Premissas!$B$34)/(1-'Taxas 2026'!$C$17-$F$4-$B$4))<'Taxas 2026'!$B$18,MAX('Taxas 2026'!$B$17,(F17+'Taxas 2026'!$D$17+Premissas!$B$34)/(1-'Taxas 2026'!$C$17-$F$4-$B$4)),"")) | V17: =IF((1-'Taxas 2026'!$C$18-$F$4-$B$4)<=0,"",IF(MAX('Taxas 2026'!$B$18,(F17+'Taxas 2026'!$D$18+Premissas!$B$34)/(1-'Taxas 2026'!$C$18-$F$4-$B$4))<'Taxas 2026'!$B$19,MAX('Taxas 2026'!$B$18,(F17+'Taxas 2026'!$D$18+Premissas!$B$34)/(1-'Taxas 2026'!$C$18-$F$4-$B$4)),"")) | W17: =IF((1-'Taxas 2026'!$C$19-$F$4-$B$4)<=0,"",IF(MAX('Taxas 2026'!$B$19,(F17+'Taxas 2026'!$D$19+Premissas!$B$34)/(1-'Taxas 2026'!$C$19-$F$4-$B$4))<1000000000,MAX('Taxas 2026'!$B$19,(F17+'Taxas 2026'!$D$19+Premissas!$B$34)/(1-'Taxas 2026'!$C$19-$F$4-$B$4)),"")) -> 362.8972 | X17: =MIN(T17:W17) -> 362.8972 | Y17: =CEILING(X17-4.9,5)+4.9 -> 364.9 | Z17: =((Y17)-(F17+(Y17)*(INDEX('Taxas 2026'!$C$15:$C$19,MATCH((Y17),'Taxas 2026'!$B$15:$B$19,1))+$F$4)+INDEX('Taxas 2026'!$D$15:$D$19,MATCH((Y17),'Taxas 2026'!$B$15:$B$19,1))+Premissas!$B$34))/(Y17) -> 0.15293642 | AA17: =IF(((Y17)-(F17+(Y17)*(INDEX('Taxas 2026'!$C$15:$C$19,MATCH((Y17),'Taxas 2026'!$B$15:$B$19,1))+$F$4)+INDEX('Taxas 2026'!$D$15:$D$19,MATCH((Y17),'Taxas 2026'!$B$15:$B$19,1))+Premissas!$B$34))/(Y17)>=$B$4,Y17,IF(((Y17+5)-(F17+(Y17+5)*(INDEX('Taxas 2026'!$C$15:$C$19,MATCH((Y17+5),'Taxas 2026'!$B$15:$B$19,1))+$F$4)+INDEX('Taxas 2026'!$D$15:$D$19,MATCH((Y17+5),'Taxas 2026'!$B$15:$B$19,1))+Premissas!$B$34))/(Y17+5)>=$B$4,Y17+5,Y17+10)) -> 364.9 | AB17: =((AA17)-(F17+(AA17)*(INDEX('Taxas 2026'!$C$15:$C$19,MATCH((AA17),'Taxas 2026'!$B$15:$B$19,1))+$F$4)+INDEX('Taxas 2026'!$D$15:$D$19,MATCH((AA17),'Taxas 2026'!$B$15:$B$19,1))+Premissas!$B$34))/(AA17) -> 0.15293642 | AC17: =IF((1-'Taxas 2026'!$C$24-$H$4-$B$4)<=0,"",IF(MAX(1,(F17+'Taxas 2026'!$D$24)/(1-'Taxas 2026'!$C$24-$H$4-$B$4))<'Taxas 2026'!$B$25,MAX(1,(F17+'Taxas 2026'!$D$24)/(1-'Taxas 2026'!$C$24-$H$4-$B$4)),"")) | AD17: =IF((1-'Taxas 2026'!$C$25-$H$4-$B$4)<=0,"",IF(MAX('Taxas 2026'!$B$25,(F17+'Taxas 2026'!$D$25)/(1-'Taxas 2026'!$C$25-$H$4-$B$4))<1000000000,MAX('Taxas 2026'!$B$25,(F17+'Taxas 2026'!$D$25)/(1-'Taxas 2026'!$C$25-$H$4-$B$4)),"")) -> 400.34483 | AE17: =MIN(AC17:AD17) -> 400.34483 | AF17: =CEILING(AE17-4.9,5)+4.9 -> 404.9 | AG17: =((AF17)-(F17+(AF17)*(INDEX('Taxas 2026'!$C$24:$C$25,MATCH((AF17),'Taxas 2026'!$B$24:$B$25,1))+$H$4)+INDEX('Taxas 2026'!$D$24:$D$25,MATCH((AF17),'Taxas 2026'!$B$24:$B$25,1))))/(AF17) -> 0.1548938 | AH17: =IF(((AF17)-(F17+(AF17)*(INDEX('Taxas 2026'!$C$24:$C$25,MATCH((AF17),'Taxas 2026'!$B$24:$B$25,1))+$H$4)+INDEX('Taxas 2026'!$D$24:$D$25,MATCH((AF17),'Taxas 2026'!$B$24:$B$25,1))))/(AF17)>=$B$4,AF17,IF(((AF17+5)-(F17+(AF17+5)*(INDEX('Taxas 2026'!$C$24:$C$25,MATCH((AF17+5),'Taxas 2026'!$B$24:$B$25,1))+$H$4)+INDEX('Taxas 2026'!$D$24:$D$25,MATCH((AF17+5),'Taxas 2026'!$B$24:$B$25,1))))/(AF17+5)>=$B$4,AF17+5,AF17+10)) -> 404.9 | AI17: =((AH17)-(F17+(AH17)*(INDEX('Taxas 2026'!$C$24:$C$25,MATCH((AH17),'Taxas 2026'!$B$24:$B$25,1))+$H$4)+INDEX('Taxas 2026'!$D$24:$D$25,MATCH((AH17),'Taxas 2026'!$B$24:$B$25,1))))/(AH17) -> 0.1548938 | AJ17: =MAX(1,(F17+Premissas!$B$45+Premissas!$B$48+INDEX('Frete 2026'!$H$6:$H$11,H17))/(1-$J$4-$B$4)) -> 516.74886 | AK17: =CEILING(AJ17-4.9,5)+4.9 -> 519.9 | AL17: =((AK17)-(F17+Premissas!$B$45+Premissas!$B$48+INDEX('Frete 2026'!$H$6:$H$11,H17)+(AK17)*$J$4))/(AK17) -> 0.1522533 | AM17: =IF(((AK17)-(F17+Premissas!$B$45+Premissas!$B$48+INDEX('Frete 2026'!$H$6:$H$11,H17)+(AK17)*$J$4))/(AK17)>=$B$4,AK17,IF(((AK17+5)-(F17+Premissas!$B$45+Premissas!$B$48+INDEX('Frete 2026'!$H$6:$H$11,H17)+(AK17+5)*$J$4))/(AK17+5)>=$B$4,AK17+5,AK17+10)) -> 519.9 | AN17: =((AM17)-(F17+Premissas!$B$45+Premissas!$B$48+INDEX('Frete 2026'!$H$6:$H$11,H17)+(AM17)*$J$4))/(AM17) -> 0.1522533
A18: Fibra Longa | B18: 10 | C18: =MATCH(A18,'Ficha de Custo'!$B$4:$D$4,0) -> 3 | D18: =INDEX('Ficha de Custo'!$B$14:$D$14,C18) -> 31.83 | E18: =INDEX('Ficha de Custo'!$B$18:$D$21,MATCH(B18,'Ficha de Custo'!$A$18:$A$21,0),C18) -> 12 | F18: =D18*B18+E18 -> 330.3 | G18: =INDEX('Ficha de Custo'!$B$36:$D$39,MATCH(B18,'Ficha de Custo'!$A$36:$A$39,0),C18) -> 2.04 | H18: =MATCH(G18-0.0000001,'Frete 2026'!$A$6:$A$11,1) -> 6 | I18: =IF((1-$D$4-$B$4)<=0,"",IF(MAX(1,(F18+INDEX('Frete 2026'!$B$6:$B$11,H18))/(1-$D$4-$B$4))<79,MAX(1,(F18+INDEX('Frete 2026'!$B$6:$B$11,H18))/(1-$D$4-$B$4)),"")) | J18: =IF((1-$D$4-$B$4)<=0,"",IF(MAX('Frete 2026'!$C$5,(F18+INDEX('Frete 2026'!$C$6:$C$11,H18))/(1-$D$4-$B$4))<'Frete 2026'!$D$5,MAX('Frete 2026'!$C$5,(F18+INDEX('Frete 2026'!$C$6:$C$11,H18))/(1-$D$4-$B$4)),"")) | K18: =IF((1-$D$4-$B$4)<=0,"",IF(MAX('Frete 2026'!$D$5,(F18+INDEX('Frete 2026'!$D$6:$D$11,H18))/(1-$D$4-$B$4))<'Frete 2026'!$E$5,MAX('Frete 2026'!$D$5,(F18+INDEX('Frete 2026'!$D$6:$D$11,H18))/(1-$D$4-$B$4)),"")) | L18: =IF((1-$D$4-$B$4)<=0,"",IF(MAX('Frete 2026'!$E$5,(F18+INDEX('Frete 2026'!$E$6:$E$11,H18))/(1-$D$4-$B$4))<'Frete 2026'!$F$5,MAX('Frete 2026'!$E$5,(F18+INDEX('Frete 2026'!$E$6:$E$11,H18))/(1-$D$4-$B$4)),"")) | M18: =IF((1-$D$4-$B$4)<=0,"",IF(MAX('Frete 2026'!$F$5,(F18+INDEX('Frete 2026'!$F$6:$F$11,H18))/(1-$D$4-$B$4))<'Frete 2026'!$G$5,MAX('Frete 2026'!$F$5,(F18+INDEX('Frete 2026'!$F$6:$F$11,H18))/(1-$D$4-$B$4)),"")) | N18: =IF((1-$D$4-$B$4)<=0,"",IF(MAX('Frete 2026'!$G$5,(F18+INDEX('Frete 2026'!$G$6:$G$11,H18))/(1-$D$4-$B$4))<1000000000,MAX('Frete 2026'!$G$5,(F18+INDEX('Frete 2026'!$G$6:$G$11,H18))/(1-$D$4-$B$4)),"")) -> 640.81081 | O18: =MIN(I18:N18) -> 640.81081 | P18: =CEILING(O18-4.9,5)+4.9 -> 644.9 | Q18: =((P18)-(F18+IF((P18)<79,INDEX('Frete 2026'!$B$6:$B$11,H18),INDEX('Frete 2026'!$C$6:$G$11,H18,MATCH((P18),'Frete 2026'!$C$5:$G$5,1)))+(P18)*$D$4))/(P18) -> 0.15351915 | R18: =IF(((P18)-(F18+IF((P18)<79,INDEX('Frete 2026'!$B$6:$B$11,H18),INDEX('Frete 2026'!$C$6:$G$11,H18,MATCH((P18),'Frete 2026'!$C$5:$G$5,1)))+(P18)*$D$4))/(P18)>=$B$4,P18,IF(((P18+5)-(F18+IF((P18+5)<79,INDEX('Frete 2026'!$B$6:$B$11,H18),INDEX('Frete 2026'!$C$6:$G$11,H18,MATCH((P18+5),'Frete 2026'!$C$5:$G$5,1)))+(P18+5)*$D$4))/(P18+5)>=$B$4,P18+5,P18+10)) -> 644.9 | S18: =((R18)-(F18+IF((R18)<79,INDEX('Frete 2026'!$B$6:$B$11,H18),INDEX('Frete 2026'!$C$6:$G$11,H18,MATCH((R18),'Frete 2026'!$C$5:$G$5,1)))+(R18)*$D$4))/(R18) -> 0.15351915 | T18: =IF((1-'Taxas 2026'!$C$16-$F$4-$B$4)<=0,"",IF(MAX('Taxas 2026'!$B$16,(F18+'Taxas 2026'!$D$16+Premissas!$B$34)/(1-'Taxas 2026'!$C$16-$F$4-$B$4))<'Taxas 2026'!$B$17,MAX('Taxas 2026'!$B$16,(F18+'Taxas 2026'!$D$16+Premissas!$B$34)/(1-'Taxas 2026'!$C$16-$F$4-$B$4)),"")) | U18: =IF((1-'Taxas 2026'!$C$17-$F$4-$B$4)<=0,"",IF(MAX('Taxas 2026'!$B$17,(F18+'Taxas 2026'!$D$17+Premissas!$B$34)/(1-'Taxas 2026'!$C$17-$F$4-$B$4))<'Taxas 2026'!$B$18,MAX('Taxas 2026'!$B$17,(F18+'Taxas 2026'!$D$17+Premissas!$B$34)/(1-'Taxas 2026'!$C$17-$F$4-$B$4)),"")) | V18: =IF((1-'Taxas 2026'!$C$18-$F$4-$B$4)<=0,"",IF(MAX('Taxas 2026'!$B$18,(F18+'Taxas 2026'!$D$18+Premissas!$B$34)/(1-'Taxas 2026'!$C$18-$F$4-$B$4))<'Taxas 2026'!$B$19,MAX('Taxas 2026'!$B$18,(F18+'Taxas 2026'!$D$18+Premissas!$B$34)/(1-'Taxas 2026'!$C$18-$F$4-$B$4)),"")) | W18: =IF((1-'Taxas 2026'!$C$19-$F$4-$B$4)<=0,"",IF(MAX('Taxas 2026'!$B$19,(F18+'Taxas 2026'!$D$19+Premissas!$B$34)/(1-'Taxas 2026'!$C$19-$F$4-$B$4))<1000000000,MAX('Taxas 2026'!$B$19,(F18+'Taxas 2026'!$D$19+Premissas!$B$34)/(1-'Taxas 2026'!$C$19-$F$4-$B$4)),"")) -> 665.98131 | X18: =MIN(T18:W18) -> 665.98131 | Y18: =CEILING(X18-4.9,5)+4.9 -> 669.9 | Z18: =((Y18)-(F18+(Y18)*(INDEX('Taxas 2026'!$C$15:$C$19,MATCH((Y18),'Taxas 2026'!$B$15:$B$19,1))+$F$4)+INDEX('Taxas 2026'!$D$15:$D$19,MATCH((Y18),'Taxas 2026'!$B$15:$B$19,1))+Premissas!$B$34))/(Y18) -> 0.15312957 | AA18: =IF(((Y18)-(F18+(Y18)*(INDEX('Taxas 2026'!$C$15:$C$19,MATCH((Y18),'Taxas 2026'!$B$15:$B$19,1))+$F$4)+INDEX('Taxas 2026'!$D$15:$D$19,MATCH((Y18),'Taxas 2026'!$B$15:$B$19,1))+Premissas!$B$34))/(Y18)>=$B$4,Y18,IF(((Y18+5)-(F18+(Y18+5)*(INDEX('Taxas 2026'!$C$15:$C$19,MATCH((Y18+5),'Taxas 2026'!$B$15:$B$19,1))+$F$4)+INDEX('Taxas 2026'!$D$15:$D$19,MATCH((Y18+5),'Taxas 2026'!$B$15:$B$19,1))+Premissas!$B$34))/(Y18+5)>=$B$4,Y18+5,Y18+10)) -> 669.9 | AB18: =((AA18)-(F18+(AA18)*(INDEX('Taxas 2026'!$C$15:$C$19,MATCH((AA18),'Taxas 2026'!$B$15:$B$19,1))+$F$4)+INDEX('Taxas 2026'!$D$15:$D$19,MATCH((AA18),'Taxas 2026'!$B$15:$B$19,1))+Premissas!$B$34))/(AA18) -> 0.15312957 | AC18: =IF((1-'Taxas 2026'!$C$24-$H$4-$B$4)<=0,"",IF(MAX(1,(F18+'Taxas 2026'!$D$24)/(1-'Taxas 2026'!$C$24-$H$4-$B$4))<'Taxas 2026'!$B$25,MAX(1,(F18+'Taxas 2026'!$D$24)/(1-'Taxas 2026'!$C$24-$H$4-$B$4)),"")) | AD18: =IF((1-'Taxas 2026'!$C$25-$H$4-$B$4)<=0,"",IF(MAX('Taxas 2026'!$B$25,(F18+'Taxas 2026'!$D$25)/(1-'Taxas 2026'!$C$25-$H$4-$B$4))<1000000000,MAX('Taxas 2026'!$B$25,(F18+'Taxas 2026'!$D$25)/(1-'Taxas 2026'!$C$25-$H$4-$B$4)),"")) -> 773.10345 | AE18: =MIN(AC18:AD18) -> 773.10345 | AF18: =CEILING(AE18-4.9,5)+4.9 -> 774.9 | AG18: =((AF18)-(F18+(AF18)*(INDEX('Taxas 2026'!$C$24:$C$25,MATCH((AF18),'Taxas 2026'!$B$24:$B$25,1))+$H$4)+INDEX('Taxas 2026'!$D$24:$D$25,MATCH((AF18),'Taxas 2026'!$B$24:$B$25,1))))/(AF18) -> 0.15100852 | AH18: =IF(((AF18)-(F18+(AF18)*(INDEX('Taxas 2026'!$C$24:$C$25,MATCH((AF18),'Taxas 2026'!$B$24:$B$25,1))+$H$4)+INDEX('Taxas 2026'!$D$24:$D$25,MATCH((AF18),'Taxas 2026'!$B$24:$B$25,1))))/(AF18)>=$B$4,AF18,IF(((AF18+5)-(F18+(AF18+5)*(INDEX('Taxas 2026'!$C$24:$C$25,MATCH((AF18+5),'Taxas 2026'!$B$24:$B$25,1))+$H$4)+INDEX('Taxas 2026'!$D$24:$D$25,MATCH((AF18+5),'Taxas 2026'!$B$24:$B$25,1))))/(AF18+5)>=$B$4,AF18+5,AF18+10)) -> 774.9 | AI18: =((AH18)-(F18+(AH18)*(INDEX('Taxas 2026'!$C$24:$C$25,MATCH((AH18),'Taxas 2026'!$B$24:$B$25,1))+$H$4)+INDEX('Taxas 2026'!$D$24:$D$25,MATCH((AH18),'Taxas 2026'!$B$24:$B$25,1))))/(AH18) -> 0.15100852 | AJ18: =MAX(1,(F18+Premissas!$B$45+Premissas!$B$48+INDEX('Frete 2026'!$H$6:$H$11,H18))/(1-$J$4-$B$4)) -> 971.73855 | AK18: =CEILING(AJ18-4.9,5)+4.9 -> 974.9 | AL18: =((AK18)-(F18+Premissas!$B$45+Premissas!$B$48+INDEX('Frete 2026'!$H$6:$H$11,H18)+(AK18)*$J$4))/(AK18) -> 0.15120558 | AM18: =IF(((AK18)-(F18+Premissas!$B$45+Premissas!$B$48+INDEX('Frete 2026'!$H$6:$H$11,H18)+(AK18)*$J$4))/(AK18)>=$B$4,AK18,IF(((AK18+5)-(F18+Premissas!$B$45+Premissas!$B$48+INDEX('Frete 2026'!$H$6:$H$11,H18)+(AK18+5)*$J$4))/(AK18+5)>=$B$4,AK18+5,AK18+10)) -> 974.9 | AN18: =((AM18)-(F18+Premissas!$B$45+Premissas!$B$48+INDEX('Frete 2026'!$H$6:$H$11,H18)+(AM18)*$J$4))/(AM18) -> 0.15120558
A20: Como o piso é calculado: em cada faixa de preço da plataforma o custo é uma reta, custo = parte fixa + k × preço. O preço que dá a margem mínima nessa faixa é parte fixa ÷ (1 − k − margem). Se ele cai dentro da faixa, vale; se cai abaixo, vale o início da faixa; se cai acima, a faixa é descartada. O piso é o menor valor válido. O sugerido arredonda para o próximo preço terminado em 4,90 ou 9,90 e sobe R$ 5 se o degrau de faixa derrubar a margem.

Sheet Tabela de Precos
A1: TABELA DE LANÇAMENTO — NOVEMBRO DE 2026
A2: Preços em azul: troque para testar. Em branco = fora do canal. Loja própria sem mídia de aquisição (cliente que volta por e-mail, WhatsApp e cartão no pedido).
A4: Oferta | B4: Linha | C4: Peças | D4: CMV | E4: Peso (kg) | F4: Faixa | G4: Preço ML | H4: MC ML | I4: MC ML % | J4: Preço Shopee | K4: MC Shopee | L4: MC Shopee % | M4: Preço TikTok | N4: MC TikTok | O4: MC TikTok % | P4: Preço loja (recompra) | Q4: MC loja | R4: MC loja %
A5: Avulsa Essencial | B5: Essencial | C5: 1 | D5: =INDEX('Ficha de Custo'!$B$30:$D$33,MATCH(C5,'Ficha de Custo'!$A$30:$A$33,0),MATCH(B5,'Ficha de Custo'!$B$4:$D$4,0)) -> 22.02 | E5: =INDEX('Ficha de Custo'!$B$36:$D$39,MATCH(C5,'Ficha de Custo'!$A$36:$A$39,0),MATCH(B5,'Ficha de Custo'!$B$4:$D$4,0)) -> 0.23 | F5: =MATCH(E5-0.0000001,'Frete 2026'!$A$6:$A$11,1) -> 1 | G5: 54.9 | H5: =IF(ISNUMBER(G5),G5-(D5+IF(G5<79,INDEX('Frete 2026'!$B$6:$B$11,F5),INDEX('Frete 2026'!$C$6:$G$11,F5,MATCH(G5,'Frete 2026'!$C$5:$G$5,1)))+G5*'Kits calculo'!$D$4),"") -> 10.1845 | I5: =IF(ISNUMBER(G5),H5/G5,"") -> 0.18551002 | J5: 54.9 | K5: =IF(ISNUMBER(J5),J5-(D5+J5*(INDEX('Taxas 2026'!$C$15:$C$19,MATCH(J5,'Taxas 2026'!$B$15:$B$19,1))+'Kits calculo'!$F$4)+INDEX('Taxas 2026'!$D$15:$D$19,MATCH(J5,'Taxas 2026'!$B$15:$B$19,1))+Premissas!$B$34),"") -> 8.2925 | L5: =IF(ISNUMBER(J5),K5/J5,"") -> 0.15104736 | M5: 64.9 | N5: =IF(ISNUMBER(M5),M5-(D5+M5*(INDEX('Taxas 2026'!$C$24:$C$25,MATCH(M5,'Taxas 2026'!$B$24:$B$25,1))+'Kits calculo'!$H$4)+INDEX('Taxas 2026'!$D$24:$D$25,MATCH(M5,'Taxas 2026'!$B$24:$B$25,1))),"") -> 9.9465 | O5: =IF(ISNUMBER(M5),N5/M5,"") -> 0.15325886 | P5: 59.9 | Q5: =IF(ISNUMBER(P5),P5-(D5+Premissas!$B$45+Premissas!$B$48+INDEX('Frete 2026'!$H$6:$H$11,F5)+P5*'Kits calculo'!$L$4),"") -> 11.24049 | R5: =IF(ISNUMBER(P5),Q5/P5,"") -> 0.18765426
A6: Kit 3 Essencial | B6: Essencial | C6: 3 | D6: =INDEX('Ficha de Custo'!$B$30:$D$33,MATCH(C6,'Ficha de Custo'!$A$30:$A$33,0),MATCH(B6,'Ficha de Custo'!$B$4:$D$4,0)) -> 66.06 | E6: =INDEX('Ficha de Custo'!$B$36:$D$39,MATCH(C6,'Ficha de Custo'!$A$36:$A$39,0),MATCH(B6,'Ficha de Custo'!$B$4:$D$4,0)) -> 0.68 | F6: =MATCH(E6-0.0000001,'Frete 2026'!$A$6:$A$11,1) -> 3 | G6: 169.9 | H6: =IF(ISNUMBER(G6),G6-(D6+IF(G6<79,INDEX('Frete 2026'!$B$6:$B$11,F6),INDEX('Frete 2026'!$C$6:$G$11,F6,MATCH(G6,'Frete 2026'!$C$5:$G$5,1)))+G6*'Kits calculo'!$D$4),"") -> 33.7195 | I6: =IF(ISNUMBER(G6),H6/G6,"") -> 0.19846675 | J6: 169.9 | K6: =IF(ISNUMBER(J6),J6-(D6+J6*(INDEX('Taxas 2026'!$C$15:$C$19,MATCH(J6,'Taxas 2026'!$B$15:$B$19,1))+'Kits calculo'!$F$4)+INDEX('Taxas 2026'!$D$15:$D$19,MATCH(J6,'Taxas 2026'!$B$15:$B$19,1))+Premissas!$B$34),"") -> 30.3215 | L6: =IF(ISNUMBER(J6),K6/J6,"") -> 0.17846675 | M6: 169.9 | N6: =IF(ISNUMBER(M6),M6-(D6+M6*(INDEX('Taxas 2026'!$C$24:$C$25,MATCH(M6,'Taxas 2026'!$B$24:$B$25,1))+'Kits calculo'!$H$4)+INDEX('Taxas 2026'!$D$24:$D$25,MATCH(M6,'Taxas 2026'!$B$24:$B$25,1))),"") -> 27.3315 | O6: =IF(ISNUMBER(M6),N6/M6,"") -> 0.16086816 | P6: 169.9 | Q6: =IF(ISNUMBER(P6),P6-(D6+Premissas!$B$45+Premissas!$B$48+INDEX('Frete 2026'!$H$6:$H$11,F6)+P6*'Kits calculo'!$L$4),"") -> 58.26149 | R6: =IF(ISNUMBER(P6),Q6/P6,"") -> 0.34291636
A7: Avulsa Fibra Longa | B7: Fibra Longa | C7: 1 | D7: =INDEX('Ficha de Custo'!$B$30:$D$33,MATCH(C7,'Ficha de Custo'!$A$30:$A$33,0),MATCH(B7,'Ficha de Custo'!$B$4:$D$4,0)) -> 34.73 | E7: =INDEX('Ficha de Custo'!$B$36:$D$39,MATCH(C7,'Ficha de Custo'!$A$36:$A$39,0),MATCH(B7,'Ficha de Custo'!$B$4:$D$4,0)) -> 0.22 | F7: =MATCH(E7-0.0000001,'Frete 2026'!$A$6:$A$11,1) -> 1 | G7: 119.9 | H7: =IF(ISNUMBER(G7),G7-(D7+IF(G7<79,INDEX('Frete 2026'!$B$6:$B$11,F7),INDEX('Frete 2026'!$C$6:$G$11,F7,MATCH(G7,'Frete 2026'!$C$5:$G$5,1)))+G7*'Kits calculo'!$D$4),"") -> 35.2995 | I7: =IF(ISNUMBER(G7),H7/G7,"") -> 0.29440784 | J7: 119.9 | K7: =IF(ISNUMBER(J7),J7-(D7+J7*(INDEX('Taxas 2026'!$C$15:$C$19,MATCH(J7,'Taxas 2026'!$B$15:$B$19,1))+'Kits calculo'!$F$4)+INDEX('Taxas 2026'!$D$15:$D$19,MATCH(J7,'Taxas 2026'!$B$15:$B$19,1))+Premissas!$B$34),"") -> 27.4015 | L7: =IF(ISNUMBER(J7),K7/J7,"") -> 0.22853628 | M7: 119.9 | N7: =IF(ISNUMBER(M7),M7-(D7+M7*(INDEX('Taxas 2026'!$C$24:$C$25,MATCH(M7,'Taxas 2026'!$B$24:$B$25,1))+'Kits calculo'!$H$4)+INDEX('Taxas 2026'!$D$24:$D$25,MATCH(M7,'Taxas 2026'!$B$24:$B$25,1))),"") -> 29.4115 | O7: =IF(ISNUMBER(M7),N7/M7,"") -> 0.24530025 | P7: 119.9 | Q7: =IF(ISNUMBER(P7),P7-(D7+Premissas!$B$45+Premissas!$B$48+INDEX('Frete 2026'!$H$6:$H$11,F7)+P7*'Kits calculo'!$L$4),"") -> 49.83649 | R7: =IF(ISNUMBER(P7),Q7/P7,"") -> 0.41565046
A8: Kit 3 Fibra Longa | B8: Fibra Longa | C8: 3 | D8: =INDEX('Ficha de Custo'!$B$30:$D$33,MATCH(C8,'Ficha de Custo'!$A$30:$A$33,0),MATCH(B8,'Ficha de Custo'!$B$4:$D$4,0)) -> 102.49 | E8: =INDEX('Ficha de Custo'!$B$36:$D$39,MATCH(C8,'Ficha de Custo'!$A$36:$A$39,0),MATCH(B8,'Ficha de Custo'!$B$4:$D$4,0)) -> 0.65 | F8: =MATCH(E8-0.0000001,'Frete 2026'!$A$6:$A$11,1) -> 3 | G8: 249.9 | H8: =IF(ISNUMBER(G8),G8-(D8+IF(G8<79,INDEX('Frete 2026'!$B$6:$B$11,F8),INDEX('Frete 2026'!$C$6:$G$11,F8,MATCH(G8,'Frete 2026'!$C$5:$G$5,1)))+G8*'Kits calculo'!$D$4),"") -> 51.5395 | I8: =IF(ISNUMBER(G8),H8/G8,"") -> 0.2062405 | J8: 249.9 | K8: =IF(ISNUMBER(J8),J8-(D8+J8*(INDEX('Taxas 2026'!$C$15:$C$19,MATCH(J8,'Taxas 2026'!$B$15:$B$19,1))+'Kits calculo'!$F$4)+INDEX('Taxas 2026'!$D$15:$D$19,MATCH(J8,'Taxas 2026'!$B$15:$B$19,1))+Premissas!$B$34),"") -> 42.6915 | L8: =IF(ISNUMBER(J8),K8/J8,"") -> 0.17083433 | M8: 249.9 | N8: =IF(ISNUMBER(M8),M8-(D8+M8*(INDEX('Taxas 2026'!$C$24:$C$25,MATCH(M8,'Taxas 2026'!$B$24:$B$25,1))+'Kits calculo'!$H$4)+INDEX('Taxas 2026'!$D$24:$D$25,MATCH(M8,'Taxas 2026'!$B$24:$B$25,1))),"") -> 37.7015 | O8: =IF(ISNUMBER(M8),N8/M8,"") -> 0.15086635 | P8: 249.9 | Q8: =IF(ISNUMBER(P8),P8-(D8+Premissas!$B$45+Premissas!$B$48+INDEX('Frete 2026'!$H$6:$H$11,F8)+P8*'Kits calculo'!$L$4),"") -> 90.23949 | R8: =IF(ISNUMBER(P8),Q8/P8,"") -> 0.3611024
A9: Kit 5 Reposição | B9: Essencial | C9: 5 | D9: =INDEX('Ficha de Custo'!$B$30:$D$33,MATCH(C9,'Ficha de Custo'!$A$30:$A$33,0),MATCH(B9,'Ficha de Custo'!$B$4:$D$4,0)) -> 108.1 | E9: =INDEX('Ficha de Custo'!$B$36:$D$39,MATCH(C9,'Ficha de Custo'!$A$36:$A$39,0),MATCH(B9,'Ficha de Custo'!$B$4:$D$4,0)) -> 1.1 | F9: =MATCH(E9-0.0000001,'Frete 2026'!$A$6:$A$11,1) -> 4 | H9: =IF(ISNUMBER(G9),G9-(D9+IF(G9<79,INDEX('Frete 2026'!$B$6:$B$11,F9),INDEX('Frete 2026'!$C$6:$G$11,F9,MATCH(G9,'Frete 2026'!$C$5:$G$5,1)))+G9*'Kits calculo'!$D$4),"") | I9: =IF(ISNUMBER(G9),H9/G9,"") | K9: =IF(ISNUMBER(J9),J9-(D9+J9*(INDEX('Taxas 2026'!$C$15:$C$19,MATCH(J9,'Taxas 2026'!$B$15:$B$19,1))+'Kits calculo'!$F$4)+INDEX('Taxas 2026'!$D$15:$D$19,MATCH(J9,'Taxas 2026'!$B$15:$B$19,1))+Premissas!$B$34),"") | L9: =IF(ISNUMBER(J9),K9/J9,"") | N9: =IF(ISNUMBER(M9),M9-(D9+M9*(INDEX('Taxas 2026'!$C$24:$C$25,MATCH(M9,'Taxas 2026'!$B$24:$B$25,1))+'Kits calculo'!$H$4)+INDEX('Taxas 2026'!$D$24:$D$25,MATCH(M9,'Taxas 2026'!$B$24:$B$25,1))),"") | O9: =IF(ISNUMBER(M9),N9/M9,"") | P9: 199.9 | Q9: =IF(ISNUMBER(P9),P9-(D9+Premissas!$B$45+Premissas!$B$48+INDEX('Frete 2026'!$H$6:$H$11,F9)+P9*'Kits calculo'!$L$4),"") -> 38.87449 | R9: =IF(ISNUMBER(P9),Q9/P9,"") -> 0.19446968
A10: Kit 10 Reposição | B10: Essencial | C10: 10 | D10: =INDEX('Ficha de Custo'!$B$30:$D$33,MATCH(C10,'Ficha de Custo'!$A$30:$A$33,0),MATCH(B10,'Ficha de Custo'!$B$4:$D$4,0)) -> 212.7 | E10: =INDEX('Ficha de Custo'!$B$36:$D$39,MATCH(C10,'Ficha de Custo'!$A$36:$A$39,0),MATCH(B10,'Ficha de Custo'!$B$4:$D$4,0)) -> 2.14 | F10: =MATCH(E10-0.0000001,'Frete 2026'!$A$6:$A$11,1) -> 6 | H10: =IF(ISNUMBER(G10),G10-(D10+IF(G10<79,INDEX('Frete 2026'!$B$6:$B$11,F10),INDEX('Frete 2026'!$C$6:$G$11,F10,MATCH(G10,'Frete 2026'!$C$5:$G$5,1)))+G10*'Kits calculo'!$D$4),"") | I10: =IF(ISNUMBER(G10),H10/G10,"") | K10: =IF(ISNUMBER(J10),J10-(D10+J10*(INDEX('Taxas 2026'!$C$15:$C$19,MATCH(J10,'Taxas 2026'!$B$15:$B$19,1))+'Kits calculo'!$F$4)+INDEX('Taxas 2026'!$D$15:$D$19,MATCH(J10,'Taxas 2026'!$B$15:$B$19,1))+Premissas!$B$34),"") | L10: =IF(ISNUMBER(J10),K10/J10,"") | N10: =IF(ISNUMBER(M10),M10-(D10+M10*(INDEX('Taxas 2026'!$C$24:$C$25,MATCH(M10,'Taxas 2026'!$B$24:$B$25,1))+'Kits calculo'!$H$4)+INDEX('Taxas 2026'!$D$24:$D$25,MATCH(M10,'Taxas 2026'!$B$24:$B$25,1))),"") | O10: =IF(ISNUMBER(M10),N10/M10,"") | P10: 369.9 | Q10: =IF(ISNUMBER(P10),P10-(D10+Premissas!$B$45+Premissas!$B$48+INDEX('Frete 2026'!$H$6:$H$11,F10)+P10*'Kits calculo'!$L$4),"") -> 72.64149 | R10: =IF(ISNUMBER(P10),Q10/P10,"") -> 0.19638143
A12: Células abaixo da margem mínima | B12: =COUNTIF(I5:I10,"<"&Premissas!$B$18)+COUNTIF(L5:L10,"<"&Premissas!$B$18)+COUNTIF(O5:O10,"<"&Premissas!$B$18)+COUNTIF(R5:R10,"<"&Premissas!$B$18) -> 0
A13: Os preços terminam em 4,90 ou 9,90. A avulsa fica abaixo de R$ 79 no ML (o ML banca o frete) e sobe para R$ 64,90 no TikTok, onde o preço carrega 15% de comissão ao afiliado. Os kits de 5 e 10 existem só na loja própria, como reposição para quem já comprou.

Sheet Benchmark
A1: BENCHMARK DE PREÇOS PRATICADOS — SETEMBRO DE 2026
A2: 34 ofertas reais em lojas oficiais, marketplaces e comunidades de ofertas ("oferta registrada" = preço promocional publicado por usuários). R$ por peça = preço ÷ peças.
A4: Grupo | B4: Peças | C4: Segmento | D4: Oferta | E4: Canal | F4: Especificação declarada | G4: Preço (R$) | H4: R$ por peça | I4: Sinal de escala | J4: Fonte
A5: 1 | B5: 1 | C5: Commodity | D5: Almeida Bueno | E5: Loja própria | F5: 100% algodão, tradicional | G5: 14.9 | H5: =G5/B5 -> 14.9 | I5: Fornecedor de revenda para marketplace | J5: almeidabueno.store
A6: 1 | B6: 1 | C6: Commodity | D6: Riachuelo · Classic Premium | E6: Loja própria | F6: 100% algodão peruano | G6: 29.9 | H6: =G6/B6 -> 29.9 | I6: Promoção, de R$ 69,90 | J6: riachuelo.com.br
A7: 1 | B7: 1 | C7: Commodity | D7: Old Rules | E7: Mercado Livre | F7: 100% algodão 30.1 penteado, slim | G7: 33.55 | H7: =G7/B7 -> 33.55 | I7: Loja oficial | J7: Mercado Livre
A8: 1 | B8: 1 | C8: Commodity | D8: Anúncio oversized | E8: Mercado Livre | F8: 100% algodão, oversized | G8: 39.92 | H8: =G8/B8 -> 39.92 | I8: +1.000 vendidos | J8: Mercado Livre
A9: 1 | B9: 1 | C9: Básico com marca | D9: Malwee | E9: Amazon | F9: 100% algodão | G9: 44.87 | H9: =G9/B9 -> 44.87 | I9: De R$ 59,90 | J9: Amazon
A10: 1 | B10: 1 | C10: Básico com marca | D10: Hering · Camiseta Brasil | E10: Loja, app e revendas | F10: 100% algodão, 175 g/m², fio próprio | G10: 49.99 | H10: =G10/B10 -> 49.99 | I10: Lançada em 03/09/2026 | J10: Hering, InfoMoney
A11: 1 | B11: 1 | C11: Premium | D11: Minimal Club · outlet | E11: Loja própria | F11: 93% algodão egípcio | G11: 76.73 | H11: =G11/B11 -> 76.73 | I11: Preço no Pix | J11: minimalclub.com.br
A12: 1 | B12: 1 | C12: Premium | D12: Insider · Tech T-shirt | E12: Loja própria | F12: Modal INTECH, antiodor | G12: 135 | H12: =G12/B12 -> 135 | I12: Preço de entrada | J12: insiderstore.com.br
A13: 1 | B13: 1 | C13: Premium | D13: We Basic · Pima | E13: Loja própria | F13: Algodão Pima | G13: 298 | H13: =G13/B13 -> 298 | I13: — | J13: webasicbrasil.com.br
A14: 1 | B14: 1 | C14: Premium | D14: Calvin Klein | E14: Loja própria | F14: Gola careca masculina | G14: 329 | H14: =G14/B14 -> 329 | I14: — | J14: calvinklein.com.br
A15: 3 | B15: 3 | C15: Commodity | D15: Kit 3 básicas algodão | E15: Amazon | F15: Algodão | G15: 46.99 | H15: =G15/B15 -> 15.663333 | I15: Oferta registrada | J15: Pelando
A16: 3 | B16: 3 | C16: Commodity | D16: Kit 3 · loja Shopee | E16: Shopee | F16: Algodão | G16: 58.99 | H16: =G16/B16 -> 19.663333 | I16: 161 vendas por mês | J16: Radar Almeida Bueno, 20/08/2026
... A38: 10 | B38: 10 | C38: Básico com marca | D38: Old Rules · kit 10 | E38: Mercado Livre | F38: 100% algodão 30.1 penteado | G38: 224.99 | H38: =G38/B38 -> 22.499 | I38: Full · entrega rápida | J38: Mercado Livre
A41: RESUMO — R$ POR PEÇA POR TAMANHO DE KIT E SEGMENTO (KITS DE 4 E 6 PEÇAS NO GRUPO DO KIT 5)
A42: Grupo | B42: Ofertas | C42: Segmento | D42: Mínimo | E42: Mediana | F42: Máximo
A43: 1 | B43: =COUNT(H5:H8) -> 4 | C43: Commodity | D43: =MIN(H5:H8) -> 14.9 | E43: =MEDIAN(H5:H8) -> 31.725 | F43: =MAX(H5:H8) -> 39.92
A44: 1 | B44: =COUNT(H9:H10) -> 2 | C44: Básico com marca | D44: =MIN(H9:H10) -> 44.87 | E44: =MEDIAN(H9:H10) -> 47.43 | F44: =MAX(H9:H10) -> 49.99
A45: 1 | B45: =COUNT(H11:H14) -> 4 | C45: Premium | D45: =MIN(H11:H14) -> 76.73 | E45: =MEDIAN(H11:H14) -> 216.5 | F45: =MAX(H11:H14) -> 329
A46: 3 | B46: =COUNT(H15:H18) -> 4 | C46: Commodity | D46: =MIN(H15:H18) -> 15.663333 | E46: =MEDIAN(H15:H18) -> 19.815 | F46: =MAX(H15:H18) -> 23.3
A47: 3 | B47: =COUNT(H19:H24) -> 6 | C47: Básico com marca | D47: =MIN(H19:H24) -> 16.53 | E47: =MEDIAN(H19:H24) -> 39.996667 | F47: =MAX(H19:H24) -> 52.33
A48: 3 | B48: =COUNT(H25:H25) -> 1 | C48: Premium | D48: =MIN(H25:H25) -> 55.453333 | E48: =MEDIAN(H25:H25) -> 55.453333 | F48: =MAX(H25:H25) -> 55.453333
A49: 5 | B49: =COUNT(H26:H28) -> 3 | C49: Commodity | D49: =MIN(H26:H28) -> 7.772 | E49: =MEDIAN(H26:H28) -> 12.6 | F49: =MAX(H26:H28) -> 17
A50: 5 | B50: =COUNT(H29:H32) -> 4 | C50: Básico com marca | D50: =MIN(H29:H32) -> 21.998 | E50: =MEDIAN(H29:H32) -> 24.417667 | F50: =MAX(H29:H32) -> 34.998
A51: 5 | B51: =COUNT(H33:H35) -> 3 | C51: Premium | D51: =MIN(H33:H35) -> 44.975 | E51: =MEDIAN(H33:H35) -> 114.7875 | F51: =MAX(H33:H35) -> 127.7
A52: 10 | B52: =COUNT(H36:H36) -> 1 | C52: Commodity | D52: =MIN(H36:H36) -> 14.99 | E52: =MEDIAN(H36:H36) -> 14.99 | F52: =MAX(H36:H36) -> 14.99
A53: 10 | B53: =COUNT(H37:H38) -> 2 | C53: Básico com marca | D53: =MIN(H37:H38) -> 18.089 | E53: =MEDIAN(H37:H38) -> 20.294 | F53: =MAX(H37:H38) -> 22.499
A55: TOP 10 — OS NOMES QUE DEFINEM O PREÇO DA CAMISETA BÁSICA EM 2026
A56: # | B56: Peças | C56: Quem | D56: Oferta-âncora | E56: Onde vende | F56: Sinal de escala | G56: Preço (R$) | H56: R$ por peça | I56: O que ensina
A57: 1 | B57: 1 | C57: Hering (Arezzo&Co após a cisão) | D57: Camiseta Brasil, 175 g/m² | E57: Loja, app, revendas, ML | F57: Maior lançamento em 30 anos; kit 5 revendido a R$ 109,99–174,99 | G57: 49.99 | H57: =G57/B57 -> 49.99 | I57: Fixou o teto da avulsa. Acima de R$ 55 sem marca, a peça perde a comparação.
A58: 2 | B58: 5 | C58: Zaroc | D58: Kit 5 slim 100% algodão | E58: ML (loja oficial) | F58: Mais de 1 milhão de peças em marketplaces | G58: 123.01 | H58: =G58/B58 -> 24.602 | I58: Kit 5 é jogo de escala: R$ 24,60 por peça.
A59: 3 | B59: 3 | C59: Insider | D59: Kit 3 Tech T-shirt (modal) | E59: Loja própria, marketplaces | F59: R$ 400 mi (2024) → R$ 800 mi projetados (2026) | G59: 166.36 | H59: =G59/B59 -> 55.453333 | I59: Vende o defeito eliminado, não o tecido.
A60: 4 | B60: 4 | C60: Minimal Club | D60: Kit 4, 93% algodão egípcio | E60: Loja própria, TikTok | F60: R$ 4 mi (2021) → R$ 100 mi (2025); 250 mil clientes | G60: 459.15 | H60: =G60/B60 -> 114.7875 | I60: "Algodão egípcio, minimal" é marca, não malha: R$ 115 por peça.
A61: 5 | B61: 3 | C61: Malwee (Jaraguá do Sul/SC) | D61: Kit 3 100% algodão | E61: ML, Amazon | F61: Avulsa a R$ 44,87 na Amazon | G61: 156.99 | H61: =G61/B61 -> 52.33 | I61: É o teto do kit 3 com marca: R$ 52 por peça.
A62: 6 | B62: 3 | C62: Reserva (Soma após a cisão) | D62: Kit 3 básicas | E62: Amazon, Dafiti, Netshoes | F62: Até R$ 233,82 conforme cor e tamanho | G62: 143.82 | H62: =G62/B62 -> 47.94 | I62: Grade e cor são preço: o mesmo kit varia 60%.
A63: 7 | B63: 10 | C63: Old Rules | D63: Kit 10, 100% algodão 30.1 | E63: ML (loja oficial), Shopee | F63: Kit 3 a R$ 69,90; kit 10 de R$ 180,89 a R$ 224,99 | G63: 224.99 | H63: =G63/B63 -> 22.499 | I63: Kit 10 é anunciado como "atacado revenda".
A64: 8 | B64: 3 | C64: SHEIN | D64: Kit 3 masculino, algodão | E64: SHEIN | F64: 1º mais vendido, 10 mil+ | G64: 59.9 | H64: =G64/B64 -> 19.966667 | I64: O piso global do kit 3: R$ 20 por peça.
A65: 9 | B65: 1 | C65: Riachuelo | D65: Avulsa, algodão peruano | E65: Loja, app | F65: Promoção, de R$ 69,90 | G65: 29.9 | H65: =G65/B65 -> 29.9 | I65: Fibra nomeada a R$ 29,90 no varejo de massa.
A66: 10 | B66: 4 | C66: Vendedor TikTok · kit 4 "algodão egípcio" | D66: Kit 4, declarado 95% egípcio | E66: TikTok Shop | F66: 16 mil+ vendidos, nota 4,8 | G66: 179.9 | H66: =G66/B66 -> 44.975 | I66: O briefing vende, mas a R$ 45 por peça não é fibra longa de verdade.
A67: Menção local: UP Básico, de Brusque/SC, vende kit de 10 camisetas 100% algodão 30.1 a R$ 149,90 (R$ 14,99 por peça). Ranking exato de faturamento por vendedor dentro de cada marketplace só existe em ferramentas pagas (Nubimetrics, Kalodata); a seleção usa preço praticado e sinais públicos de escala.

Sheet Cores
A1: CARTELA DE CORES E LOTE DE LANÇAMENTO
A2: Núcleo (o que vende o ano todo) + Terra (tendência que já virou neutro). Os tons indicados com ≈ são aproximações de tela: aprove cada cor em lab dip físico.
A4: Kits no lote de lançamento | B4: 1200
A6: PALETA
A7: Cor | B7: Família | C7: Hex | D7: Referência | K7: Papel
A8: Preto | B8: Núcleo | C8: #16181C | D8: tingimento reativo | K8: A cor nº 1 de camiseta; a que mais desbota.
A9: Branco óptico | B9: Núcleo | C9: #FAFAF8 | D9: alvejamento óptico | K9: Exige malha que não fica transparente.
A10: Cinza mescla | B10: Núcleo | C10: #A3A7AC | D10: fio tinto | K10: Declarar a composição exata desta cor.
A11: Azul-marinho | B11: Núcleo | C11: #1F2A44 | D11: tingimento reativo | K11: O terceiro neutro.
A12: Verde-oliva | B12: Terra | C12: #5F6B3E | D12: verde militar | K12: Aparece nos kits de 4 do TikTok Shop.
A13: Off-white Nuvem | B13: Terra | C13: #F0EEE9 | D13: ≈ Pantone 11-4201 Cloud Dancer (cor de 2026) | K13: Primeiro branco cor do ano da Pantone.
A14: Areia | B14: Terra | C14: #D6C6A8 | D14: bege/areia | K14: Verão 2027 masculino: bege, areia, off-white.
A15: Café | B15: Terra | C15: #A47764 | D15: ≈ Pantone 17-1230 Mocha Mousse (cor de 2025) | K15: O marrom virou neutro.
A16: Acento 2027, só em avulsa e em lote pequeno: Azul luminoso (≈ WGSN × Coloro Luminous Blue, cor de 2027), Manteiga (ELLE Brasil, verão 2027) e Argila (≈ WGSN × Coloro Clay, S/S 27).
A18: COMPOSIÇÃO DOS KITS DE 3 — PEÇAS DE CADA COR
A19: Kit | B19: Preto | C19: Branco óptico | D19: Cinza mescla | E19: Azul-marinho | F19: Verde-oliva | G19: Off-white Nuvem | H19: Areia | I19: Café | J19: Peças | K19: Participação nos kits
A20: Clássico | B20: 1 | C20: 1 | D20: 1 | E20: 0 | F20: 0 | G20: 0 | H20: 0 | I20: 0 | J20: =SUM(B20:I20) -> 3 | K20: 0.35
A21: All Black | B21: 3 | C21: 0 | D21: 0 | E21: 0 | F21: 0 | G21: 0 | H21: 0 | I21: 0 | J21: =SUM(B21:I21) -> 3 | K21: 0.2
A22: Urbano | B22: 1 | C22: 0 | D22: 0 | E22: 1 | F22: 1 | G22: 0 | H22: 0 | I22: 0 | J22: =SUM(B22:I22) -> 3 | K22: 0.2
A23: Terra | B23: 0 | C23: 0 | D23: 0 | E23: 0 | F23: 0 | G23: 1 | H23: 1 | I23: 1 | J23: =SUM(B23:I23) -> 3 | K23: 0.15
A24: All White | B24: 0 | C24: 3 | D24: 0 | E24: 0 | F24: 0 | G24: 0 | H24: 0 | I24: 0 | J24: =SUM(B24:I24) -> 3 | K24: 0.1
A25: Total | K25: =SUM(K20:K24) -> 1
A27: KITS POR TAMANHO E COMPOSIÇÃO = ARRED(KITS DO TAMANHO × PARTICIPAÇÃO)
A28: Kit | B28: P | C28: M | D28: G | E28: GG | F28: XG | G28: Total
A29: Kits do tamanho | B29: ='Grade de Medidas'!N5 -> 180 | C29: ='Grade de Medidas'!N6 -> 360 | D29: ='Grade de Medidas'!N7 -> 360 | E29: ='Grade de Medidas'!N8 -> 204 | F29: ='Grade de Medidas'!N9 -> 96 | G29: =SUM(B29:F29) -> 1200
A30: Clássico | B30: =ROUND(B$29*$K20,0) -> 63 | C30: =ROUND(C$29*$K20,0) -> 126 | D30: =ROUND(D$29*$K20,0) -> 126 | E30: =ROUND(E$29*$K20,0) -> 71 | F30: =ROUND(F$29*$K20,0) -> 34 | G30: =SUM(B30:F30) -> 420
A31: All Black | B31: =ROUND(B$29*$K21,0) -> 36 | C31: =ROUND(C$29*$K21,0) -> 72 | D31: =ROUND(D$29*$K21,0) -> 72 | E31: =ROUND(E$29*$K21,0) -> 41 | F31: =ROUND(F$29*$K21,0) -> 19 | G31: =SUM(B31:F31) -> 240
A32: Urbano | B32: =ROUND(B$29*$K22,0) -> 36 | C32: =ROUND(C$29*$K22,0) -> 72 | D32: =ROUND(D$29*$K22,0) -> 72 | E32: =ROUND(E$29*$K22,0) -> 41 | F32: =ROUND(F$29*$K22,0) -> 19 | G32: =SUM(B32:F32) -> 240
A33: Terra | B33: =ROUND(B$29*$K23,0) -> 27 | C33: =ROUND(C$29*$K23,0) -> 54 | D33: =ROUND(D$29*$K23,0) -> 54 | E33: =ROUND(E$29*$K23,0) -> 31 | F33: =ROUND(F$29*$K23,0) -> 14 | G33: =SUM(B33:F33) -> 180
A34: All White | B34: =ROUND(B$29*$K24,0) -> 18 | C34: =ROUND(C$29*$K24,0) -> 36 | D34: =ROUND(D$29*$K24,0) -> 36 | E34: =ROUND(E$29*$K24,0) -> 20 | F34: =ROUND(F$29*$K24,0) -> 10 | G34: =SUM(B34:F34) -> 120
A36: LOTE DE LANÇAMENTO — PEÇAS POR COR E TAMANHO
A37: Cor | B37: P | C37: M | D37: G | E37: GG | F37: XG | G37: Total | H37: Participação
A38: Preto | B38: =SUMPRODUCT(B$30:B$34,$B$20:$B$24) -> 207 | C38: =SUMPRODUCT(C$30:C$34,$B$20:$B$24) -> 414 | D38: =SUMPRODUCT(D$30:D$34,$B$20:$B$24) -> 414 | E38: =SUMPRODUCT(E$30:E$34,$B$20:$B$24) -> 235 | F38: =SUMPRODUCT(F$30:F$34,$B$20:$B$24) -> 110 | G38: =SUM(B38:F38) -> 1380 | H38: =G38/$G$46 -> 0.38333333
A39: Branco óptico | B39: =SUMPRODUCT(B$30:B$34,$C$20:$C$24) -> 117 | C39: =SUMPRODUCT(C$30:C$34,$C$20:$C$24) -> 234 | D39: =SUMPRODUCT(D$30:D$34,$C$20:$C$24) -> 234 | E39: =SUMPRODUCT(E$30:E$34,$C$20:$C$24) -> 131 | F39: =SUMPRODUCT(F$30:F$34,$C$20:$C$24) -> 64 | G39: =SUM(B39:F39) -> 780 | H39: =G39/$G$46 -> 0.21666667
A40: Cinza mescla | B40: =SUMPRODUCT(B$30:B$34,$D$20:$D$24) -> 63 | C40: =SUMPRODUCT(C$30:C$34,$D$20:$D$24) -> 126 | D40: =SUMPRODUCT(D$30:D$34,$D$20:$D$24) -> 126 | E40: =SUMPRODUCT(E$30:E$34,$D$20:$D$24) -> 71 | F40: =SUMPRODUCT(F$30:F$34,$D$20:$D$24) -> 34 | G40: =SUM(B40:F40) -> 420 | H40: =G40/$G$46 -> 0.11666667
A41: Azul-marinho | B41: =SUMPRODUCT(B$30:B$34,$E$20:$E$24) -> 36 | C41: =SUMPRODUCT(C$30:C$34,$E$20:$E$24) -> 72 | D41: =SUMPRODUCT(D$30:D$34,$E$20:$E$24) -> 72 | E41: =SUMPRODUCT(E$30:E$34,$E$20:$E$24) -> 41 | F41: =SUMPRODUCT(F$30:F$34,$E$20:$E$24) -> 19 | G41: =SUM(B41:F41) -> 240 | H41: =G41/$G$46 -> 0.066666667
A42: Verde-oliva | B42: =SUMPRODUCT(B$30:B$34,$F$20:$F$24) -> 36 | C42: =SUMPRODUCT(C$30:C$34,$F$20:$F$24) -> 72 | D42: =SUMPRODUCT(D$30:D$34,$F$20:$F$24) -> 72 | E42: =SUMPRODUCT(E$30:E$34,$F$20:$F$24) -> 41 | F42: =SUMPRODUCT(F$30:F$34,$F$20:$F$24) -> 19 | G42: =SUM(B42:F42) -> 240 | H42: =G42/$G$46 -> 0.066666667
A43: Off-white Nuvem | B43: =SUMPRODUCT(B$30:B$34,$G$20:$G$24) -> 27 | C43: =SUMPRODUCT(C$30:C$34,$G$20:$G$24) -> 54 | D43: =SUMPRODUCT(D$30:D$34,$G$20:$G$24) -> 54 | E43: =SUMPRODUCT(E$30:E$34,$G$20:$G$24) -> 31 | F43: =SUMPRODUCT(F$30:F$34,$G$20:$G$24) -> 14 | G43: =SUM(B43:F43) -> 180 | H43: =G43/$G$46 -> 0.05
A44: Areia | B44: =SUMPRODUCT(B$30:B$34,$H$20:$H$24) -> 27 | C44: =SUMPRODUCT(C$30:C$34,$H$20:$H$24) -> 54 | D44: =SUMPRODUCT(D$30:D$34,$H$20:$H$24) -> 54 | E44: =SUMPRODUCT(E$30:E$34,$H$20:$H$24) -> 31 | F44: =SUMPRODUCT(F$30:F$34,$H$20:$H$24) -> 14 | G44: =SUM(B44:F44) -> 180 | H44: =G44/$G$46 -> 0.05
A45: Café | B45: =SUMPRODUCT(B$30:B$34,$I$20:$I$24) -> 27 | C45: =SUMPRODUCT(C$30:C$34,$I$20:$I$24) -> 54 | D45: =SUMPRODUCT(D$30:D$34,$I$20:$I$24) -> 54 | E45: =SUMPRODUCT(E$30:E$34,$I$20:$I$24) -> 31 | F45: =SUMPRODUCT(F$30:F$34,$I$20:$I$24) -> 14 | G45: =SUM(B45:F45) -> 180 | H45: =G45/$G$46 -> 0.05
A46: Total de peças | B46: =SUM(B38:B45) -> 540 | C46: =SUM(C38:C45) -> 1080 | D46: =SUM(D38:D45) -> 1080 | E46: =SUM(E38:E45) -> 612 | F46: =SUM(F38:F45) -> 288 | G46: =SUM(G38:G45) -> 3600 | H46: =SUM(H38:H45) -> 1

Sheet Grade de Medidas
A1: FICHA DE MODELAGEM — CAMISETA ESSENCIAL, MODELAGEM REGULAR
A2: Medidas da peça pronta em cm. Tórax do corpo pela ABNT NBR 16060 (XG extrapolado pelo mesmo passo de 8 cm). A = ½ tórax, B = comprimento, C = ombro, D = manga, E = ½ boca da manga, F = decote, G = profundidade do decote.
A4: Tamanho | B4: Tórax do corpo (cm) | C4: Ponto médio do corpo | D4: A | E4: B | F4: C | G4: D | H4: E | I4: F | J4: G | K4: Folga no tórax | L4: Consumo de malha (× média M/G) | M4: Grade de produção | N4: Kits no lote | O4: Peças no lote
A5: P | B5: 84–88 | C5: 86 | D5: 50 | E5: 69 | F5: 43 | G5: 19 | H5: 16 | I5: 17 | J5: 9 | K5: =2*D5-C5 -> 14 | L5: =D5*E5/((D$6*E$6+D$7*E$7)/2) -> 0.85523054 | M5: 0.15 | N5: =ROUND(Cores!$B$4*M5,0) -> 180 | O5: =N5*3 -> 540
A6: M | B6: 92–96 | C6: 94 | D6: 54 | E6: 71 | F6: 45 | G6: 20 | H6: 17 | I6: 17.5 | J6: 9.5 | K6: =2*D6-C6 -> 14 | L6: =D6*E6/((D$6*E$6+D$7*E$7)/2) -> 0.95042142 | M6: 0.3 | N6: =ROUND(Cores!$B$4*M6,0) -> 360 | O6: =N6*3 -> 1080
A7: G | B7: 100–104 | C7: 102 | D7: 58 | E7: 73 | F7: 47 | G7: 21 | H7: 18 | I7: 18 | J7: 10 | K7: =2*D7-C7 -> 14 | L7: =D7*E7/((D$6*E$6+D$7*E$7)/2) -> 1.0495786 | M7: 0.3 | N7: =ROUND(Cores!$B$4*M7,0) -> 360 | O7: =N7*3 -> 1080
A8: GG | B8: 108–112 | C8: 110 | D8: 62 | E8: 75 | F8: 49 | G8: 22 | H8: 19 | I8: 18.5 | J8: 10.5 | K8: =2*D8-C8 -> 14 | L8: =D8*E8/((D$6*E$6+D$7*E$7)/2) -> 1.152702 | M8: 0.17 | N8: =ROUND(Cores!$B$4*M8,0) -> 204 | O8: =N8*3 -> 612
A9: XG | B9: 116–120 | C9: 118 | D9: 66 | E9: 77 | F9: 51 | G9: 23 | H9: 20 | I9: 19 | J9: 11 | K9: =2*D9-C9 -> 14 | L9: =D9*E9/((D$6*E$6+D$7*E$7)/2) -> 1.2597918 | M9: 0.08 | N9: =ROUND(Cores!$B$4*M9,0) -> 96 | O9: =N9*3 -> 288
A10: Total | M10: =SUM(M5:M9) -> 1 | N10: =SUM(N5:N9) -> 1200 | O10: =SUM(O5:O9) -> 3600
A12: Consumo médio ponderado pela grade | L12: =SUMPRODUCT(M5:M9,L5:L9) -> 1.0250273
A13: Malha a mais por peça na Essencial (R$) | L13: =(L12-1)*'Ficha de Custo'!C8 -> 0.25828141
A14: Malha a mais em cada XG na Essencial (R$) | L14: =(L9-1)*'Ficha de Custo'!C8 -> 2.6810511
A16: Grade: M e G concentram perto de 30% das vendas cada no varejo brasileiro; a regra 1-2-2-1 produz P e GG pela metade de M e G; o XG entra porque 64,9% dos homens adultos das capitais tinham excesso de peso em 2024 (Vigitel). Recalibre com as vendas dos primeiros 60 dias.
A18: TOLERÂNCIAS E ENSAIOS
A19: Item | B19: Especificação | H19: Tolerância ou método
A20: A, B e C | B20: Tabela acima | H20: ± 1,0 cm
A21: D, E, F e G | B21: Tabela acima | H21: ± 0,5 cm
A22: Gramatura | B22: 180 g/m² | H22: ± 5% (171 a 189 g/m²)
A23: Encolhimento | B23: ≤ 5% no comprimento e na largura; meta ≤ 3% com malha pré-encolhida | H23: ABNT NBR ISO 6330 + ISO 5077
A24: Torção lateral | B24: ≤ 5% | H24: ISO 16322
A25: Solidez à lavagem | B25: Nota ≥ 4 na escala de cinza | H25: ABNT NBR ISO 105-C06
A26: Etiqueta | B26: Composição, CNPJ, origem, conservação e tamanho | H26: Resolução Conmetro nº 2/2008
A27: Acabamento | B27: Ribana 1×1 de 2 cm; barra de 2,5 cm (manga 2 cm) em duas agulhas; ombro a ombro com fita | H27: Inspeção visual por lote

Sheet Cenarios
A1: OS SEIS CAMINHOS — COMPARAÇÃO NO MERCADO LIVRE
A2: Mesma plataforma, mesmas regras. Só mudam produto, kit e preço. Colunas azuis são editáveis; custo, embalagem e peso vêm da Ficha de Custo.
A4: Caminho | B4: Custo/peça | C4: Peças | D4: Embalagem | E4: Peso (kg) | F4: Faixa | G4: Preço do kit | H4: CMV | I4: Comissão | J4: Custo logístico | K4: Frete | L4: Mídia | M4: Imposto | N4: Devolução | O4: Total custos | P4: MC R$ | Q4: MC % | R4: Veredito
A5: A. Kit 5 · Essencial · R$ 99 | B5: ='Ficha de Custo'!C14 -> 20.52 | C5: 5 | D5: ='Ficha de Custo'!C20 -> 5.5 | E5: ='Ficha de Custo'!C38 -> 1.1 | F5: =MATCH(E5-0.0000001,'Frete 2026'!$A$6:$A$11,1) -> 4 | G5: 99 | H5: =B5*C5+D5 -> 108.1 | I5: =G5*Premissas!$B$26 -> 13.86 | J5: =IF(G5<79,INDEX('Frete 2026'!$B$6:$B$11,F5),0) -> 0 | K5: =IF(G5>=79,INDEX('Frete 2026'!$C$6:$G$11,F5,MATCH(G5,'Frete 2026'!$C$5:$G$5,1)),0) -> 16.05 | L5: =G5*Premissas!$B$27 -> 5.94 | M5: =G5*Premissas!$B$21 -> 4.455 | N5: =G5*Premissas!$B$22 -> 4.95 | O5: =SUM(H5:N5) -> 153.355 | P5: =G5-O5 -> -54.355 | Q5: =IF(G5=0,0,P5/G5) -> -0.5490404 | R5: =IF(Q5<0,"INVIÁVEL",IF(Q5<Premissas!$B$18,"ABAIXO DO MÍNIMO",IF(Q5<0.25,"SAUDÁVEL","FORTE"))) -> INVIÁVEL
A6: B. Kit 5 · Popular · R$ 99 | B6: ='Ficha de Custo'!B14 -> 10.43 | C6: 5 | D6: ='Ficha de Custo'!B20 -> 1.1 | E6: ='Ficha de Custo'!B38 -> 0.9 | F6: =MATCH(E6-0.0000001,'Frete 2026'!$A$6:$A$11,1) -> 3 | G6: 99 | H6: =B6*C6+D6 -> 53.25 | I6: =G6*Premissas!$B$26 -> 13.86 | J6: =IF(G6<79,INDEX('Frete 2026'!$B$6:$B$11,F6),0) -> 0 | K6: =IF(G6>=79,INDEX('Frete 2026'!$C$6:$G$11,F6,MATCH(G6,'Frete 2026'!$C$5:$G$5,1)),0) -> 13.55 | L6: =G6*Premissas!$B$27 -> 5.94 | M6: =G6*Premissas!$B$21 -> 4.455 | N6: =G6*Premissas!$B$22 -> 4.95 | O6: =SUM(H6:N6) -> 96.005 | P6: =G6-O6 -> 2.995 | Q6: =IF(G6=0,0,P6/G6) -> 0.030252525 | R6: =IF(Q6<0,"INVIÁVEL",IF(Q6<Premissas!$B$18,"ABAIXO DO MÍNIMO",IF(Q6<0.25,"SAUDÁVEL","FORTE"))) -> ABAIXO DO MÍNIMO
A7: C. Kit 5 · peça a R$ 8,00 · R$ 99 | B7: 8 | C7: 5 | D7: ='Ficha de Custo'!B20 -> 1.1 | E7: ='Ficha de Custo'!B38 -> 0.9 | F7: =MATCH(E7-0.0000001,'Frete 2026'!$A$6:$A$11,1) -> 3 | G7: 99 | H7: =B7*C7+D7 -> 41.1 | I7: =G7*Premissas!$B$26 -> 13.86 | J7: =IF(G7<79,INDEX('Frete 2026'!$B$6:$B$11,F7),0) -> 0 | K7: =IF(G7>=79,INDEX('Frete 2026'!$C$6:$G$11,F7,MATCH(G7,'Frete 2026'!$C$5:$G$5,1)),0) -> 13.55 | L7: =G7*Premissas!$B$27 -> 5.94 | M7: =G7*Premissas!$B$21 -> 4.455 | N7: =G7*Premissas!$B$22 -> 4.95 | O7: =SUM(H7:N7) -> 83.855 | P7: =G7-O7 -> 15.145 | Q7: =IF(G7=0,0,P7/G7) -> 0.1529798 | R7: =IF(Q7<0,"INVIÁVEL",IF(Q7<Premissas!$B$18,"ABAIXO DO MÍNIMO",IF(Q7<0.25,"SAUDÁVEL","FORTE"))) -> SAUDÁVEL
A8: D. Kit 3 · Essencial · R$ 169,90 | B8: ='Ficha de Custo'!C14 -> 20.52 | C8: 3 | D8: ='Ficha de Custo'!C19 -> 4.5 | E8: ='Ficha de Custo'!C37 -> 0.68 | F8: =MATCH(E8-0.0000001,'Frete 2026'!$A$6:$A$11,1) -> 3 | G8: 169.9 | H8: =B8*C8+D8 -> 66.06 | I8: =G8*Premissas!$B$26 -> 23.786 | J8: =IF(G8<79,INDEX('Frete 2026'!$B$6:$B$11,F8),0) -> 0 | K8: =IF(G8>=79,INDEX('Frete 2026'!$C$6:$G$11,F8,MATCH(G8,'Frete 2026'!$C$5:$G$5,1)),0) -> 20 | L8: =G8*Premissas!$B$27 -> 10.194 | M8: =G8*Premissas!$B$21 -> 7.6455 | N8: =G8*Premissas!$B$22 -> 8.495 | O8: =SUM(H8:N8) -> 136.1805 | P8: =G8-O8 -> 33.7195 | Q8: =IF(G8=0,0,P8/G8) -> 0.19846675 | R8: =IF(Q8<0,"INVIÁVEL",IF(Q8<Premissas!$B$18,"ABAIXO DO MÍNIMO",IF(Q8<0.25,"SAUDÁVEL","FORTE"))) -> SAUDÁVEL
A9: E. Avulsa · Fibra Longa · R$ 119,90 | B9: ='Ficha de Custo'!D14 -> 31.83 | C9: 1 | D9: ='Ficha de Custo'!D18 -> 2.9 | E9: ='Ficha de Custo'!D36 -> 0.22 | F9: =MATCH(E9-0.0000001,'Frete 2026'!$A$6:$A$11,1) -> 1 | G9: 119.9 | H9: =B9*C9+D9 -> 34.73 | I9: =G9*Premissas!$B$26 -> 16.786 | J9: =IF(G9<79,INDEX('Frete 2026'!$B$6:$B$11,F9),0) -> 0 | K9: =IF(G9>=79,INDEX('Frete 2026'!$C$6:$G$11,F9,MATCH(G9,'Frete 2026'!$C$5:$G$5,1)),0) -> 14.5 | L9: =G9*Premissas!$B$27 -> 7.194 | M9: =G9*Premissas!$B$21 -> 5.3955 | N9: =G9*Premissas!$B$22 -> 5.995 | O9: =SUM(H9:N9) -> 84.6005 | P9: =G9-O9 -> 35.2995 | Q9: =IF(G9=0,0,P9/G9) -> 0.29440784 | R9: =IF(Q9<0,"INVIÁVEL",IF(Q9<Premissas!$B$18,"ABAIXO DO MÍNIMO",IF(Q9<0.25,"SAUDÁVEL","FORTE"))) -> FORTE
A10: F. Avulsa · Essencial · R$ 54,90 | B10: ='Ficha de Custo'!C14 -> 20.52 | C10: 1 | D10: ='Ficha de Custo'!C18 -> 1.5 | E10: ='Ficha de Custo'!C36 -> 0.23 | F10: =MATCH(E10-0.0000001,'Frete 2026'!$A$6:$A$11,1) -> 1 | G10: 54.9 | H10: =B10*C10+D10 -> 22.02 | I10: =G10*Premissas!$B$26 -> 7.686 | J10: =IF(G10<79,INDEX('Frete 2026'!$B$6:$B$11,F10),0) -> 6.5 | K10: =IF(G10>=79,INDEX('Frete 2026'!$C$6:$G$11,F10,MATCH(G10,'Frete 2026'!$C$5:$G$5,1)),0) -> 0 | L10: =G10*Premissas!$B$27 -> 3.294 | M10: =G10*Premissas!$B$21 -> 2.4705 | N10: =G10*Premissas!$B$22 -> 2.745 | O10: =SUM(H10:N10) -> 44.7155 | P10: =G10-O10 -> 10.1845 | Q10: =IF(G10=0,0,P10/G10) -> 0.18551002 | R10: =IF(Q10<0,"INVIÁVEL",IF(Q10<Premissas!$B$18,"ABAIXO DO MÍNIMO",IF(Q10<0.25,"SAUDÁVEL","FORTE"))) -> SAUDÁVEL
A12: Kit 5 a R$ 99 (Popular): custo máximo por peça para empatar | G12: =(G6-SUM(I6:N6)-D6)/C6 -> 11.029 | H12: Acima destes custos, o kit de 5 a R$ 99 dá prejuízo (linha 12) ou fica abaixo de 15% (linha 13) no Mercado Livre.
A13: Kit 5 a R$ 99 (Popular): custo máximo por peça para a margem mínima | G13: =(G6*(1-Premissas!$B$18)-SUM(I6:N6)-D6)/C6 -> 8.059

Sheet Sensibilidade
A1: SENSIBILIDADE — MARGEM DE CONTRIBUIÇÃO NO MERCADO LIVRE
A2: Linhas: custo por peça. Colunas: preço do kit. Peças, embalagem e peso do pacote vêm de Premissas (kit em simulação). Frete pela tabela verde.
A3: Kit em simulação: | B3: =Premissas!$B$6 -> 3
A5: Custo/peça ↓ Preço → | B5: 129.9 | C5: 139.9 | D5: 149.9 | E5: 159.9 | F5: 169.9 | G5: 179.9 | H5: 199.9 | I5: 219.9
A6: 8 | B6: =IF(B$5=0,0,(B$5-($A6*Premissas!$B$6+Premissas!$B$10)-B$5*'Kits calculo'!$D$4-IF(B$5<79,INDEX('Frete 2026'!$B$6:$B$11,Premissas!$B$14),INDEX('Frete 2026'!$C$6:$G$11,Premissas!$B$14,MATCH(B$5,'Frete 2026'!$C$5:$G$5,1))))/B$5) -> 0.34818707 | C6: =IF(C$5=0,0,(C$5-($A6*Premissas!$B$6+Premissas!$B$10)-C$5*'Kits calculo'!$D$4-IF(C$5<79,INDEX('Frete 2026'!$B$6:$B$11,Premissas!$B$14),INDEX('Frete 2026'!$C$6:$G$11,Premissas!$B$14,MATCH(C$5,'Frete 2026'!$C$5:$G$5,1))))/C$5) -> 0.37369192 | D6: =IF(D$5=0,0,(D$5-($A6*Premissas!$B$6+Premissas!$B$10)-D$5*'Kits calculo'!$D$4-IF(D$5<79,INDEX('Frete 2026'!$B$6:$B$11,Premissas!$B$14),INDEX('Frete 2026'!$C$6:$G$11,Premissas!$B$14,MATCH(D$5,'Frete 2026'!$C$5:$G$5,1))))/D$5) -> 0.39579386 | E6: =IF(E$5=0,0,(E$5-($A6*Premissas!$B$6+Premissas!$B$10)-E$5*'Kits calculo'!$D$4-IF(E$5<79,INDEX('Frete 2026'!$B$6:$B$11,Premissas!$B$14),INDEX('Frete 2026'!$C$6:$G$11,Premissas!$B$14,MATCH(E$5,'Frete 2026'!$C$5:$G$5,1))))/E$5) -> 0.40168543 | F6: =IF(F$5=0,0,(F$5-($A6*Premissas!$B$6+Premissas!$B$10)-F$5*'Kits calculo'!$D$4-IF(F$5<79,INDEX('Frete 2026'!$B$6:$B$11,Premissas!$B$14),INDEX('Frete 2026'!$C$6:$G$11,Premissas!$B$14,MATCH(F$5,'Frete 2026'!$C$5:$G$5,1))))/F$5) -> 0.41953796 | G6: =IF(G$5=0,0,(G$5-($A6*Premissas!$B$6+Premissas!$B$10)-G$5*'Kits calculo'!$D$4-IF(G$5<79,INDEX('Frete 2026'!$B$6:$B$11,Premissas!$B$14),INDEX('Frete 2026'!$C$6:$G$11,Premissas!$B$14,MATCH(G$5,'Frete 2026'!$C$5:$G$5,1))))/G$5) -> 0.43540578 | H6: =IF(H$5=0,0,(H$5-($A6*Premissas!$B$6+Premissas!$B$10)-H$5*'Kits calculo'!$D$4-IF(H$5<79,INDEX('Frete 2026'!$B$6:$B$11,Premissas!$B$14),INDEX('Frete 2026'!$C$6:$G$11,Premissas!$B$14,MATCH(H$5,'Frete 2026'!$C$5:$G$5,1))))/H$5) -> 0.46237869 | I6: =IF(I$5=0,0,(I$5-($A6*Premissas!$B$6+Premissas!$B$10)-I$5*'Kits calculo'!$D$4-IF(I$5<79,INDEX('Frete 2026'!$B$6:$B$11,Premissas!$B$14),INDEX('Frete 2026'!$C$6:$G$11,Premissas!$B$14,MATCH(I$5,'Frete 2026'!$C$5:$G$5,1))))/I$5) -> 0.47466803
A7: 10.43 | B7: =IF(B$5=0,0,(B$5-($A7*Premissas!$B$6+Premissas!$B$10)-B$5*'Kits calculo'!$D$4-IF(B$5<79,INDEX('Frete 2026'!$B$6:$B$11,Premissas!$B$14),INDEX('Frete 2026'!$C$6:$G$11,Premissas!$B$14,MATCH(B$5,'Frete 2026'!$C$5:$G$5,1))))/B$5) -> 0.29206697 | C7: =IF(C$5=0,0,(C$5-($A7*Premissas!$B$6+Premissas!$B$10)-C$5*'Kits calculo'!$D$4-IF(C$5<79,INDEX('Frete 2026'!$B$6:$B$11,Premissas!$B$14),INDEX('Frete 2026'!$C$6:$G$11,Premissas!$B$14,MATCH(C$5,'Frete 2026'!$C$5:$G$5,1))))/C$5) -> 0.32158327 | D7: =IF(D$5=0,0,(D$5-($A7*Premissas!$B$6+Premissas!$B$10)-D$5*'Kits calculo'!$D$4-IF(D$5<79,INDEX('Frete 2026'!$B$6:$B$11,Premissas!$B$14),INDEX('Frete 2026'!$C$6:$G$11,Premissas!$B$14,MATCH(D$5,'Frete 2026'!$C$5:$G$5,1))))/D$5) -> 0.34716144 | E7: =IF(E$5=0,0,(E$5-($A7*Premissas!$B$6+Premissas!$B$10)-E$5*'Kits calculo'!$D$4-IF(E$5<79,INDEX('Frete 2026'!$B$6:$B$11,Premissas!$B$14),INDEX('Frete 2026'!$C$6:$G$11,Premissas!$B$14,MATCH(E$5,'Frete 2026'!$C$5:$G$5,1))))/E$5) -> 0.35609443 | F7: =IF(F$5=0,0,(F$5-($A7*Premissas!$B$6+Premissas!$B$10)-F$5*'Kits calculo'!$D$4-IF(F$5<79,INDEX('Frete 2026'!$B$6:$B$11,Premissas!$B$14),INDEX('Frete 2026'!$C$6:$G$11,Premissas!$B$14,MATCH(F$5,'Frete 2026'!$C$5:$G$5,1))))/F$5) -> 0.37663037 | G7: =IF(G$5=0,0,(G$5-($A7*Premissas!$B$6+Premissas!$B$10)-G$5*'Kits calculo'!$D$4-IF(G$5<79,INDEX('Frete 2026'!$B$6:$B$11,Premissas!$B$14),INDEX('Frete 2026'!$C$6:$G$11,Premissas!$B$14,MATCH(G$5,'Frete 2026'!$C$5:$G$5,1))))/G$5) -> 0.39488327 | H7: =IF(H$5=0,0,(H$5-($A7*Premissas!$B$6+Premissas!$B$10)-H$5*'Kits calculo'!$D$4-IF(H$5<79,INDEX('Frete 2026'!$B$6:$B$11,Premissas!$B$14),INDEX('Frete 2026'!$C$6:$G$11,Premissas!$B$14,MATCH(H$5,'Frete 2026'!$C$5:$G$5,1))))/H$5) -> 0.42591046 | I7: =IF(I$5=0,0,(I$5-($A7*Premissas!$B$6+Premissas!$B$10)-I$5*'Kits calculo'!$D$4-IF(I$5<79,INDEX('Frete 2026'!$B$6:$B$11,Premissas!$B$14),INDEX('Frete 2026'!$C$6:$G$11,Premissas!$B$14,MATCH(I$5,'Frete 2026'!$C$5:$G$5,1))))/I$5) -> 0.4415166
A8: 12 | B8: =IF(B$5=0,0,(B$5-($A8*Premissas!$B$6+Premissas!$B$10)-B$5*'Kits calculo'!$D$4-IF(B$5<79,INDEX('Frete 2026'!$B$6:$B$11,Premissas!$B$14),INDEX('Frete 2026'!$C$6:$G$11,Premissas!$B$14,MATCH(B$5,'Frete 2026'!$C$5:$G$5,1))))/B$5) -> 0.25580831 | C8: =IF(C$5=0,0,(C$5-($A8*Premissas!$B$6+Premissas!$B$10)-C$5*'Kits calculo'!$D$4-IF(C$5<79,INDEX('Frete 2026'!$B$6:$B$11,Premissas!$B$14),INDEX('Frete 2026'!$C$6:$G$11,Premissas!$B$14,MATCH(C$5,'Frete 2026'!$C$5:$G$5,1))))/C$5) -> 0.28791637 | D8: =IF(D$5=0,0,(D$5-($A8*Premissas!$B$6+Premissas!$B$10)-D$5*'Kits calculo'!$D$4-IF(D$5<79,INDEX('Frete 2026'!$B$6:$B$11,Premissas!$B$14),INDEX('Frete 2026'!$C$6:$G$11,Premissas!$B$14,MATCH(D$5,'Frete 2026'!$C$5:$G$5,1))))/D$5) -> 0.31574049 | E8: =IF(E$5=0,0,(E$5-($A8*Premissas!$B$6+Premissas!$B$10)-E$5*'Kits calculo'!$D$4-IF(E$5<79,INDEX('Frete 2026'!$B$6:$B$11,Premissas!$B$14),INDEX('Frete 2026'!$C$6:$G$11,Premissas!$B$14,MATCH(E$5,'Frete 2026'!$C$5:$G$5,1))))/E$5) -> 0.32663852 | F8: =IF(F$5=0,0,(F$5-($A8*Premissas!$B$6+Premissas!$B$10)-F$5*'Kits calculo'!$D$4-IF(F$5<79,INDEX('Frete 2026'!$B$6:$B$11,Premissas!$B$14),INDEX('Frete 2026'!$C$6:$G$11,Premissas!$B$14,MATCH(F$5,'Frete 2026'!$C$5:$G$5,1))))/F$5) -> 0.34890818 | G8: =IF(G$5=0,0,(G$5-($A8*Premissas!$B$6+Premissas!$B$10)-G$5*'Kits calculo'!$D$4-IF(G$5<79,INDEX('Frete 2026'!$B$6:$B$11,Premissas!$B$14),INDEX('Frete 2026'!$C$6:$G$11,Premissas!$B$14,MATCH(G$5,'Frete 2026'!$C$5:$G$5,1))))/G$5) -> 0.36870206 | H8: =IF(H$5=0,0,(H$5-($A8*Premissas!$B$6+Premissas!$B$10)-H$5*'Kits calculo'!$D$4-IF(H$5<79,INDEX('Frete 2026'!$B$6:$B$11,Premissas!$B$14),INDEX('Frete 2026'!$C$6:$G$11,Premissas!$B$14,MATCH(H$5,'Frete 2026'!$C$5:$G$5,1))))/H$5) -> 0.40234867 | I8: =IF(I$5=0,0,(I$5-($A8*Premissas!$B$6+Premissas!$B$10)-I$5*'Kits calculo'!$D$4-IF(I$5<79,INDEX('Frete 2026'!$B$6:$B$11,Premissas!$B$14),INDEX('Frete 2026'!$C$6:$G$11,Premissas!$B$14,MATCH(I$5,'Frete 2026'!$C$5:$G$5,1))))/I$5) -> 0.42009777
A9: 14 | B9: =IF(B$5=0,0,(B$5-($A9*Premissas!$B$6+Premissas!$B$10)-B$5*'Kits calculo'!$D$4-IF(B$5<79,INDEX('Frete 2026'!$B$6:$B$11,Premissas!$B$14),INDEX('Frete 2026'!$C$6:$G$11,Premissas!$B$14,MATCH(B$5,'Frete 2026'!$C$5:$G$5,1))))/B$5) -> 0.20961894 | C9: =IF(C$5=0,0,(C$5-($A9*Premissas!$B$6+Premissas!$B$10)-C$5*'Kits calculo'!$D$4-IF(C$5<79,INDEX('Frete 2026'!$B$6:$B$11,Premissas!$B$14),INDEX('Frete 2026'!$C$6:$G$11,Premissas!$B$14,MATCH(C$5,'Frete 2026'!$C$5:$G$5,1))))/C$5) -> 0.24502859 | D9: =IF(D$5=0,0,(D$5-($A9*Premissas!$B$6+Premissas!$B$10)-D$5*'Kits calculo'!$D$4-IF(D$5<79,INDEX('Frete 2026'!$B$6:$B$11,Premissas!$B$14),INDEX('Frete 2026'!$C$6:$G$11,Premissas!$B$14,MATCH(D$5,'Frete 2026'!$C$5:$G$5,1))))/D$5) -> 0.27571381 | E9: =IF(E$5=0,0,(E$5-($A9*Premissas!$B$6+Premissas!$B$10)-E$5*'Kits calculo'!$D$4-IF(E$5<79,INDEX('Frete 2026'!$B$6:$B$11,Premissas!$B$14),INDEX('Frete 2026'!$C$6:$G$11,Premissas!$B$14,MATCH(E$5,'Frete 2026'!$C$5:$G$5,1))))/E$5) -> 0.28911507 | F9: =IF(F$5=0,0,(F$5-($A9*Premissas!$B$6+Premissas!$B$10)-F$5*'Kits calculo'!$D$4-IF(F$5<79,INDEX('Frete 2026'!$B$6:$B$11,Premissas!$B$14),INDEX('Frete 2026'!$C$6:$G$11,Premissas!$B$14,MATCH(F$5,'Frete 2026'!$C$5:$G$5,1))))/F$5) -> 0.31359329 | G9: =IF(G$5=0,0,(G$5-($A9*Premissas!$B$6+Premissas!$B$10)-G$5*'Kits calculo'!$D$4-IF(G$5<79,INDEX('Frete 2026'!$B$6:$B$11,Premissas!$B$14),INDEX('Frete 2026'!$C$6:$G$11,Premissas!$B$14,MATCH(G$5,'Frete 2026'!$C$5:$G$5,1))))/G$5) -> 0.33535019 | H9: =IF(H$5=0,0,(H$5-($A9*Premissas!$B$6+Premissas!$B$10)-H$5*'Kits calculo'!$D$4-IF(H$5<79,INDEX('Frete 2026'!$B$6:$B$11,Premissas!$B$14),INDEX('Frete 2026'!$C$6:$G$11,Premissas!$B$14,MATCH(H$5,'Frete 2026'!$C$5:$G$5,1))))/H$5) -> 0.37233367 | I9: =IF(I$5=0,0,(I$5-($A9*Premissas!$B$6+Premissas!$B$10)-I$5*'Kits calculo'!$D$4-IF(I$5<79,INDEX('Frete 2026'!$B$6:$B$11,Premissas!$B$14),INDEX('Frete 2026'!$C$6:$G$11,Premissas!$B$14,MATCH(I$5,'Frete 2026'!$C$5:$G$5,1))))/I$5) -> 0.39281264
A10: 16 | B10: =IF(B$5=0,0,(B$5-($A10*Premissas!$B$6+Premissas!$B$10)-B$5*'Kits calculo'!$D$4-IF(B$5<79,INDEX('Frete 2026'!$B$6:$B$11,Premissas!$B$14),INDEX('Frete 2026'!$C$6:$G$11,Premissas!$B$14,MATCH(B$5,'Frete 2026'!$C$5:$G$5,1))))/B$5) -> 0.16342956 | C10: =IF(C$5=0,0,(C$5-($A10*Premissas!$B$6+Premissas!$B$10)-C$5*'Kits calculo'!$D$4-IF(C$5<79,INDEX('Frete 2026'!$B$6:$B$11,Premissas!$B$14),INDEX('Frete 2026'!$C$6:$G$11,Premissas!$B$14,MATCH(C$5,'Frete 2026'!$C$5:$G$5,1))))/C$5) -> 0.20214081 | D10: =IF(D$5=0,0,(D$5-($A10*Premissas!$B$6+Premissas!$B$10)-D$5*'Kits calculo'!$D$4-IF(D$5<79,INDEX('Frete 2026'!$B$6:$B$11,Premissas!$B$14),INDEX('Frete 2026'!$C$6:$G$11,Premissas!$B$14,MATCH(D$5,'Frete 2026'!$C$5:$G$5,1))))/D$5) -> 0.23568712 | E10: =IF(E$5=0,0,(E$5-($A10*Premissas!$B$6+Premissas!$B$10)-E$5*'Kits calculo'!$D$4-IF(E$5<79,INDEX('Frete 2026'!$B$6:$B$11,Premissas!$B$14),INDEX('Frete 2026'!$C$6:$G$11,Premissas!$B$14,MATCH(E$5,'Frete 2026'!$C$5:$G$5,1))))/E$5) -> 0.25159162 | F10: =IF(F$5=0,0,(F$5-($A10*Premissas!$B$6+Premissas!$B$10)-F$5*'Kits calculo'!$D$4-IF(F$5<79,INDEX('Frete 2026'!$B$6:$B$11,Premissas!$B$14),INDEX('Frete 2026'!$C$6:$G$11,Premissas!$B$14,MATCH(F$5,'Frete 2026'!$C$5:$G$5,1))))/F$5) -> 0.2782784 | G10: =IF(G$5=0,0,(G$5-($A10*Premissas!$B$6+Premissas!$B$10)-G$5*'Kits calculo'!$D$4-IF(G$5<79,INDEX('Frete 2026'!$B$6:$B$11,Premissas!$B$14),INDEX('Frete 2026'!$C$6:$G$11,Premissas!$B$14,MATCH(G$5,'Frete 2026'!$C$5:$G$5,1))))/G$5) -> 0.30199833 | H10: =IF(H$5=0,0,(H$5-($A10*Premissas!$B$6+Premissas!$B$10)-H$5*'Kits calculo'!$D$4-IF(H$5<79,INDEX('Frete 2026'!$B$6:$B$11,Premissas!$B$14),INDEX('Frete 2026'!$C$6:$G$11,Premissas!$B$14,MATCH(H$5,'Frete 2026'!$C$5:$G$5,1))))/H$5) -> 0.34231866 | I10: =IF(I$5=0,0,(I$5-($A10*Premissas!$B$6+Premissas!$B$10)-I$5*'Kits calculo'!$D$4-IF(I$5<79,INDEX('Frete 2026'!$B$6:$B$11,Premissas!$B$14),INDEX('Frete 2026'!$C$6:$G$11,Premissas!$B$14,MATCH(I$5,'Frete 2026'!$C$5:$G$5,1))))/I$5) -> 0.36552751
A11: 18 | B11: =IF(B$5=0,0,(B$5-($A11*Premissas!$B$6+Premissas!$B$10)-B$5*'Kits calculo'!$D$4-IF(B$5<79,INDEX('Frete 2026'!$B$6:$B$11,Premissas!$B$14),INDEX('Frete 2026'!$C$6:$G$11,Premissas!$B$14,MATCH(B$5,'Frete 2026'!$C$5:$G$5,1))))/B$5) -> 0.11724018 | C11: =IF(C$5=0,0,(C$5-($A11*Premissas!$B$6+Premissas!$B$10)-C$5*'Kits calculo'!$D$4-IF(C$5<79,INDEX('Frete 2026'!$B$6:$B$11,Premissas!$B$14),INDEX('Frete 2026'!$C$6:$G$11,Premissas!$B$14,MATCH(C$5,'Frete 2026'!$C$5:$G$5,1))))/C$5) -> 0.15925304 | D11: =IF(D$5=0,0,(D$5-($A11*Premissas!$B$6+Premissas!$B$10)-D$5*'Kits calculo'!$D$4-IF(D$5<79,INDEX('Frete 2026'!$B$6:$B$11,Premissas!$B$14),INDEX('Frete 2026'!$C$6:$G$11,Premissas!$B$14,MATCH(D$5,'Frete 2026'!$C$5:$G$5,1))))/D$5) -> 0.19566044 | E11: =IF(E$5=0,0,(E$5-($A11*Premissas!$B$6+Premissas!$B$10)-E$5*'Kits calculo'!$D$4-IF(E$5<79,INDEX('Frete 2026'!$B$6:$B$11,Premissas!$B$14),INDEX('Frete 2026'!$C$6:$G$11,Premissas!$B$14,MATCH(E$5,'Frete 2026'!$C$5:$G$5,1))))/E$5) -> 0.21406817 | F11: =IF(F$5=0,0,(F$5-($A11*Premissas!$B$6+Premissas!$B$10)-F$5*'Kits calculo'!$D$4-IF(F$5<79,INDEX('Frete 2026'!$B$6:$B$11,Premissas!$B$14),INDEX('Frete 2026'!$C$6:$G$11,Premissas!$B$14,MATCH(F$5,'Frete 2026'!$C$5:$G$5,1))))/F$5) -> 0.24296351 | G11: =IF(G$5=0,0,(G$5-($A11*Premissas!$B$6+Premissas!$B$10)-G$5*'Kits calculo'!$D$4-IF(G$5<79,INDEX('Frete 2026'!$B$6:$B$11,Premissas!$B$14),INDEX('Frete 2026'!$C$6:$G$11,Premissas!$B$14,MATCH(G$5,'Frete 2026'!$C$5:$G$5,1))))/G$5) -> 0.26864647 | H11: =IF(H$5=0,0,(H$5-($A11*Premissas!$B$6+Premissas!$B$10)-H$5*'Kits calculo'!$D$4-IF(H$5<79,INDEX('Frete 2026'!$B$6:$B$11,Premissas!$B$14),INDEX('Frete 2026'!$C$6:$G$11,Premissas!$B$14,MATCH(H$5,'Frete 2026'!$C$5:$G$5,1))))/H$5) -> 0.31230365 | I11: =IF(I$5=0,0,(I$5-($A11*Premissas!$B$6+Premissas!$B$10)-I$5*'Kits calculo'!$D$4-IF(I$5<79,INDEX('Frete 2026'!$B$6:$B$11,Premissas!$B$14),INDEX('Frete 2026'!$C$6:$G$11,Premissas!$B$14,MATCH(I$5,'Frete 2026'!$C$5:$G$5,1))))/I$5) -> 0.33824238
A12: 20.52 | B12: =IF(B$5=0,0,(B$5-($A12*Premissas!$B$6+Premissas!$B$10)-B$5*'Kits calculo'!$D$4-IF(B$5<79,INDEX('Frete 2026'!$B$6:$B$11,Premissas!$B$14),INDEX('Frete 2026'!$C$6:$G$11,Premissas!$B$14,MATCH(B$5,'Frete 2026'!$C$5:$G$5,1))))/B$5) -> 0.05904157 | C12: =IF(C$5=0,0,(C$5-($A12*Premissas!$B$6+Premissas!$B$10)-C$5*'Kits calculo'!$D$4-IF(C$5<79,INDEX('Frete 2026'!$B$6:$B$11,Premissas!$B$14),INDEX('Frete 2026'!$C$6:$G$11,Premissas!$B$14,MATCH(C$5,'Frete 2026'!$C$5:$G$5,1))))/C$5) -> 0.10521444 | D12: =IF(D$5=0,0,(D$5-($A12*Premissas!$B$6+Premissas!$B$10)-D$5*'Kits calculo'!$D$4-IF(D$5<79,INDEX('Frete 2026'!$B$6:$B$11,Premissas!$B$14),INDEX('Frete 2026'!$C$6:$G$11,Premissas!$B$14,MATCH(D$5,'Frete 2026'!$C$5:$G$5,1))))/D$5) -> 0.14522682 | E12: =IF(E$5=0,0,(E$5-($A12*Premissas!$B$6+Premissas!$B$10)-E$5*'Kits calculo'!$D$4-IF(E$5<79,INDEX('Frete 2026'!$B$6:$B$11,Premissas!$B$14),INDEX('Frete 2026'!$C$6:$G$11,Premissas!$B$14,MATCH(E$5,'Frete 2026'!$C$5:$G$5,1))))/E$5) -> 0.16678862 | F12: =IF(F$5=0,0,(F$5-($A12*Premissas!$B$6+Premissas!$B$10)-F$5*'Kits calculo'!$D$4-IF(F$5<79,INDEX('Frete 2026'!$B$6:$B$11,Premissas!$B$14),INDEX('Frete 2026'!$C$6:$G$11,Premissas!$B$14,MATCH(F$5,'Frete 2026'!$C$5:$G$5,1))))/F$5) -> 0.19846675 | G12: =IF(G$5=0,0,(G$5-($A12*Premissas!$B$6+Premissas!$B$10)-G$5*'Kits calculo'!$D$4-IF(G$5<79,INDEX('Frete 2026'!$B$6:$B$11,Premissas!$B$14),INDEX('Frete 2026'!$C$6:$G$11,Premissas!$B$14,MATCH(G$5,'Frete 2026'!$C$5:$G$5,1))))/G$5) -> 0.22662312 | H12: =IF(H$5=0,0,(H$5-($A12*Premissas!$B$6+Premissas!$B$10)-H$5*'Kits calculo'!$D$4-IF(H$5<79,INDEX('Frete 2026'!$B$6:$B$11,Premissas!$B$14),INDEX('Frete 2026'!$C$6:$G$11,Premissas!$B$14,MATCH(H$5,'Frete 2026'!$C$5:$G$5,1))))/H$5) -> 0.27448474 | I12: =IF(I$5=0,0,(I$5-($A12*Premissas!$B$6+Premissas!$B$10)-I$5*'Kits calculo'!$D$4-IF(I$5<79,INDEX('Frete 2026'!$B$6:$B$11,Premissas!$B$14),INDEX('Frete 2026'!$C$6:$G$11,Premissas!$B$14,MATCH(I$5,'Frete 2026'!$C$5:$G$5,1))))/I$5) -> 0.30386312
A13: 22 | B13: =IF(B$5=0,0,(B$5-($A13*Premissas!$B$6+Premissas!$B$10)-B$5*'Kits calculo'!$D$4-IF(B$5<79,INDEX('Frete 2026'!$B$6:$B$11,Premissas!$B$14),INDEX('Frete 2026'!$C$6:$G$11,Premissas!$B$14,MATCH(B$5,'Frete 2026'!$C$5:$G$5,1))))/B$5) -> 0.024861432 | C13: =IF(C$5=0,0,(C$5-($A13*Premissas!$B$6+Premissas!$B$10)-C$5*'Kits calculo'!$D$4-IF(C$5<79,INDEX('Frete 2026'!$B$6:$B$11,Premissas!$B$14),INDEX('Frete 2026'!$C$6:$G$11,Premissas!$B$14,MATCH(C$5,'Frete 2026'!$C$5:$G$5,1))))/C$5) -> 0.073477484 | D13: =IF(D$5=0,0,(D$5-($A13*Premissas!$B$6+Premissas!$B$10)-D$5*'Kits calculo'!$D$4-IF(D$5<79,INDEX('Frete 2026'!$B$6:$B$11,Premissas!$B$14),INDEX('Frete 2026'!$C$6:$G$11,Premissas!$B$14,MATCH(D$5,'Frete 2026'!$C$5:$G$5,1))))/D$5) -> 0.11560707 | E13: =IF(E$5=0,0,(E$5-($A13*Premissas!$B$6+Premissas!$B$10)-E$5*'Kits calculo'!$D$4-IF(E$5<79,INDEX('Frete 2026'!$B$6:$B$11,Premissas!$B$14),INDEX('Frete 2026'!$C$6:$G$11,Premissas!$B$14,MATCH(E$5,'Frete 2026'!$C$5:$G$5,1))))/E$5) -> 0.13902126 | F13: =IF(F$5=0,0,(F$5-($A13*Premissas!$B$6+Premissas!$B$10)-F$5*'Kits calculo'!$D$4-IF(F$5<79,INDEX('Frete 2026'!$B$6:$B$11,Premissas!$B$14),INDEX('Frete 2026'!$C$6:$G$11,Premissas!$B$14,MATCH(F$5,'Frete 2026'!$C$5:$G$5,1))))/F$5) -> 0.17233373 | G13: =IF(G$5=0,0,(G$5-($A13*Premissas!$B$6+Premissas!$B$10)-G$5*'Kits calculo'!$D$4-IF(G$5<79,INDEX('Frete 2026'!$B$6:$B$11,Premissas!$B$14),INDEX('Frete 2026'!$C$6:$G$11,Premissas!$B$14,MATCH(G$5,'Frete 2026'!$C$5:$G$5,1))))/G$5) -> 0.20194275 | H13: =IF(H$5=0,0,(H$5-($A13*Premissas!$B$6+Premissas!$B$10)-H$5*'Kits calculo'!$D$4-IF(H$5<79,INDEX('Frete 2026'!$B$6:$B$11,Premissas!$B$14),INDEX('Frete 2026'!$C$6:$G$11,Premissas!$B$14,MATCH(H$5,'Frete 2026'!$C$5:$G$5,1))))/H$5) -> 0.25227364 | I13: =IF(I$5=0,0,(I$5-($A13*Premissas!$B$6+Premissas!$B$10)-I$5*'Kits calculo'!$D$4-IF(I$5<79,INDEX('Frete 2026'!$B$6:$B$11,Premissas!$B$14),INDEX('Frete 2026'!$C$6:$G$11,Premissas!$B$14,MATCH(I$5,'Frete 2026'!$C$5:$G$5,1))))/I$5) -> 0.28367212
A14: 25 | B14: =IF(B$5=0,0,(B$5-($A14*Premissas!$B$6+Premissas!$B$10)-B$5*'Kits calculo'!$D$4-IF(B$5<79,INDEX('Frete 2026'!$B$6:$B$11,Premissas!$B$14),INDEX('Frete 2026'!$C$6:$G$11,Premissas!$B$14,MATCH(B$5,'Frete 2026'!$C$5:$G$5,1))))/B$5) -> -0.044422633 | C14: =IF(C$5=0,0,(C$5-($A14*Premissas!$B$6+Premissas!$B$10)-C$5*'Kits calculo'!$D$4-IF(C$5<79,INDEX('Frete 2026'!$B$6:$B$11,Premissas!$B$14),INDEX('Frete 2026'!$C$6:$G$11,Premissas!$B$14,MATCH(C$5,'Frete 2026'!$C$5:$G$5,1))))/C$5) -> 0.0091458184 | D14: =IF(D$5=0,0,(D$5-($A14*Premissas!$B$6+Premissas!$B$10)-D$5*'Kits calculo'!$D$4-IF(D$5<79,INDEX('Frete 2026'!$B$6:$B$11,Premissas!$B$14),INDEX('Frete 2026'!$C$6:$G$11,Premissas!$B$14,MATCH(D$5,'Frete 2026'!$C$5:$G$5,1))))/D$5) -> 0.055567045 | E14: =IF(E$5=0,0,(E$5-($A14*Premissas!$B$6+Premissas!$B$10)-E$5*'Kits calculo'!$D$4-IF(E$5<79,INDEX('Frete 2026'!$B$6:$B$11,Premissas!$B$14),INDEX('Frete 2026'!$C$6:$G$11,Premissas!$B$14,MATCH(E$5,'Frete 2026'!$C$5:$G$5,1))))/E$5) -> 0.082736085 | F14: =IF(F$5=0,0,(F$5-($A14*Premissas!$B$6+Premissas!$B$10)-F$5*'Kits calculo'!$D$4-IF(F$5<79,INDEX('Frete 2026'!$B$6:$B$11,Premissas!$B$14),INDEX('Frete 2026'!$C$6:$G$11,Premissas!$B$14,MATCH(F$5,'Frete 2026'!$C$5:$G$5,1))))/F$5) -> 0.11936139 | G14: =IF(G$5=0,0,(G$5-($A14*Premissas!$B$6+Premissas!$B$10)-G$5*'Kits calculo'!$D$4-IF(G$5<79,INDEX('Frete 2026'!$B$6:$B$11,Premissas!$B$14),INDEX('Frete 2026'!$C$6:$G$11,Premissas!$B$14,MATCH(G$5,'Frete 2026'!$C$5:$G$5,1))))/G$5) -> 0.15191495 | H14: =IF(H$5=0,0,(H$5-($A14*Premissas!$B$6+Premissas!$B$10)-H$5*'Kits calculo'!$D$4-IF(H$5<79,INDEX('Frete 2026'!$B$6:$B$11,Premissas!$B$14),INDEX('Frete 2026'!$C$6:$G$11,Premissas!$B$14,MATCH(H$5,'Frete 2026'!$C$5:$G$5,1))))/H$5) -> 0.20725113 | I14: =IF(I$5=0,0,(I$5-($A14*Premissas!$B$6+Premissas!$B$10)-I$5*'Kits calculo'!$D$4-IF(I$5<79,INDEX('Frete 2026'!$B$6:$B$11,Premissas!$B$14),INDEX('Frete 2026'!$C$6:$G$11,Premissas!$B$14,MATCH(I$5,'Frete 2026'!$C$5:$G$5,1))))/I$5) -> 0.24274443
A15: 28 | B15: =IF(B$5=0,0,(B$5-($A15*Premissas!$B$6+Premissas!$B$10)-B$5*'Kits calculo'!$D$4-IF(B$5<79,INDEX('Frete 2026'!$B$6:$B$11,Premissas!$B$14),INDEX('Frete 2026'!$C$6:$G$11,Premissas!$B$14,MATCH(B$5,'Frete 2026'!$C$5:$G$5,1))))/B$5) -> -0.1137067 | C15: =IF(C$5=0,0,(C$5-($A15*Premissas!$B$6+Premissas!$B$10)-C$5*'Kits calculo'!$D$4-IF(C$5<79,INDEX('Frete 2026'!$B$6:$B$11,Premissas!$B$14),INDEX('Frete 2026'!$C$6:$G$11,Premissas!$B$14,MATCH(C$5,'Frete 2026'!$C$5:$G$5,1))))/C$5) -> -0.055185847 | D15: =IF(D$5=0,0,(D$5-($A15*Premissas!$B$6+Premissas!$B$10)-D$5*'Kits calculo'!$D$4-IF(D$5<79,INDEX('Frete 2026'!$B$6:$B$11,Premissas!$B$14),INDEX('Frete 2026'!$C$6:$G$11,Premissas!$B$14,MATCH(D$5,'Frete 2026'!$C$5:$G$5,1))))/D$5) -> -0.004472982 | E15: =IF(E$5=0,0,(E$5-($A15*Premissas!$B$6+Premissas!$B$10)-E$5*'Kits calculo'!$D$4-IF(E$5<79,INDEX('Frete 2026'!$B$6:$B$11,Premissas!$B$14),INDEX('Frete 2026'!$C$6:$G$11,Premissas!$B$14,MATCH(E$5,'Frete 2026'!$C$5:$G$5,1))))/E$5) -> 0.026450907 | F15: =IF(F$5=0,0,(F$5-($A15*Premissas!$B$6+Premissas!$B$10)-F$5*'Kits calculo'!$D$4-IF(F$5<79,INDEX('Frete 2026'!$B$6:$B$11,Premissas!$B$14),INDEX('Frete 2026'!$C$6:$G$11,Premissas!$B$14,MATCH(F$5,'Frete 2026'!$C$5:$G$5,1))))/F$5) -> 0.066389052 | G15: =IF(G$5=0,0,(G$5-($A15*Premissas!$B$6+Premissas!$B$10)-G$5*'Kits calculo'!$D$4-IF(G$5<79,INDEX('Frete 2026'!$B$6:$B$11,Premissas!$B$14),INDEX('Frete 2026'!$C$6:$G$11,Premissas!$B$14,MATCH(G$5,'Frete 2026'!$C$5:$G$5,1))))/G$5) -> 0.10188716 | H15: =IF(H$5=0,0,(H$5-($A15*Premissas!$B$6+Premissas!$B$10)-H$5*'Kits calculo'!$D$4-IF(H$5<79,INDEX('Frete 2026'!$B$6:$B$11,Premissas!$B$14),INDEX('Frete 2026'!$C$6:$G$11,Premissas!$B$14,MATCH(H$5,'Frete 2026'!$C$5:$G$5,1))))/H$5) -> 0.16222861 | I15: =IF(I$5=0,0,(I$5-($A15*Premissas!$B$6+Premissas!$B$10)-I$5*'Kits calculo'!$D$4-IF(I$5<79,INDEX('Frete 2026'!$B$6:$B$11,Premissas!$B$14),INDEX('Frete 2026'!$C$6:$G$11,Premissas!$B$14,MATCH(I$5,'Frete 2026'!$C$5:$G$5,1))))/I$5) -> 0.20181673
A16: 31.83 | B16: =IF(B$5=0,0,(B$5-($A16*Premissas!$B$6+Premissas!$B$10)-B$5*'Kits calculo'!$D$4-IF(B$5<79,INDEX('Frete 2026'!$B$6:$B$11,Premissas!$B$14),INDEX('Frete 2026'!$C$6:$G$11,Premissas!$B$14,MATCH(B$5,'Frete 2026'!$C$5:$G$5,1))))/B$5) -> -0.20215935 | C16: =IF(C$5=0,0,(C$5-($A16*Premissas!$B$6+Premissas!$B$10)-C$5*'Kits calculo'!$D$4-IF(C$5<79,INDEX('Frete 2026'!$B$6:$B$11,Premissas!$B$14),INDEX('Frete 2026'!$C$6:$G$11,Premissas!$B$14,MATCH(C$5,'Frete 2026'!$C$5:$G$5,1))))/C$5) -> -0.13731594 | D16: =IF(D$5=0,0,(D$5-($A16*Premissas!$B$6+Premissas!$B$10)-D$5*'Kits calculo'!$D$4-IF(D$5<79,INDEX('Frete 2026'!$B$6:$B$11,Premissas!$B$14),INDEX('Frete 2026'!$C$6:$G$11,Premissas!$B$14,MATCH(D$5,'Frete 2026'!$C$5:$G$5,1))))/D$5) -> -0.081124083 | E16: =IF(E$5=0,0,(E$5-($A16*Premissas!$B$6+Premissas!$B$10)-E$5*'Kits calculo'!$D$4-IF(E$5<79,INDEX('Frete 2026'!$B$6:$B$11,Premissas!$B$14),INDEX('Frete 2026'!$C$6:$G$11,Premissas!$B$14,MATCH(E$5,'Frete 2026'!$C$5:$G$5,1))))/E$5) -> -0.045406504 | F16: =IF(F$5=0,0,(F$5-($A16*Premissas!$B$6+Premissas!$B$10)-F$5*'Kits calculo'!$D$4-IF(F$5<79,INDEX('Frete 2026'!$B$6:$B$11,Premissas!$B$14),INDEX('Frete 2026'!$C$6:$G$11,Premissas!$B$14,MATCH(F$5,'Frete 2026'!$C$5:$G$5,1))))/F$5) -> -0.0012389641 | G16: =IF(G$5=0,0,(G$5-($A16*Premissas!$B$6+Premissas!$B$10)-G$5*'Kits calculo'!$D$4-IF(G$5<79,INDEX('Frete 2026'!$B$6:$B$11,Premissas!$B$14),INDEX('Frete 2026'!$C$6:$G$11,Premissas!$B$14,MATCH(G$5,'Frete 2026'!$C$5:$G$5,1))))/G$5) -> 0.038018344 | H16: =IF(H$5=0,0,(H$5-($A16*Premissas!$B$6+Premissas!$B$10)-H$5*'Kits calculo'!$D$4-IF(H$5<79,INDEX('Frete 2026'!$B$6:$B$11,Premissas!$B$14),INDEX('Frete 2026'!$C$6:$G$11,Premissas!$B$14,MATCH(H$5,'Frete 2026'!$C$5:$G$5,1))))/H$5) -> 0.10474987 | I16: =IF(I$5=0,0,(I$5-($A16*Premissas!$B$6+Premissas!$B$10)-I$5*'Kits calculo'!$D$4-IF(I$5<79,INDEX('Frete 2026'!$B$6:$B$11,Premissas!$B$14),INDEX('Frete 2026'!$C$6:$G$11,Premissas!$B$14,MATCH(I$5,'Frete 2026'!$C$5:$G$5,1))))/I$5) -> 0.14956571
A18: Leitura: verde = margem mínima ou mais; amarelo = entre 0% e a margem mínima; vermelho = prejuízo. Custos em azul na coluna A: 10,43 = Popular, 20,52 = Essencial, 31,83 = Fibra Longa.

Sheet Projecao
A1: PROJEÇÃO DE 12 MESES — KIT 3 ESSENCIAL
A2: Volumes em azul são premissas de rampa de vendedor novo em moda. Preço e margens vêm de Premissas e Calculadora (kit em simulação).
A3: Fator de cenário: | B3: 1 | C3: Use 0,60 para o cenário conservador, 1,00 para o base e 1,50 para o agressivo.
A5: Mês | B5: Kits ML | C5: Kits Shopee | D5: Kits TikTok | E5: Total kits | F5: Faturamento | G5: MC Mercado Livre | H5: MC Shopee | I5: MC TikTok | J5: MC total | K5: Custo fixo | L5: Resultado | M5: Acumulado
A6: 1 | B6: 40 | C6: 15 | D6: 10 | E6: =(B6+C6+D6)*$B$3 -> 65 | F6: =E6*Premissas!$B$15 -> 11043.5 | G6: =B6*$B$3*Calculadora!$B$15 -> 1348.78 | H6: =C6*$B$3*Calculadora!$C$15 -> 454.8225 | I6: =D6*$B$3*Calculadora!$D$15 -> 273.315 | J6: =SUM(G6:I6) -> 2076.9175 | K6: =Premissas!$B$23 -> 13000 | L6: =J6-K6 -> -10923.083 | M6: =L6 -> -10923.083
A7: 2 | B7: 70 | C7: 30 | D7: 25 | E7: =(B7+C7+D7)*$B$3 -> 125 | F7: =E7*Premissas!$B$15 -> 21237.5 | G7: =B7*$B$3*Calculadora!$B$15 -> 2360.365 | H7: =C7*$B$3*Calculadora!$C$15 -> 909.645 | I7: =D7*$B$3*Calculadora!$D$15 -> 683.2875 | J7: =SUM(G7:I7) -> 3953.2975 | K7: =Premissas!$B$23 -> 13000 | L7: =J7-K7 -> -9046.7025 | M7: =M6+L7 -> -19969.785
A8: 3 | B8: 110 | C8: 55 | D8: 50 | E8: =(B8+C8+D8)*$B$3 -> 215 | F8: =E8*Premissas!$B$15 -> 36528.5 | G8: =B8*$B$3*Calculadora!$B$15 -> 3709.145 | H8: =C8*$B$3*Calculadora!$C$15 -> 1667.6825 | I8: =D8*$B$3*Calculadora!$D$15 -> 1366.575 | J8: =SUM(G8:I8) -> 6743.4025 | K8: =Premissas!$B$23 -> 13000 | L8: =J8-K8 -> -6256.5975 | M8: =M7+L8 -> -26226.382
A9: 4 | B9: 170 | C9: 90 | D9: 85 | E9: =(B9+C9+D9)*$B$3 -> 345 | F9: =E9*Premissas!$B$15 -> 58615.5 | G9: =B9*$B$3*Calculadora!$B$15 -> 5732.315 | H9: =C9*$B$3*Calculadora!$C$15 -> 2728.935 | I9: =D9*$B$3*Calculadora!$D$15 -> 2323.1775 | J9: =SUM(G9:I9) -> 10784.427 | K9: =Premissas!$B$23 -> 13000 | L9: =J9-K9 -> -2215.5725 | M9: =M8+L9 -> -28441.955
A10: 5 | B10: 240 | C10: 130 | D10: 130 | E10: =(B10+C10+D10)*$B$3 -> 500 | F10: =E10*Premissas!$B$15 -> 84950 | G10: =B10*$B$3*Calculadora!$B$15 -> 8092.68 | H10: =C10*$B$3*Calculadora!$C$15 -> 3941.795 | I10: =D10*$B$3*Calculadora!$D$15 -> 3553.095 | J10: =SUM(G10:I10) -> 15587.57 | K10: =Premissas!$B$23 -> 13000 | L10: =J10-K10 -> 2587.57 | M10: =M9+L10 -> -25854.385
A11: 6 | B11: 310 | C11: 175 | D11: 180 | E11: =(B11+C11+D11)*$B$3 -> 665 | F11: =E11*Premissas!$B$15 -> 112983.5 | G11: =B11*$B$3*Calculadora!$B$15 -> 10453.045 | H11: =C11*$B$3*Calculadora!$C$15 -> 5306.2625 | I11: =D11*$B$3*Calculadora!$D$15 -> 4919.67 | J11: =SUM(G11:I11) -> 20678.978 | K11: =Premissas!$B$23 -> 13000 | L11: =J11-K11 -> 7678.9775 | M11: =M10+L11 -> -18175.408
A12: 7 | B12: 380 | C12: 220 | D12: 230 | E12: =(B12+C12+D12)*$B$3 -> 830 | F12: =E12*Premissas!$B$15 -> 141017 | G12: =B12*$B$3*Calculadora!$B$15 -> 12813.41 | H12: =C12*$B$3*Calculadora!$C$15 -> 6670.73 | I12: =D12*$B$3*Calculadora!$D$15 -> 6286.245 | J12: =SUM(G12:I12) -> 25770.385 | K12: =Premissas!$B$23 -> 13000 | L12: =J12-K12 -> 12770.385 | M12: =M11+L12 -> -5405.0225
A13: 8 | B13: 450 | C13: 265 | D13: 290 | E13: =(B13+C13+D13)*$B$3 -> 1005 | F13: =E13*Premissas!$B$15 -> 170749.5 | G13: =B13*$B$3*Calculadora!$B$15 -> 15173.775 | H13: =C13*$B$3*Calculadora!$C$15 -> 8035.1975 | I13: =D13*$B$3*Calculadora!$D$15 -> 7926.135 | J13: =SUM(G13:I13) -> 31135.107 | K13: =Premissas!$B$23 -> 13000 | L13: =J13-K13 -> 18135.107 | M13: =M12+L13 -> 12730.085
A14: 9 | B14: 520 | C14: 310 | D14: 350 | E14: =(B14+C14+D14)*$B$3 -> 1180 | F14: =E14*Premissas!$B$15 -> 200482 | G14: =B14*$B$3*Calculadora!$B$15 -> 17534.14 | H14: =C14*$B$3*Calculadora!$C$15 -> 9399.665 | I14: =D14*$B$3*Calculadora!$D$15 -> 9566.025 | J14: =SUM(G14:I14) -> 36499.83 | K14: =Premissas!$B$23 -> 13000 | L14: =J14-K14 -> 23499.83 | M14: =M13+L14 -> 36229.915
A15: 10 | B15: 600 | C15: 355 | D15: 410 | E15: =(B15+C15+D15)*$B$3 -> 1365 | F15: =E15*Premissas!$B$15 -> 231913.5 | G15: =B15*$B$3*Calculadora!$B$15 -> 20231.7 | H15: =C15*$B$3*Calculadora!$C$15 -> 10764.132 | I15: =D15*$B$3*Calculadora!$D$15 -> 11205.915 | J15: =SUM(G15:I15) -> 42201.747 | K15: =Premissas!$B$23 -> 13000 | L15: =J15-K15 -> 29201.748 | M15: =M14+L15 -> 65431.662
A16: 11 | B16: 700 | C16: 400 | D16: 470 | E16: =(B16+C16+D16)*$B$3 -> 1570 | F16: =E16*Premissas!$B$15 -> 266743 | G16: =B16*$B$3*Calculadora!$B$15 -> 23603.65 | H16: =C16*$B$3*Calculadora!$C$15 -> 12128.6 | I16: =D16*$B$3*Calculadora!$D$15 -> 12845.805 | J16: =SUM(G16:I16) -> 48578.055 | K16: =Premissas!$B$23 -> 13000 | L16: =J16-K16 -> 35578.055 | M16: =M15+L16 -> 101009.72
A17: 12 | B17: 820 | C17: 450 | D17: 540 | E17: =(B17+C17+D17)*$B$3 -> 1810 | F17: =E17*Premissas!$B$15 -> 307519 | G17: =B17*$B$3*Calculadora!$B$15 -> 27649.99 | H17: =C17*$B$3*Calculadora!$C$15 -> 13644.675 | I17: =D17*$B$3*Calculadora!$D$15 -> 14759.01 | J17: =SUM(G17:I17) -> 56053.675 | K17: =Premissas!$B$23 -> 13000 | L17: =J17-K17 -> 43053.675 | M17: =M16+L17 -> 144063.39
A18: ANO 1 | B18: =SUM(B6:B17) -> 4410 | C18: =SUM(C6:C17) -> 2495 | D18: =SUM(D6:D17) -> 2770 | E18: =SUM(E6:E17) -> 9675 | F18: =SUM(F6:F17) -> 1643782.5 | G18: =SUM(G6:G17) -> 148702.99 | H18: =SUM(H6:H17) -> 75652.143 | I18: =SUM(I6:I17) -> 75708.255 | ... L18: =SUM(L6:L17) -> 144063.39 | M18: =M17 -> 144063.39
A19: MC % | J19: =IF(F18=0,0,J18/F18) -> 0.18254446
A21: Investimento inicial estimado
A22: Estoque inicial · 1.200 kits | E22: =Cores!$B$4*Premissas!$B$16 -> 79272 | F22: Kits do lote (aba Cores) × CMV do kit em simulação.
A23: Fotografia e conteúdo · 5 kits e 4 cores de avulsa | E23: 18000 | F23: Modelo real, 7 imagens por SKU, detalhe da gola e da etiqueta, tabela de medidas em imagem.
A24: ERP e hub de integração · setup + 12 meses | E24: 9600 | F24: Gestão de estoque unificada entre as três plataformas.
A25: Ferramentas de inteligência · 12 meses | E25: 7200 | F25: Nubimetrics para o Mercado Livre e Kalodata para o TikTok Shop.
A26: Caixa de mídia · 3 meses | E26: 15000 | F26: Product Ads e Shopee Ads no período de maturação da reputação.
A27: Reserva operacional | E27: 25000 | F27: O repasse do marketplace leva de 14 a 30 dias; o caixa precisa cobrir 60 dias de ciclo.
A28: TOTAL DO INVESTIMENTO | E28: =SUM(E22:E27) -> 154072
A30: Mês em que o caixa acumulado cobre o investimento | E30: =IF(COUNTIF(M6:M17,">="&E28)=0,"após o mês 12",13-COUNTIF(M6:M17,">="&E28)) -> após o mês 12 | F30: Compara o acumulado de cada mês com o investimento. No cenário base, o mês 13 cobre o investimento se o resultado do mês 12 se repetir.
A31: Mês do equilíbrio operacional | E31: =IF(COUNTIF(L6:L17,">=0")=0,"após o mês 12",13-COUNTIF(L6:L17,">=0")) -> 5
A32: Peças por semana no mês 12 | E32: =E17*Premissas!$B$6/(52/12) -> 1253.0769 | F32: Capacidade fabril que o cenário exige no fim do ano 1, com grade completa.

Sheet Midia
A1: CALCULADORA DE MÍDIA — LOJA PRÓPRIA
A2: O Meta cobra por impressão; o Google, por clique. Os dois alimentam o mesmo produto.
A4: ENTRADAS
A5: Ticket médio | B5: =Premissas!$B$15 -> 169.9 | C5: Vem de Premissas!B15.
A6: Margem antes de mídia (%) | B6: =Calculadora!$E$20 -> 0.34291636 | C6: Vem da Calculadora: loja própria, antes do custo de aquisição.
A7: Verba mensal total | B7: 10000
A8: Split da verba para Meta | B8: 0.7 | C8: O restante vai para o Google.
A9: CPM — Meta | B9: 22 | C9: Feed no Brasil em 2026: R$ 15 a R$ 35. Stories e Reels: R$ 8 a R$ 20.
A10: CTR — Meta | B10: 0.016 | C10: Cliques ÷ impressões.
A11: Conversão — Meta | B11: 0.015 | C11: Pedidos ÷ cliques.
A12: CPC — Google | B12: 2.5 | C12: Moda no Brasil: R$ 1,50 a R$ 4,00.
A13: Conversão — Google | B13: 0.022 | C13: A busca converte melhor porque a intenção já existe.
A14: Taxa de recompra em 12 meses | B14: 0.35 | C14: Sem retenção: 15% a 25%. Com fidelidade e e-mail: 35% a 50%.
A15: Pedidos extras por recomprador | B15: 1.4
A17: RESULTADO
A18: Margem de contribuição por pedido | B18: =B5*B6 -> 58.26149 | C18: Antes do custo de mídia.
A19: ROAS de equilíbrio | B19: =IF(B6<=0,"—",1/B6) -> 2.916163 | C19: Abaixo disso a mídia não se paga. Mediana de mercado em Meta Ads: 1,93×.
A20: Verba — Meta | B20: =B7*B8 -> 7000
A21: Verba — Google | B21: =B7-B20 -> 3000
A22: Impressões — Meta | B22: =IF(B9=0,0,B20/B9*1000) -> 318181.82
A23: Cliques — Meta | B23: =B22*B10 -> 5090.9091
A24: Pedidos — Meta | B24: =B23*B11 -> 76.363636
A25: Cliques — Google | B25: =IF(B12=0,0,B21/B12) -> 1200
A26: Pedidos — Google | B26: =B25*B13 -> 26.4
A27: Pedidos totais | B27: =B24+B26 -> 102.76364
A28: CAC médio | B28: =IF(B27=0,"—",B7/B27) -> 97.310686 | C28: Custo de aquisição por cliente.
A29: Receita gerada | B29: =B27*B5 -> 17459.542
A30: ROAS realizado | B30: =IF(B7=0,0,B29/B7) -> 1.7459542
A31: Resultado após mídia | B31: =B27*B18-B7 -> -4012.8374 | C31: Negativo: a primeira compra não paga a aquisição.
A32: LTV em 12 meses | B32: =B18*(1+B14*B15) -> 86.80962 | C32: Margem da primeira compra mais a das recompras.
A33: LTV ÷ CAC | B33: =IF(OR(B27=0,B7=0),"—",B32/(B7/B27)) -> 0.89208722 | C33: A regra de mercado é no mínimo 3,0×.
A35: Veredito | B35: =IF(B31>=0,"A mídia se paga na primeira compra","A mídia NÃO se paga na primeira compra") -> A mídia NÃO se paga na primeira compra

Sheet Taxas 2026
A1: TABELAS DE REFERÊNCIA — VIGENTES EM OUTUBRO DE 2026
A2: As faixas numéricas da Shopee e do TikTok Shop alimentam a Calculadora, Kits calculo e Tabela de Precos.
A4: MERCADO LIVRE — CATEGORIA MODA
A5: Tipo de anúncio | B5: Comissão | C5: Custo adicional | D5: Observação
A6: Clássico | B6: 0.14 | C6: — | D6: Parcelamento sem juros limitado. Menor taxa, menor exposição.
A7: Premium | B7: 0.19 | C7: — | D7: 12x sem juros e mais exposição na busca.
A8: Preço abaixo de R$ 79 | B8: — | C8: custo logístico | D8: Desde 02/03/2026 a taxa fixa virou custo operacional por peso (aba Frete 2026, coluna B). O ML banca o frete do comprador a partir de R$ 19.
A9: Preço a partir de R$ 79 | B9: — | C9: frete grátis | D9: Frete grátis obrigatório pago pelo vendedor pela tabela de reputação (aba Frete 2026). Reputação vermelha paga o dobro da verde.
A13: SHOPEE — TABELA DE MARÇO DE 2026 (COBRADA POR ITEM; O KIT É UM ITEM)
A14: Faixa de preço | B14: A partir de (R$) | C14: Comissão | D14: Taxa fixa por item | E14: Observação
A15: Abaixo de R$ 8 | B15: 0 | C15: 0.5 | D15: 0 | E15: Faixa punitiva.
A16: De R$ 8 a R$ 79,99 | B16: 8 | C16: 0.2 | D16: 4 | E16: A pior faixa para ticket baixo: 20% mais R$ 4.
A17: De R$ 80 a R$ 99,99 | B17: 80 | C17: 0.14 | D17: 16 | E17: A comissão cai, mas a taxa fixa sobe muito: evite esta faixa.
A18: De R$ 100 a R$ 199,99 | B18: 100 | C18: 0.14 | D18: 20 | E18: Faixa do kit de 3 a R$ 169,90.
A19: R$ 200 ou mais | B19: 200 | C19: 0.14 | D19: 26 | E19: Sem teto de comissão desde março de 2026.
A20: O Programa de Frete Grátis ficou obrigatório em março de 2026 e está embutido na comissão. Vendedores CPF com mais de 450 pedidos em 90 dias pagam R$ 3 a mais por item.
A22: TIKTOK SHOP — TABELA DE 15 DE JULHO DE 2026
A23: Faixa de preço | B23: A partir de (R$) | C23: Comissão | D23: Taxa fixa por item | E23: Observação
A24: Abaixo de R$ 50 | B24: 0 | C24: 0.1 | D24: 0 | E24: A comissão subiu de 6% para 10% nesta faixa.
A25: R$ 50 ou mais | B25: 50 | C25: 0.06 | D25: 6 | E25: A taxa fixa subiu de R$ 4 para R$ 6.
A26: Programa de frete grátis: 6% sobre o produto (inalterado). Comissão de afiliado: de 10% a 20% em roupas, definida pelo vendedor. Ambos em Premissas.
A28: SIMPLES NACIONAL 2026 — ALÍQUOTAS NOMINAIS
A29: Receita bruta em 12 meses | B29: Anexo I · Comércio | C29: Anexo II · Indústria | D29: Parcela a deduzir | E29: Observação
A30: Até R$ 180.000 | B30: 0.04 | C30: 0.045 | D30: —
A31: De R$ 180.000 a R$ 360.000 | B31: 0.073 | C31: 0.078 | D31: R$ 5.940
A32: De R$ 360.000 a R$ 720.000 | B32: 0.095 | C32: 0.1 | D32: R$ 13.860
A33: De R$ 720.000 a R$ 1.800.000 | B33: 0.107 | C33: 0.112 | D33: R$ 22.500
A34: De R$ 1.800.000 a R$ 3.600.000 | B34: 0.143 | C34: 0.147 | D34: I: R$ 87.300 · II: R$ 85.500
A35: De R$ 3.600.000 a R$ 4.800.000 | B35: 0.19 | C35: 0.3 | D35: I: R$ 378.000 · II: R$ 720.000
A36: Alíquota efetiva = [(RBT12 × nominal) − parcela a deduzir] ÷ RBT12. Reforma tributária: 2026 é ano de teste (CBS 0,9%, IBS 0,1%) sem efeito no DAS. A opção de IBS e CBS fora do DAS para o 1º semestre de 2027 foi de 1º a 30/09/2026 (Resolução CGSN nº 186/2026) e pode ser cancelada até 30/11/2026, de forma irretratável; a próxima janela é março de 2027.
A38: MÍDIA E DEVOLUÇÃO — REFERÊNCIAS DE 2026
A39: Indicador | B39: Faixa | C39: Fonte | D39: Observação
A40: CPM Meta — Feed | B40: R$ 15 a R$ 35 | C40: Benchmarks Brasil 2026 | D40: —
A41: CPM Meta — Stories e Reels | B41: R$ 8 a R$ 20 | C41: Benchmarks Brasil 2026 | D41: Mais barato, exige criativo em vídeo.
A42: CPC Google — moda | B42: R$ 1,50 a R$ 4,00 | C42: Benchmarks Brasil 2026 | D42: Média geral da Rede de Pesquisa perto de R$ 2,50.
A43: ROAS mediano — e-commerce | B43: 1,93× | C43: Benchmarks por indústria | D43: Mediana de mercado em Meta Ads.
A44: Aumento de custo do Meta Ads | B44: 12,15% | C44: Repasse de 01/01/2026 | D44: PIS/Cofins de 9,25% e ISS de 2,9%.
A45: Devolução em moda online | B45: 30% a 40% | C45: E-commerce Brasil 2026 | D45: Tamanho errado responde por mais da metade dos casos.
A46: Recompra sem retenção | B46: 15% a 25% | C46: Benchmarks de varejo | D46: Com fidelidade e e-mail: 35% a 50%.
